Workbook

Sheet Fields&Module
A1: 0 | B1: 0 | D1: LIFE | H1: GENERAL | L1: Y/N | M1: Freq | N1: MOP | O1: TableName > | P1: Policy | Q1: Schedule | R1: PayPlan | S1: Debit Notes | T1: Payments | U1: Vehicles | V1: Nominee | W1: ComNotes | X1: ComPay | Y1: Statement | Z1: Endorsements | AA1: R-Notices | AB1: Client | AC1: BO | AD1: Contact | AE1: FU | AF1: Proposals | AG1: Tasks | AH1: Claims | AI1: Income | AJ1: Expenses | AK1: Tax
A2: 1 | B2: 0 | H2: Field Name | I2: =SUM(I3:I201) -> 0 | J2: Field Type | K2: Default | L2: =SUM(L32:L292) -> 3 | M2: =SUM(M32:M292) -> 4 | N2: =SUM(N32:N292) -> 2 | O2: No Of Fields > | P2: =SUM(P3:P307) -> 19 | Q2: =SUM(Q3:Q307) -> 14 | R2: =SUM(R3:R307) -> 9 | S2: =SUM(S3:S307) -> 5 | T2: =SUM(T3:T307) -> 11 | U2: =SUM(U3:U307) -> 19 | V2: =SUM(V3:V307) -> 11 | W2: =SUM(W3:W307) -> 6 | ... AK2: =SUM(AK3:AK307) -> 16 | AL2: =SUM(P2:AK2) -> 289
A3: 1 | B3: 1 | C3: Policy | D3: PolicyID | H3: PolicyID | J3: UniqueID | P3: 1
A4: 2 | B4: 2 | C4: Policy | D4: ClientID | H4: ClientID | J4: Unique ID | P4: 1
A5: 3 | B5: 3 | C5: Policy | D5: Policy No | H5: Policy No | J5: UniqueNo | P5: 1
A6: 4 | B6: 4 | C6: Policy | D6: Insurer | H6: Insurer | J6: LookUp Table | P6: 1
A7: 5 | B7: 5 | C7: Policy | D7: Class | H7: Class | J7: LookUp Table | P7: 1
A8: 6 | B8: 6 | C8: Policy | H8: Insured | J8: Text | P8: 1
A9: 6 | B9: 6 | C9: Policy | D9: Policy Type | J9: LookUp Table | P9: 1
A10: 7 | B10: 7 | C10: Policy | D10: Application Date | H10: Application Date | J10: Date | K10: [Today] | P10: 1
A11: 8 | B11: 8 | C11: Policy | D11: Business | H11: Business | J11: LookUp Table | K11: Direct | P11: 1
A12: 9 | B12: 9 | C12: Policy | D12: PolicyStatus | H12: PolicyStatus | J12: Derived | K12: In Force | P12: 1
A13: 10 | B13: 10 | C13: Policy | D13: RenewalNotices | H13: RenewalNotices | J13: Check Box | P13: 1
A14: 11 | B14: 11 | C14: Policy | D14: Channel | H14: Channel | J14: LookUp Table | P14: 1
A15: 12 | B15: 12 | C15: Policy | D15: DFR | H15: DFR | J15: Highlight | K15: Off | L15: 1 | P15: 1
A16: 13 | B16: 13 | C16: Policy | D16: Agency | H16: Agency | J16: LookUp Table | K16: Keystone | P16: 1
A17: 14 | B17: 14 | C17: Policy | D17: Agent | H17: Agent | J17: Text | K17: Mandy | P17: 1
A18: 15 | B18: 15 | C18: Policy | D18: Source | H18: Source | J18: LookUp Table | P18: 1
A19: 16 | B19: 16 | C19: Policy | D19: Source Name | H19: Source Name | J19: Text | P19: 1
A20: 17 | B20: 17 | C20: Policy | D20: Notes | H20: Notes | J20: Text | P20: 1
A21: 18 | B21: 18 | C21: Policy | D21: [Documents] | H21: [Documents] | J21: Attachment | P21: 1
A22: 19 | B22: 1 | C22: Schedule | D22: ScheduleID | H22: ScheduleID | J22: Unique ID | Q22: 1
A23: 20 | B23: 2 | C23: Schedule | D23: PolicyID | H23: PolicyID | J23: Unique ID | Q23: 1
A24: 21 | B24: 3 | C24: Schedule | D24: Year | H24: Year | J24: Numbers | K24: [Current] | Q24: 1
A25: 22 | B25: 4 | C25: Schedule | D25: Plan | H25: Plan | J25: Text | Q25: 1
A26: 23 | B26: 5 | C26: Schedule | D26: Sum Assured | H26: SumInsured | J26: Currency | Q26: 1
A27: 25 | B27: 7 | C27: Schedule | D27: Term [No] | H27: Term [No] | J27: Numbers | K27: 1 | Q27: 1
A28: 26 | B28: 8 | C28: Schedule | D28: Term [Period] | H28: Term [Period] | J28: LookUp Table | K28: Year | Q28: 1
A29: 27 | B29: 9 | C29: Schedule | D29: StartDate | H29: StartDate | J29: Date | K29: [Today] | Q29: 1
A30: 28 | B30: 10 | C30: Schedule | D30: End Date | H30: End Date | J30: Date | K30: Calculated | Q30: 1
A31: 29 | B31: 11 | C31: Schedule | D31: Cancelled Date | H31: Cancelled Date | J31: Date | Q31: 1
A32: 30 | B32: 12 | C32: Schedule | D32: AddONs | H32: AddONs | J32: Text | Q32: 1
A33: 31 | B33: 13 | C33: Schedule | D33: BasePremium | H33: BasePremium | J33: Currency | Q33: 1
A34: 32 | B34: 14 | C34: Schedule | D34: TotalPremium | H34: TotalPremium | J34: Currency | Q34: 1
A35: 33 | B35: 15 | C35: Schedule | D35: [Documents] | H35: [Documents] | J35: Attachment | M35: 1 | Q35: 1
A36: 35 | B36: 1 | C36: PayPlan | D36: PayPlanID | H36: PayPlanID | J36: Unique ID | R36: 1
A37: 36 | B37: 2 | C37: PayPlan | D37: ScheduleID | H37: ScheduleID | J37: Unique ID | R37: 1
A38: 37 | B38: 3 | C38: PayPlan | D38: PaymentPlan | H38: PaymentPlan | J38: LookUp Table | K38: Single | R38: 1
A39: 38 | B39: 4 | C39: PayPlan | D39: No Of Instalments | H39: No Of Instalments | J39: Numbers | K39: 1 | R39: 1
A40: 39 | B40: 5 | C40: PayPlan | D40: Frequency | H40: Frequency | J40: LookUp Table | R40: 1
A41: 40 | B41: 6 | C41: PayPlan | D41: StartDate | H41: StartDate | J41: Date | K41: [Policy Start Date] | R41: 1
A42: 41 | B42: 7 | C42: PayPlan | D42: StopDate | H42: StopDate | J42: Date | R42: 1
A43: 42 | B43: 8 | C43: PayPlan | D43: MOP | H43: MOP | J43: LookUp Table | N43: 1 | R43: 1
A44: 43 | B44: 9 | C44: PayPlan | D44: SOP | H44: SOP | J44: Text | M44: 1 | R44: 1
A45: 44 | B45: 1 | C45: DebitNote | H45: DNID | J45: Unique ID | S45: 1
A46: 45 | B46: 2 | C46: DebitNote | H46: PayPlanID | J46: Unique ID | S46: 1
A47: 46 | B47: 3 | C47: DebitNote | H47: DueAmount | J47: Currency | K47: Calculated | S47: 1
A48: 47 | B48: 4 | C48: DebitNote | H48: DueDate | J48: Date | K48: Derived | S48: 1
A49: 48 | B49: 5 | C49: DebitNote | H49: PaymentStatus | J49: LookUp Table | K49: Derived | S49: 1
A50: 49 | B50: 1 | C50: Payment | H50: PaymentID | J50: Unique ID | T50: 1
A51: 50 | B51: 2 | C51: Payment | H51: DNID | J51: Unique ID | T51: 1
A52: 51 | B52: 3 | C52: Payment | H52: PayDate | J52: Date | T52: 1
A53: 52 | B53: 4 | C53: Payment | H53: PayAmount | J53: Currency | T53: 1
A54: 53 | B54: 5 | C54: Payment | H54: PaymentType | J54: LookUp Table | T54: 1
A55: 54 | B55: 6 | C55: Payment | H55: PayMethod | J55: LookUp Table | T55: 1
A56: 55 | B56: 7 | C56: Payment | H56: ChqDetails | J56: Text | N56: 1 | T56: 1
A57: 56 | B57: 8 | C57: Payment | H57: Receipt No | J57: Text | T57: 1
A58: 57 | B58: 9 | C58: Payment | H58: PayNotes | J58: Text | T58: 1
A59: 58 | B59: 10 | C59: Payment | H59: Variance | J59: Currency | K59: Calculated | T59: 1
A60: 59 | B60: 11 | C60: Payment | H60: Variance Reason | J60: Text | T60: 1
A61: 60 | B61: 1 | C61: Vehicle | H61: VehicleID | J61: Unique ID | U61: 1
A62: 61 | B62: 2 | C62: Vehicle | H62: PolicyID | J62: Unique ID | U62: 1
A63: 62 | B63: 3 | C63: Vehicle | H63: Regn No | J63: Text | U63: 1
A64: 63 | B64: 4 | C64: Vehicle | H64: Make | J64: Text [Dynamic] | U64: 1
A65: 64 | B65: 5 | C65: Vehicle | H65: Model | J65: Text [Dynamic] | U65: 1
A66: 65 | B66: 6 | C66: Vehicle | H66: Year | J66: LookUp Table | U66: 1
A67: 66 | B67: 7 | C67: Vehicle | H67: VehicleType | J67: Text [Dynamic] | U67: 1
A68: 67 | B68: 8 | C68: Vehicle | H68: Seating | J68: Number | U68: 1
A69: 68 | B69: 9 | C69: Vehicle | H69: Color | J69: Text | U69: 1
A70: 69 | B70: 10 | C70: Vehicle | H70: Engine Type | J70: LookUp Table | U70: 1
A71: 70 | B71: 11 | C71: Vehicle | H71: Engine CC | J71: Number | U71: 1
A72: 71 | B72: 12 | C72: Vehicle | H72: Engine No | J72: Text | U72: 1
... A79: 78 | B79: 13 | C79: Vehicle | H79: [Documents] | J79: Attachment | U79: 1
A80: 79 | B80: 1 | C80: Nominee | H80: NomineeID | J80: Unique ID | V80: 1
A81: 80 | B81: 2 | C81: Nominee | H81: PolicyID | J81: Unique ID | V81: 1
A82: 81 | B82: 3 | C82: Nominee | H82: Name | J82: Text | V82: 1
A83: 82 | B83: 4 | C83: Nominee | H83: DOB | J83: Date | V83: 1
A84: 83 | B84: 6 | C84: Nominee | H84: NIN | J84: Text | V84: 1
A85: 84 | B85: 5 | C85: Nominee | H85: Relationship | J85: Text | V85: 1
A86: 85 | B86: 7 | C86: Nominee | H86: Share | J86: Number | V86: 1
A87: 86 | B87: 8 | C87: Nominee | H87: DateAdded | J87: Date | V87: 1
A88: 87 | B88: 9 | C88: Nominee | H88: DateRemoved | J88: Date | V88: 1
A89: 88 | B89: 10 | C89: Nominee | H89: Comment | J89: Text | V89: 1
A90: 89 | B90: 11 | C90: Nominee | H90: [IDs) | J90: Attachment | V90: 1
A91: 90 | B91: 1 | C91: ComNote | H91: PolicyID | J91: Unique ID | W91: 1
A92: 91 | B92: 2 | C92: ComNote | H92: ScheduleID | J92: Unique ID | W92: 1
A93: 92 | B93: 3 | C93: ComNote | H93: Rate | J93: Percentage | W93: 1
A94: 93 | B94: 4 | C94: ComNote | H94: Amount Due | J94: Currency | K94: Calculated | W94: 1
A95: 94 | B95: 5 | C95: ComNote | H95: Date Due | J95: Date | W95: 1
A96: 95 | B96: 6 | C96: ComNote | H96: CommissionStatus | J96: LookUp Table | K96: Derived | W96: 1
A97: 96 | B97: 1 | C97: ComPay | H97: ComPayID | J97: Unique ID | X97: 1
A98: 97 | B98: 2 | C98: ComPay | H98: CNID | J98: Unique ID | X98: 1
A99: 98 | B99: 3 | C99: ComPay | H99: =H106 -> StatementID | J99: Unique ID | X99: 1
A100: 99 | B100: 4 | C100: ComPay | H100: Com Status | J100: LookUp Table | K100: Derived | X100: 1
A101: 100 | B101: 5 | C101: ComPay | H101: Amount Received | J101: Currency | X101: 1
A102: 101 | B102: 6 | C102: ComPay | H102: Variance | J102: Currency | K102: Calculated | X102: 1
A103: 102 | B103: 7 | C103: ComPay | H103: Variance Reason | J103: Text | X103: 1
A104: 103 | B104: 6 | C104: ComPay | H104: Type Received | J104: LookUp Table | X104: 1
A105: 104 | B105: 7 | C105: ComPay | H105: Com Notes | J105: Text | X105: 1
A106: 105 | B106: 1 | C106: ComStatement | H106: StatementID | J106: Unique ID | Y106: 1
...

Sheet Login

Sheet Template

Sheet System DB
B2: CLIENTS | E2: POLICIES MANAGEMENT | T2: PREMIUM PAYMENTS MANAGEMENT | AF2: LEADS & LIFE INSURANCE
AB4: PAYMENTS | AJ4: PROPOSALS
X5: DEBIT NOTES | AB5: PaymentID | AF5: CONTACTS | AJ5: PRID | AK5: 1
T6: PAYMENTPLAN | X6: DebitNoteID | Y6: 1 | AA6: M | AB6: =X6 -> DebitNoteID | AF6: ContactID | AG6: 1 | AI6: M | AJ6: =AF6 -> ContactID
P7: SCHEDULES | T7: PayPlanID | U7: 1 | W7: M | X7: =T7 -> PayPlanID
E8: POLICIES | P8: ScheduleID | Q8: 1 | S8: M | T8: =P8 -> ScheduleID
B9: CLIENTS | E9: PolicyID | F9: 1 | O9: M | P9: =E9 -> PolicyID | AJ9: MEDICALS
B10: Client ID | C10: 1 | D10: M | E10: =B10 -> Client ID | P10: Attachments | AF10: FOLLOWUPS | AJ10: MedID
B11: ClientType* | E11: PolicyNO | L11: RENEWALNotices | P11: DebitNote | AF11: FUID | AJ11: =AJ5 -> PRID | AK11: 1
B12: Name | L12: RNID | P12: Receipt | AF12: =AF6 -> ContactID | AG12: M
E13: Attachments | K13: M | L13: =E9 -> PolicyID | P13: PolicySchedule | T13: COMMISSION MANAGEMENT | AF13: =B10 -> Client ID
B14: Attachments | E14: Proposal Form | P14: RenewalNotice | AF14: =AJ5 -> PRID
B15: ID | E15: Vehicle RC | P15: Payment Agreement
B16: POA | E16: Quotes | X16: COMMISSIONS
B17: BusinessDocs | E17: QS Reports | L17: VEHICLES | T17: Com NOTE | X17: ComID
E18: Photos | L18: VehicleID | T18: ComNoteID | U18: 1 | W18: M | X18: =T18 -> ComNoteID | AB18: COMStatement | AF18: FINANCIAL MANAGEMENT
L19: =E9 -> PolicyID | S19: 1 | T19: =P8 -> ScheduleID | X19: =AB19 -> ComStatID | Y19: M | AA19: 1 | AB19: ComStatID | AC19: 1
E20: CLAIMS | L20: RegnNo | AB20: Attachments
B21: BeneficialOwners | E21: ClaimID | AB21: ComStat | AF21: INCOME | AJ21: TAX RETURN
B22: BOID | E22: =E9 -> PolicyID | F22: M | L22: Attachments | AF22: IncomeID | AJ22: TaxRetID
B23: =B10 -> Client ID | C23: M | E23: Attachments | L23: SLTA Certificate | AE23: 1 | AF23: =AB19 -> ComStatID
B24: Name | E24: ClaimForm | L24: Proof Of Purchase | AF24: Attachments
E25: Other Docs | L25: Value Certificate | T25: OTHER MODULES | AF25: Bank Statements
B26: Attachments
B27: ID | E27: NOMINEES | L27: ENDORSEMENTS
B28: POA | E28: NomineeID | L28: EndorseID | T28: SYSTEM | X28: DOCUMENTS | AB28: NOTIFICATIONS | AF28: EXPENSES
E29: =E9 -> PolicyID | F29: M | L29: =E9 -> PolicyID | AF29: ExpensesID
E30: Name | AF30: Attachments
E31: Attachments | AF31: Receipts
E32: IDS | T32: CALENDAR | X32: REPORTS | AB32: TASKS

Sheet P1
E2: POLICIES MANAGEMENT | T2: PREMIUM PAYMENTS MANAGEMENT
AB4: PAYMENTS
X5: DEBIT NOTES | AB5: PaymentID
T6: PAYMENTPLAN | X6: DebitNoteID | Y6: 1 | AA6: M | AB6: =X6 -> DebitNoteID
P7: SCHEDULES | T7: PayPlanID | U7: 1 | W7: M | X7: =T7 -> PayPlanID
E8: POLICIES | P8: ScheduleID | Q8: 1 | S8: M | T8: =P8 -> ScheduleID
E9: PolicyID | F9: 1 | O9: M | P9: =E9 -> PolicyID
E10: Client ID | P10: Attachments
E11: PolicyNO | L11: RENEWALNotices | P11: DebitNote
L12: RNID | P12: Receipt
E13: Attachments | K13: M | L13: =E9 -> PolicyID | P13: PolicySchedule
E14: Proposal Form | P14: RenewalNotice
E15: Vehicle RC | P15: Payment Agreement
E16: Quotes
E17: QS Reports
E18: Photos
T28: SYSTEM | X28: DOCUMENTS | AB28: NOTIFICATIONS

Sheet P2
E2: POLICIES MANAGEMENT | T2: PREMIUM PAYMENTS MANAGEMENT
AB4: PAYMENTS
X5: DEBIT NOTES
T6: PAYMENTPLAN | Y6: 1 | AA6: M
P7: SCHEDULES | U7: 1 | W7: M
E8: POLICIES | Q8: 1 | S8: M
F9: 1 | O9: M
L11: RENEWALNotices
T13: COMMISSION MANAGEMENT
X16: COMMISSIONS
T17: Com NOTE | X17: ComID
T18: ComNoteID | U18: 1 | W18: M | X18: =T18 -> ComNoteID | AB18: COMStatement
S19: 1 | T19: ScheduleID | X19: =AB19 -> ComStatID | Y19: M | AA19: 1 | AB19: ComStatID
AB20: Attachments
AB21: ComStat
T28: SYSTEM | X28: DOCUMENTS | AB28: NOTIFICATIONS

Sheet P3
B2: CLIENTS | E2: POLICIES MANAGEMENT | T2: PREMIUM PAYMENTS MANAGEMENT
AB4: PAYMENTS
X5: DEBIT NOTES
T6: PAYMENTPLAN | Y6: 1 | AA6: M
P7: SCHEDULES | U7: 1 | W7: M
E8: POLICIES | Q8: 1 | S8: M
B9: CLIENTS | E9: PolicyID | F9: 1 | O9: M
B10: Client ID | C10: 1 | D10: M | E10: Client ID
B11: ClientType* | L11: RENEWALNotices
B12: Name
K13: M | T13: COMMISSION MANAGEMENT
B14: Attachments
B15: ID
B16: POA | X16: COMMISSIONS
B17: BusinessDocs | T17: Com NOTE
U18: 1 | W18: M | AB18: COMStatement
S19: 1 | Y19: M | AA19: 1
B21: BeneficialOwners
B22: BOID
B23: =B10 -> Client ID | C23: M
B24: Name
B26: Attachments
B27: ID
B28: POA | T28: SYSTEM | X28: DOCUMENTS | AB28: NOTIFICATIONS

Sheet P4
E2: POLICIES MANAGEMENT | T2: PREMIUM PAYMENTS MANAGEMENT
AB4: PAYMENTS
X5: DEBIT NOTES
T6: PAYMENTPLAN | Y6: 1 | AA6: M
P7: SCHEDULES | U7: 1 | W7: M
E8: POLICIES | Q8: 1 | S8: M
B9: CLIENTS | E9: PolicyID | F9: 1 | O9: M
C10: 1 | D10: M
L11: RENEWALNotices
T13: COMMISSION MANAGEMENT
X16: COMMISSIONS
L17: VEHICLES | T17: Com NOTE
L18: VehicleID | U18: 1 | W18: M | AB18: COMStatement
L19: PolicyID | S19: 1 | Y19: M | AA19: 1
E20: CLAIMS | L20: RegnNo
B21: BeneficialOwners | E21: ClaimID
E22: PolicyID | F22: M | L22: Attachments
C23: M | E23: Attachments | L23: SLTA Certificate
E24: ClaimForm | L24: Proof Of Purchase
E25: Other Docs | L25: Value Certificate
L27: ENDORSEMENTS
L28: EndorseID | T28: SYSTEM | X28: DOCUMENTS | AB28: NOTIFICATIONS
L29: PolicyID

Sheet P5
E2: POLICIES MANAGEMENT | T2: PREMIUM PAYMENTS MANAGEMENT | AF2: LEADS & LIFE INSURANCE
AB4: PAYMENTS | AJ4: PROPOSALS
X5: DEBIT NOTES | AF5: CONTACTS | AJ5: PRID | AK5: 1
T6: PAYMENTPLAN | Y6: 1 | AA6: M | AF6: ContactID | AG6: 1 | AI6: M | AJ6: =AF6 -> ContactID
P7: SCHEDULES | U7: 1 | W7: M
E8: POLICIES | Q8: 1 | S8: M
B9: CLIENTS | F9: 1 | O9: M | AJ9: MEDICALS
C10: 1 | D10: M | AF10: FOLLOWUPS | AJ10: MedID
L11: RENEWALNotices | AF11: FUID | AJ11: =AJ5 -> PRID | AK11: 1
AF12: =AF6 -> ContactID | AG12: M
T13: COMMISSION MANAGEMENT | AF13: =B10 -> 0
AF14: =AJ5 -> PRID
X16: COMMISSIONS
L17: VEHICLES | T17: Com NOTE
U18: 1 | W18: M | AB18: COMStatement
S19: 1 | Y19: M | AA19: 1
E20: CLAIMS
B21: BeneficialOwners
F22: M
C23: M
E27: NOMINEES | L27: ENDORSEMENTS
E28: NomineeID | T28: SYSTEM | X28: DOCUMENTS | AB28: NOTIFICATIONS
E29: =E9 -> 0 | F29: M
E30: Name
E31: Attachments
E32: IDS

Sheet P6
E2: POLICIES MANAGEMENT | T2: PREMIUM PAYMENTS MANAGEMENT | AF2: LEADS & LIFE INSURANCE
AB4: PAYMENTS | AJ4: PROPOSALS
X5: DEBIT NOTES | AF5: CONTACTS | AK5: 1
T6: PAYMENTPLAN | Y6: 1 | AA6: M | AG6: 1 | AI6: M
P7: SCHEDULES | U7: 1 | W7: M
E8: POLICIES | Q8: 1 | S8: M
B9: CLIENTS | F9: 1 | O9: M | AJ9: MEDICALS
C10: 1 | D10: M | AF10: FOLLOWUPS
L11: RENEWALNotices | AK11: 1
AG12: M
T13: COMMISSION MANAGEMENT
X16: COMMISSIONS
L17: VEHICLES | T17: Com NOTE
U18: 1 | W18: M | AB18: COMStatement
S19: 1 | Y19: M | AA19: 1
E20: CLAIMS
B21: BeneficialOwners
F22: M
C23: M
L27: ENDORSEMENTS
T28: SYSTEM | X28: DOCUMENTS | AB28: NOTIFICATIONS
AB32: TASKS

Sheet P7
E2: POLICIES MANAGEMENT | T2: PREMIUM PAYMENTS MANAGEMENT | AF2: LEADS & LIFE INSURANCE
AB4: PAYMENTS | AJ4: PROPOSALS
X5: DEBIT NOTES | AF5: CONTACTS | AK5: 1
T6: PAYMENTPLAN | Y6: 1 | AA6: M | AG6: 1 | AI6: M
P7: SCHEDULES | U7: 1 | W7: M
E8: POLICIES | Q8: 1 | S8: M
B9: CLIENTS | F9: 1 | O9: M | AJ9: MEDICALS
C10: 1 | D10: M | AF10: FOLLOWUPS
L11: RENEWALNotices | AK11: 1
AG12: M
T13: COMMISSION MANAGEMENT
X16: COMMISSIONS
L17: VEHICLES | T17: Com NOTE
U18: 1 | W18: M | AB18: COMStatement
S19: 1 | Y19: M | AA19: 1
E20: CLAIMS
B21: BeneficialOwners
F22: M
C23: M
L27: ENDORSEMENTS
T28: SYSTEM | X28: DOCUMENTS | AB28: NOTIFICATIONS
X32: REPORTS | AB32: TASKS

Sheet P8
E2: POLICIES MANAGEMENT | T2: PREMIUM PAYMENTS MANAGEMENT | AF2: LEADS & LIFE INSURANCE
AB4: PAYMENTS | AJ4: PROPOSALS
X5: DEBIT NOTES | AF5: CONTACTS | AK5: 1
T6: PAYMENTPLAN | Y6: 1 | AA6: M | AG6: 1 | AI6: M
P7: SCHEDULES | U7: 1 | W7: M
E8: POLICIES | Q8: 1 | S8: M
B9: CLIENTS | F9: 1 | O9: M | AJ9: MEDICALS
C10: 1 | D10: M | AF10: FOLLOWUPS
L11: RENEWALNotices | AK11: 1
AG12: M
T13: COMMISSION MANAGEMENT
X16: COMMISSIONS
L17: VEHICLES | T17: Com NOTE
U18: 1 | W18: M | AB18: COMStatement
S19: 1 | Y19: M | AA19: 1
E20: CLAIMS
B21: BeneficialOwners
F22: M
C23: M
L27: ENDORSEMENTS
T28: SYSTEM | X28: DOCUMENTS | AB28: NOTIFICATIONS
T32: CALENDAR | X32: REPORTS | AB32: TASKS

Sheet P9
E2: POLICIES MANAGEMENT | T2: PREMIUM PAYMENTS MANAGEMENT | AF2: LEADS & LIFE INSURANCE
AB4: PAYMENTS | AJ4: PROPOSALS
X5: DEBIT NOTES | AF5: CONTACTS | AK5: 1
T6: PAYMENTPLAN | Y6: 1 | AA6: M | AG6: 1 | AI6: M
P7: SCHEDULES | U7: 1 | W7: M
E8: POLICIES | Q8: 1 | S8: M
B9: CLIENTS | F9: 1 | O9: M | AJ9: MEDICALS
C10: 1 | D10: M | AF10: FOLLOWUPS
L11: RENEWALNotices | AK11: 1
AG12: M
T13: COMMISSION MANAGEMENT
X16: COMMISSIONS
L17: VEHICLES | T17: Com NOTE
U18: 1 | W18: M | AB18: COMStatement | AF18: FINANCIAL MANAGEMENT
S19: 1 | Y19: M | AA19: 1 | AC19: 1
E20: CLAIMS
B21: BeneficialOwners | AF21: INCOME | AJ21: TAX RETURN
F22: M | AF22: IncomeID | AJ22: TaxRetID
C23: M | AE23: 1 | AF23: ComStatID
AF24: Attachments
AF25: Bank Statements
L27: ENDORSEMENTS
T28: SYSTEM | X28: DOCUMENTS | AB28: NOTIFICATIONS | AF28: EXPENSES
AF29: ExpensesID
AF30: Attachments
AF31: Receipts
T32: CALENDAR | X32: REPORTS | AB32: TASKS

Sheet Lookups
A2: Contact Type | E2: Client Type | I2: Insurer | M2: Term | Q2: Payment Plan | U2: Claim Stage | Y2: Vehicle Make | AC2: ENDORSEMENT
A3: Seq | B3: Name | C3: Active | E3: Seq | F3: Name | G3: Active | I3: Seq | J3: Name | K3: Active | M3: Seq | N3: Name | O3: Active | Q3: Seq | R3: Name | S3: Active | U3: Seq | V3: Name | W3: Active | Y3: Seq | Z3: Name | AA3: Active | AC3: Seq | AD3: Type | AE3: Description
A4: 1 | B4: Lead | C4: Y | E4: 1 | F4: Individual | G4: Y | I4: 1 | J4: SACOS | K4: Y | M4: 1 | N4: Year | O4: Y | Q4: 1 | R4: Single | S4: Y | U4: 1 | V4: Awaiting Documents | Y4: 1 | Z4: Hyundai | AA4: Y | AC4: 1 | AD4: Renewal | AE4: Policy Renewed
A5: 2 | B5: Prospect | C5: Y | E5: 2 | F5: Business | G5: Y | I5: 2 | J5: HSavy | K5: Y | M5: 2 | N5: Days | O5: Y | Q5: 2 | R5: Split | S5: Y | U5: 2 | V5: Awaiting QS Report | Y5: 2 | Z5: Kia | AA5: Y | AC5: 2 | AD5: Cancelation | AE5: Policy Cancelled
A6: 3 | B6: Contact | C6: Y | E6: 3 | F6: Company | G6: Y | I6: 3 | J6: Alliance | K6: Y | M6: 4 | N6: Weeks | O6: Y | Q6: 3 | R6: Instalments | S6: Y | Y6: 3 | Z6: Suzuki | AA6: Y | AC6: 3 | AD6: Amendment | AE6: Sum Insured Reduced
A7: 4 | B7: SO Bank Officer | C7: Y | E7: 4 | F7: Organization | G7: Y | I7: 4 | J7: MUA | K7: N | Q7: 4 | R7: Regular (Life) | S7: Y | Y7: 4 | Z7: Toyota | AA7: Y | AC7: 4 | AD7: Amendment | AE7: Sum Insured Increased
A8: 5 | B8: Payroll Officer | C8: Y | U8: Claim Status | Y8: 5 | Z8: Ford | AA8: Y | AC8: 5 | AD8: Amendment | AE8: Plan Cover Changed
E9: ID Type | I9: Class | M9: Island | Q9: Mode Of Payment (Life) | U9: Seq | V9: Name | W9: Active | Y9: 6 | Z9: MG | AA9: Y | AC9: 6 | AD9: Amendment | AE9: Beneficary change
E10: Seq | F10: Name | G10: Active | I10: Seq | J10: Name | K10: Active | M10: Seq | N10: Name | O10: Active | Q10: Seq | R10: Name | S10: Active | U10: 1 | V10: Processing | W10: Y | Y10: 7 | Z10: Nissan | AA10: Y | AC10: 7 | AD10: Amendment | AE10: Pay Plan Changed
A11: Contact Stage | E11: 1 | F11: ID Card | G11: Y | I11: 1 | J11: Motor | K11: Y | M11: 1 | N11: Mahe | O11: Y | Q11: 1 | R11: Transfer | S11: Y | U11: 2 | V11: Settled | W11: Y | Y11: 8 | Z11: Mazda | AA11: Y | AC11: 8 | AD11: Amendment | AE11: Vehicle changed
A12: Seq | B12: Name | C12: Active | E12: 2 | F12: Driving License | G12: Y | I12: 2 | J12: General | K12: Y | M12: 2 | N12: Praslin | O12: Y | Q12: 2 | R12: Cheque | S12: Y | U12: 3 | V12: Declined | W12: Y | Y12: 9 | Z12: BMW | AA12: Y
A13: 1 | B13: Open | C13: Y | E13: 3 | F13: Passport | G13: Y | I13: 3 | J13: Life | K13: Y | M13: 3 | N13: La Digue | O13: Y | Q13: 3 | R13: Cash | S13: Y | Y13: 10 | Z13: Mercedes | AA13: Y
A14: 2 | B14: Qualified | C14: Y | E14: 4 | I14: 4 | J14: Bonds | K14: Y | M14: 4 | N14: Perseverance | O14: Y | Q14: 4 | R14: Online | S14: Y | Y14: 11 | Z14: Lexus | AA14: Y | AC14: Source Of Payment
A15: 3 | B15: KIV | C15: Y | I15: 5 | J15: Travel | K15: Y | M15: 5 | N15: Cerf | O15: Y | Q15: 5 | R15: Standing Order | S15: Y | U15: Income Category | Y15: 12 | Z15: Haval | AA15: Y | AC15: Seq | AD15: Source | AE15: Name
A16: 4 | B16: Closed | C16: Y | E16: Monthly Income | I16: 6 | J16: Marine | K16: Y | M16: 6 | N16: Eden | O16: Y | Q16: 6 | R16: Salary Deduction | S16: Y | U16: Seq | V16: Name | W16: Active | Y16: 13 | Z16: Honda | AA16: Y | AC16: 1 | AD16: Direct
E17: Seq | F17: Name | G17: Active | I17: 7 | J17: Health | K17: N | M17: 7 | N17: Silhouette | O17: Y | Q17: 7 | R17: Direect | S17: Y | U17: 1 | V17: Commission | W17: Y | Y17: 10 | Z17: Tata | AA17: Y | AC17: 2 | AD17: Online
A18: Contact Status | E18: 1 | F18: Less than 10,000 | G18: Y | M18: 8 | O18: Y | U18: 2 | V18: Bonus | W18: Y | Y18: 11 | Z18: Isuzu | AA18: Y | AC18: 3 | AD18: Bank | AE18: ABSA
A19: Seq | B19: Name | C19: Active | E19: 2 | F19: 10,001 to 20,000 | G19: Y | I19: Business Type | U19: 3 | V19: Prize | W19: Y | AC19: 4 | AE19: MCB
A20: 1 | B20: Not Contacted | C20: Y | E20: 3 | F20: 20,001 to 30,000 | G20: Y | I20: Seq | J20: Name | K20: Active | M20: Salutation | Q20: Mode Of Payment (General) | U20: 4 | V20: Other | W20: Y | AC20: 5 | AE20: NOU
A21: 2 | B21: Qualified | C21: Y | E21: 4 | F21: 30,001 to 40,000 | G21: Y | I21: 1 | J21: Direct | K21: Y | M21: Seq | N21: Name | O21: Active | Q21: Seq | R21: Name | S21: Active | Y21: Useage | AC21: 6 | AE21: BAR
A22: 3 | B22: Converted to Client | C22: Y | E22: 5 | F22: 40,001 to 50,000 | G22: Y | I22: 2 | J22: Transfer | K22: Y | M22: 1 | N22: Mr | O22: Y | Q22: 1 | R22: Cash | S22: Y | Y22: Seq | Z22: Name | AA22: Active | AC22: 7 | AE22: BOC
A23: 4 | B23: Keep In View | C23: Y | E23: 6 | F23: 50,001 and above | G23: Y | I23: 3 | J23: Renewal | K23: Y | M23: 2 | N23: Ms | O23: Y | Q23: 2 | R23: Card | S23: Y | U23: Expense Category | Y23: 1 | Z23: Private | AA23: Y | AC23: 8 | AE23: SCB
A24: 5 | B24: Archived | C24: Y | M24: 3 | N24: Mrs | O24: Y | Q24: 3 | R24: Transfer | S24: Y | U24: Seq | V24: Name | W24: Active | Y24: 2 | Z24: Commercial | AA24: Y | AC24: 9 | AE24: SCU
I25: Policy Status [Derived] | M25: 4 | N25: Miss | O25: Y | Q25: 4 | R25: Cheque | S25: Y | U25: 1 | V25: License | W25: Y | Y25: 3 | Z25: For Hire | AA25: Y | AC25: 10 | AE25: ASL
E26: Income Source | I26: Seq | J26: Name | K26: Active | M26: 5 | N26: Dr | O26: Y | U26: 2 | V26: Insurance | W26: Y | Y26: 4 | Z26: Carriage Of Goods | AA26: Y | AC26: 11 | AD26: Salary | AE26: AIRTEL
A27: Proposal Stage | E27: Seq | F27: Name | G27: Active | I27: 1 | J27: In Force | K27: Y | M27: 6 | N27: Mr & Mrs | O27: Y | U27: 3 | V27: Office supplies | W27: Y | Y27: 5 | Z27: Commuter | AA27: Y | AC27: 12 | AE27: Cable & Wireless
A28: Seq | B28: Name | C28: Active | E28: 1 | F28: Employment | G28: Y | I28: 2 | J28: Expired | K28: Y | Q28: PaymentType | U28: 4 | V28: Telephone & Internet | W28: Y | AC28: 13 | AE28: Intelvision
A29: 1 | B29: Not Contacted | C29: Y | E29: 2 | F29: Self Employed | G29: Y | I29: 3 | J29: Cancelled | K29: Y | Q29: Seq | R29: Name | S29: Active | U29: 5 | V29: Marketting | W29: Y | AC29: 14 | AE29: PUC
A30: 2 | B30: RNR | C30: Y | E30: 3 | F30: Business | G30: Y | J30: APL | M30: Agency | Q30: 1 | R30: Full | S30: Y | U30: 6 | V30: Travel | W30: Y | Y30: Vehicle Type | AC30: 15 | AE30: SFA
A31: 3 | B31: In Discussion | C31: Y | E31: 4 | F31: Investment | G31: Y | J31: Lapsed | M31: Seq | N31: Name | O31: Active | Q31: 2 | R31: Instalment | S31: Y | U31: 7 | V31: Referals | W31: Y | Y31: Seq | Z31: Name | AA31: Active | AC31: 16 | AE31: STC
A32: 4 | B32: Offer Made | C32: Y | E32: 5 | F32: Rentals | G32: Y | J32: Matured' | M32: 1 | N32: Keystone | O32: Y | Q32: 3 | R32: Adjustment | S32: Y | U32: 8 | V32: Rentals | W32: Y | Y32: 1 | Z32: SUV | AA32: Y | AC32: 17 | AE32: FSA
A33: 5 | B33: Proposal Filled | C33: Y | E33: 6 | F33: Retirement | G33: Y | J33: Surrenders | M33: 2 | N33: LIS | O33: Y | U33: 9 | V33: Vehicle | W33: Y | Y33: 2 | Z33: Hatchback | AA33: Y | AC33: 18 | AE33: Mins Of Education
E34: 7 | F34: Allowance | G34: Y | J34: Payout D | Q34: Payment Status | U34: 10 | V34: Fuel | W34: Y | Y34: 3 | Z34: Sedan | AA34: Y | AC34: 19 | AE34: Mins Of Health
E35: 8 | F35: Other | G35: Y | J35: Payout TPD | M35: Agent | Q35: Seq | R35: Name | S35: Active | U35: 11 | V35: Bank Fees | W35: Y | Y35: 4 | Z35: Twin Cab | AA35: Y | AC35: 20 | AE35: SFRSA
A36: Proposal Status | J36: Null & Void | M36: Seq | N36: Name | O36: Active | Q36: 1 | R36: Paid | S36: Y | U36: 12 | V36: Charges | W36: Y | Y36: 5 | Z36: Pick Up | AA36: Y | AC36: 21 | AE36: Seychelles Police
A37: Seq | B37: Name | C37: Active | M37: 1 | N37: Mandy | O37: Y | Q37: 2 | R37: Partly Paid | S37: Y | U37: 13 | V37: Misc | W37: Y | Y37: 6 | Z37: Scooter | AA37: Y | AC37: 22 | AE37: Treasury
A38: 1 | B38: Awaiting Medical | C38: Y | E38: Ranking | I38: ClientStatus [Derived] | M38: 2 | N38: Simon | O38: Y | Q38: 3 | R38: Unpaid | S38: Y | U38: 14 | V38: Asset Purchase | W38: Y | Y38: 7 | Z38: Motor Cycle | AA38: Y | AC38: 23 | AE38: Judiciary
A39: 2 | B39: Awaiting Policy | C39: Y | E39: Seq | F39: Name | G39: Active | I39: Seq | J39: Name | K39: Active | Y39: 8 | Z39: Taxi | AA39: Y | AC39: 24 | AE39: Pilgrims
A40: 3 | B40: Approved | C40: Y | E40: 1 | F40: VIP | G40: Y | I40: 1 | J40: Active | K40: Y | M40: Issuing Country | Q40: Frequency | Y40: 9 | Z40: Van | AA40: Y | AC40: 25 | AE40: SPTC
A41: 4 | B41: Declined | C41: Y | E41: 2 | F41: High | G41: Y | I41: 2 | J41: Dormant | K41: Y | M41: Seq | N41: Name | O41: Code | Q41: Seq | R41: Name | S41: Active | U41: Engine Type | Y41: 10 | AA41: Y
A42: 5 | B42: Withdrawn | C42: Y | E42: 3 | F42: Medium | G42: Y | M42: 1 | N42: Seychelles | O42: SEY | Q42: 1 | R42: Annual | S42: Y | U42: Seq | V42: Name | W42: Active
E43: 4 | F43: Low | G43: Y | M43: 2 | N43: Great Britain | O43: GBR | Q43: 2 | R43: Singlr | S43: Y | U43: 1 | V43: Hybrid | W43: Y
M44: 3 | N44: Botswana | O44: BOT | Q44: 3 | R44: Monthly | S44: Y | U44: 2 | V44: Petrol | W44: Y | AC44: Commission Rates
M45: 4 | N45: Sri Lanka | O45: SRI | Q45: 4 | R45: Quarterly | S45: Y | U45: 3 | V45: Diesel | W45: Y | AC45: SEQ | AD45: Category | AE45: Insurer | AF45: Start Date | AG45: End date | AH45: Rate
M46: 5 | N46: India | O46: IND | Q46: 5 | R46: Bi-Annual | S46: Y | U46: 4 | V46: Electric | W46: Y | AC46: 1 | AD46: Motor | AE46: Alliance | AF46: 43831 | AG46: 44926 | AH46: 0.1
M47: 6 | N47: Nepal | O47: NEP | AC47: 2 | AE47: Alliance | AF47: 44927 | AH47: 0.11
M48: 7 | N48: Bangladesh | O48: BAN | AC48: 3 | AE48: SACOS | AF48: 43831 | AH48: 0.1
M49: 8 | N49: Russia | O49: RUS | AC49: 4 | AE49: HSavy | AF49: 43831 | AH49: 0.1
M50: 9 | N50: Ukraine | O50: UKR | AC50: 5 | AD50: General | AE50: Alliance | AF50: 43831 | AH50: 0.15
M51: 10 | N51: Kenya | O51: KEN | AC51: 6 | AE51: SACOS | AF51: 43831 | AH51: 0.15
AC52: 7 | AE52: SACOS | AF52: 43831 | AG52: 45657 | AH52: 0.15
AC53: 8 | AE53: HSavy | AF53: 45658 | AH53: 0.17
AC54: 9 | AD54: Bonds | AE54: Alliance | AF54: 43831 | AH54: 0.15
AC55: 10 | AE55: SACOS | AF55: 43831 | AH55: 0.15
AC56: 11 | AE56: HSavy | AF56: 43831 | AH56: 0.15
AC57: 12 | AD57: Travel | AE57: SACOS | AF57: 43831 | AH57: 0.05
AC58: 13 | AE58: HSavy | AF58: 43831 | AH58: 0.15
AC59: 14 | AD59: Marine | AE59: Alliance | AF59: 43831 | AH59: 0.15
AC60: 15 | AE60: SACOS | AF60: 43831 | AH60: 0.15
AC61: 16 | AE61: HSavy | AF61: 43831 | AH61: 0.15
AC62: 17 | AD62: Health | AE62: Alliance | AF62: 43831 | AH62: 0.15
AC63: 18 | AE63: SACOS | AF63: 43831 | AH63: 0.15
AC64: 19 | AE64: HSavy | AF64: 43831 | AH64: 0.15

Sheet Status
B2: POLICIES | E2: CLIENTS | H2: CONTACTS | K2: PROPOSALS (LIFE)
B3: General | C3: Life
B4: Status | C4: Status | E4: Type | F4: Status | H4: Type | I4: Status | K4: Status
H5: Lead | I5: Open | K5: Offer Made
I6: Not Reached | K6: Form Filled
I7: Archived | K7: Awaiting documents
H8: Prospect | I8: In Discussion | K8: Awaiting Deposit
I9: Offer Made | K9: Submitted
I10: Archived | K10: Awaiting Medical
I11: KIV | K11: Awaiting Policy
H12: Contact | I12: Active | K12: Declined
I13: Archived | K13: Withdrawn
K14: Approved
B16: In Force | C16: In Force | E16: Individual | F16: Active
B17: Cancelled | C17: APL | E17: Business
B18: Expired | C18: Matured | E18: Company
B19: Archived | C19: Cancelled | E19: Organisation
C20: Surrendered | E20: Individual | F20: Dormant
C21: TPD Payout | E21: Business
C22: Death Payout | E22: Company
C23: Null & Void | E23: Organisation

Sheet DASH
E2: Dashboard
F6: 1 | I6: 1 | M6: 1 | Q6: 1 | U6: 121 | Y6: 3265.23
D7: Tasks Today | H7: Policies Expiring | L7: Instalments Overdue | P7: IDs Expired | T7: General Policies | X7: Gen-Com Outstanding
F11: 7 | I11: 7 | M11: 11 | Q11: 7 | U11: 239 | Y11: 1
D12: Open Leads | H12: Follow Ups Today | L12: Proposals Pending | Q12: Proposals Processing | U12: Life Policies | X12: Birthdays Today
E16: Income v/s Expense | I16: 2024 | M16: Income | Q16: =I16 -> 2024 | U16: Expenses | Y16: =I16 -> 2024
E18: From : | F18: 45292 | H18: To : | I18: 45657
F19: 253000 | I19: 225023

Sheet CFU
E2: Follow Ups - Contacts
E4: Records Found - 11
F6: Action | G6: Contact Name | H6: Category | I6: Contact No | J6: Date | K6: Time | L6: Type | M6: Assigned | N6: Status | O6: Close Date | P6: Follow Up Notes | Q6: 1st Called | R6: Rank | S6: Next FU | W6: Status | X6: Agency | Y6: Address | Z6: Employer | AA6: Contact ID | AB6: Savings Budget | AC6: Married | AD6: Children | AE6: Children Details | AF6: Vehicle | AG6: House | AH6: Business | AI6: Other
G7: Wanda Lucas | H7: Prospect | I7: 4423212 | J7: =TODAY() -> 45952 | K7: 1000 | L7: Call | M7: Mandy | N7: Not Done | Q7: =TODAY()-7 -> 45945 | R7: Warm | W7: Active | X7: Keystone | Y7: Beau Vallon | Z7: SEYPEC | AA7: LD24-0077
G8: Debra Grey | H8: Lead | I8: 2511611 | J8: =TODAY() -> 45952 | K8: 1000 | L8: Follow Up | M8: Mandy | N8: Not Done | Q8: =TODAY()-9 -> 45943 | R8: Hot | W8: Active | X8: Keystone | Y8: Mont Fleuri | Z8: Cable & Wireless | AA8: LD24-0076
G9: Sheila Ewang | H9: Lead | I9: 2765432 | J9: =TODAY() -> 45952 | K9: 1000 | L9: Follow Up | M9: Mandy | N9: Not Done | Q9: =TODAY()-45 -> 45907 | R9: Warm | W9: Active | X9: Keystone | Y9: Beau Vallon | Z9: AIRTEL | AA9: LD24-0075
G10: Kirk Patrick | H10: Lead | I10: 4373234 | J10: =TODAY() -> 45952 | K10: 1000 | L10: Follow Up | M10: Mandy | N10: Not Done | Q10: =TODAY()-30 -> 45922 | R10: Warm | W10: Active | X10: Keystone | Y10: Cascade | AA10: LD24-0074
G11: Scott Svenson | H11: Lead | I11: 4378645 | J11: =TODAY() -> 45952 | K11: 1000 | L11: Meeting | M11: Mandy | N11: Not Done | Q11: =TODAY()-30 -> 45922 | R11: KIV | W11: In Active | X11: Keystone | Y11: Victoria | AA11: LD24-0073
G12: Samuel Hill | H12: Lead | I12: 2514231 | J12: =TODAY() -> 45952 | K12: 1000 | L12: Follow Up | M12: Mandy | N12: Not Done | Q12: =TODAY()-25 -> 45927 | R12: Warm | W12: Active | Y12: Mont Fleuri | Z12: SPTC | AA12: LD24-0073
G13: Kaste McEwan | H13: Lead | I13: 2765887 | J13: =TODAY() -> 45952 | K13: 1000 | L13: Follow Up | M13: Mandy | N13: Not Done | Q13: 45439 | R13: Warm | W13: Active | X13: Keystone | Y13: Beau Vallon | Z13: Inter Island Boats | AA13: LD24-0072
G14: Mary Trader | H14: Lead | I14: 4373234 | J14: =TODAY()-1 -> 45951 | K14: 1000 | L14: Call | M14: Mandy | N14: Not Done | Q14: 45432 | R14: Warm | W14: Active | X14: Keystone | Y14: Providence | AA14: LD24-0071
G15: Damien Kinmo | H15: Lead | I15: 2787653 | J15: =TODAY()-1 -> 45951 | K15: 1000 | L15: Call | M15: Mandy | N15: Not Done | Q15: 30602 | R15: Warm | W15: Active | X15: Keystone | Y15: Grand Anse | AA15: LD24-0070
G16: Dua Gomez | H16: Lead | I16: 4378645 | J16: =TODAY()-2 -> 45950 | K16: 1000 | L16: Follow Up | M16: Mandy | N16: Not Done | Q16: 45387 | R16: KIV | W16: Active | Y16: Mont Fleuri | Z16: SPTC | AA16: LD24-0073
G17: Cox Santana | H17: Lead | I17: 4378677 | J17: =TODAY()-3 -> 45949 | K17: 1000 | L17: Follow Up | M17: Mandy | N17: Not Done | Q17: 45387 | R17: Warm | W17: Active | X17: Keystone | Y17: Beau Vallon | Z17: Inter Island Boats | AA17: LD24-0072
W18: Active | X18: Keystone | Y18: Providence | AA18: LD24-0071
W19: Active | X19: Keystone | Y19: Grand Anse | AA19: LD24-0070
W20: Active | X20: Keystone | Y20: Anse Aux Pins | Z20: Avani Hotel | AA20: LD24-0069
W21: Active | X21: Keystone | Y21: Grand Anse | AA21: LD24-0070

Sheet UR
E2: Upcoming Renewals
E4: Records 1 to 4 of 4
F6: Action | G6: Policy No | H6: Policy No | I6: Policy No | J6: Client Name | K6: Policy Class | L6: Policy Plan | M6: Insurer | N6: Sum Insured | O6: Premium | P6: Start Date | Q6: End Date | R6: Regn No | S6: Status
G7: 1 | I7: MPV-23-HEA-P0002132 | J7: Jean Grey | K7: Motor | L7: Comprehensive | M7: SACOS | N7: 390000 | O7: 11455.893 | P7: =Q7-365 -> 45592 | Q7: =TODAY()+5 -> 45957 | R7: S44444 | S7: DFR
G8: 2 | I8: HS1-22-HIN-000321 | J8: Tom Thumb | K8: General | L8: House Insurance | M8: Hsavy | N8: 2500000 | O8: =X8*1.16 -> 0 | P8: 45234 | Q8: 45615 | S8: DFR
G9: 3 | I9: PL-22-ALP-000033 | J9: Cornerstone (Pty) Ltd | K9: General | L9: Public Liability | M9: Alliance | N9: 2000000 | O9: =X9*1.16 -> 0 | P9: 45245 | Q9: =TODAY()+9 -> 45961 | S9: DFR
G10: 4 | I10: HS1-23-P00023132 | J10: Cornerstone (Pty) Ltd | K10: General | L10: Employer's Liabilithy | M10: Alliance | N10: 1000000 | O10: 2900 | P10: 45247 | Q10: =TODAY()+9 -> 45961 | S10: DFR

Sheet POD
E2: Premium Overdue
E4: Reocrds Found - 1
F6: Action | G6: Debit Note | H6: Debit Note | I6: Debit Note | J6: Date Due | K6: Amount Due | L6: Status | M6: Policy Number | O6: Client Name
G7: 1 | I7: DN23100 | J7: =TODAY()-1 -> 45951 | K7: 5727.9466 | L7: Unpaid | M7: MPV-23-HEA-P00002132 | O7: Jean Grey

Sheet Pex
E2: Policies Expiring
E4: Records Found - 1 | P4: `
F6: Action | G6: Policy No | H6: Policy No | I6: Policy No | J6: Client Name | K6: Policy Class | L6: Insurer | M6: Insured Item | N6: Regn No | O6: Last Premium | P6: End Date | Q6: Status | R6: Days
G7: 1 | I7: HS1-072-HEA-P0002011 | J7: Basil Walton | K7: General | L7: Hsavy | M7: Residence at Belombre | O7: 5043 | P7: =TODAY() -> 45952 | Q7: =IF(P7<TODAY(),"Expired","") | R7: =P7-TODAY() -> 0

Sheet OL
E2: Open Leads
E4: Records Found - 7
F6: Action | G6: Contact Name | H6: Type | I6: Source | J6: Source Name | K6: Acquired | L6: Aging | M6: Contact No | N6: Occupation | P6: 1st Called | Q6: 2FU | R6: Next FU | S6: Next FU | T6: Ranking | U6: Status | X6: Status | Y6: Agency | Z6: Address | AA6: Employer | AB6: Contact ID | AC6: Savings Budget | AD6: Married | AE6: Children | AF6: Children Details | AG6: Vehicle | AH6: House | AI6: Business | AJ6: Other
G7: Blake Banks | H7: Lead | I7: Direct | K7: =TODAY() -> 45952 | L7: =TODAY()-K7 -> 0 | M7: 2511611 | N7: Accountant | T7: Hot | U7: Open | X7: Active | Y7: Keystone | Z7: Beau Vallon | AA7: SEYPEC | AB7: LD24-0077
G8: Kim Rider | H8: Lead | I8: Referal | J8: Greta Sams | K8: =TODAY() -> 45952 | L8: =TODAY()-K8 -> 0 | M8: 4423212 | N8: Driver | T8: Hot | U8: Open | X8: Active | Y8: Keystone | Z8: Mont Fleuri | AA8: Cable & Wireless | AB8: LD24-0076
G9: Tamara Vincent | H9: Lead | I9: Referal | J9: Greta Sams | K9: =TODAY()-4 -> 45948 | L9: =TODAY()-K9 -> 4 | M9: 2765432 | N9: Customer Service Officer | U9: Open | X9: Active | Y9: Keystone | Z9: Beau Vallon | AA9: AIRTEL | AB9: LD24-0075
G10: Kate Boom | H10: Lead | I10: Referal | J10: Brandon Smith | K10: =TODAY()-4 -> 45948 | L10: =TODAY()-K10 -> 4 | M10: 2876565 | N10: Driver | T10: Warm | U10: Open | X10: Active | Y10: Keystone | Z10: Cascade | AB10: LD24-0074
G11: Ian Dirk | H11: Lead | I11: Referal | J11: Gary Foster | K11: =TODAY()-6 -> 45946 | L11: =TODAY()-K11 -> 6 | M11: 6212143 | N11: Tailor | T11: Warm | U11: Open | X11: In Active | Y11: Keystone | Z11: Victoria | AB11: LD24-0073
G12: Orlando Mendez | H12: Lead | I12: Direct | K12: =TODAY()-4 -> 45948 | L12: =TODAY()-K12 -> 4 | M12: 4323232 | N12: Plumber | U12: Open | X12: Active | Z12: Mont Fleuri | AA12: SPTC | AB12: LD24-0073
G13: Sandra Diaz | H13: Lead | I13: Direct | K13: =TODAY()-6 -> 45946 | L13: =TODAY()-K13 -> 6 | M13: 2786543 | N13: Police Officer | U13: Open | X13: Active | Y13: Keystone | Z13: Beau Vallon | AA13: Inter Island Boats | AB13: LD24-0072
X14: Active | Y14: Keystone | Z14: Providence | AB14: LD24-0071
X15: Active | Y15: Keystone | Z15: Grand Anse | AB15: LD24-0070
X16: Active | Z16: Mont Fleuri | AA16: SPTC | AB16: LD24-0073
X17: Active | Y17: Keystone | Z17: Beau Vallon | AA17: Inter Island Boats | AB17: LD24-0072
X18: Active | Y18: Keystone | Z18: Providence | AB18: LD24-0071
X19: Active | Y19: Keystone | Z19: Grand Anse | AB19: LD24-0070
X20: Active | Y20: Keystone | Z20: Anse Aux Pins | AA20: Avani Hotel | AB20: LD24-0069
X21: Active | Y21: Keystone | Z21: Grand Anse | AB21: LD24-0070

Sheet Cal
E2: Calendar
E5: 2025 | F5: JUNE
E7: MON | F7: TUE | G7: WED | H7: THU | I7: FRI | J7: SAT | K7: SUN
E8: 26 | F8: 27 | G8: 28 | H8: 29 | I8: 30 | J8: 31 | K8: 1
F9: License Fee
E12: 2 | F12: 3 | G12: 4 | H12: 5 | I12: 6 | J12: 7 | K12: 8
F13: Suesan Voicy | G13: Kevin Minion | H13: Patrick Ewan | I13: Steve Ball
E16: 9 | F16: 10 | G16: 11 | H16: 12 | I16: 13 | J16: 14 | K16: 15
F17: Bruce Terry | H17: Samantha Farley | K17: Jeffery Albany
F18: Hazel Gator | H18: Ellie Bailey
E20: 16 | F20: 17 | G20: 18 | I20: 20 | J20: 21 | K20: 22
H21: Jeffery Albany
H22: Gary Totem
E24: 23 | F24: 24 | G24: 25 | H24: 26 | I24: 27 | J24: 28 | K24: 29
E25: Timothy Charlston | F25: Brandon Yale | G25: Heather Swift
E26: Graham Rust
E28: 30 | F28: 1 | G28: 2 | H28: 3 | I28: 4 | J28: 5 | K28: 6
H29: P.O. Box Rental
H30: Shery Nathan

Sheet CalT
E2: Calendar
E5: 2025 | F5: JUNE
E7: MON | F7: TUE | G7: WED | H7: THU | I7: FRI | J7: SAT | K7: SUN
E8: 26 | F8: 27 | G8: 28 | H8: 29 | I8: 30 | J8: 31 | K8: 1
F9: License Fee
E12: 2 | F12: 3 | G12: 4 | H12: 5 | I12: 6 | J12: 7 | K12: 8
E16: 9 | F16: 10 | G16: 11 | H16: 12 | I16: 13 | J16: 14 | K16: 15
E20: 16 | F20: 17 | G20: 18 | I20: 20 | J20: 21 | K20: 22
E24: 23 | F24: 24 | G24: 25 | H24: 26 | I24: 27 | J24: 28 | K24: 29
E28: 30 | F28: 1 | G28: 2 | H28: 3 | I28: 4 | J28: 5 | K28: 6
H29: P.O. Box Rental

Sheet CalF
E2: Calendar
E5: 2025 | F5: JUNE
E7: MON | F7: TUE | G7: WED | H7: THU | I7: FRI | J7: SAT | K7: SUN
E8: 26 | F8: 27 | G8: 28 | H8: 29 | I8: 30 | J8: 31 | K8: 1
I9: Davis Trent
E12: 2 | F12: 3 | G12: 4 | H12: 5 | I12: 6 | J12: 7 | K12: 8
G13: Kevin Minion | I13: Steve Ball
E16: 9 | F16: 10 | G16: 11 | H16: 12 | I16: 13 | J16: 14 | K16: 15
F17: Bruce Terry | H17: Samantha Farley
F18: Hazel Gator
E20: 16 | F20: 17 | G20: 18 | I20: 20 | J20: 21 | K20: 22
E24: 23 | F24: 24 | G24: 25 | H24: 26 | I24: 27 | J24: 28 | K24: 29
E28: 30 | F28: 1 | G28: 2 | H28: 3 | I28: 4 | J28: 5 | K28: 6

Sheet CalR
E2: Calendar
E5: 2025 | F5: JUNE
E7: MON | F7: TUE | G7: WED | H7: THU | I7: FRI | J7: SAT | K7: SUN
E8: 26 | F8: 27 | G8: 28 | H8: 29 | I8: 30 | J8: 31 | K8: 1
I9: Davis Trent
E12: 2 | F12: 3 | G12: 4 | H12: 5 | I12: 6 | J12: 7 | K12: 8
F13: Suesan Voicy | H13: Patrick Ewan
E16: 9 | F16: 10 | G16: 11 | H16: 12 | I16: 13 | J16: 14 | K16: 15
H18: Ellie Bailey
E20: 16 | F20: 17 | G20: 18 | I20: 20 | J20: 21 | K20: 22
H21: Gary Totem
E24: 23 | F24: 24 | G24: 25 | H24: 26 | I24: 27 | J24: 28 | K24: 29
E25: Graham Rust | F25: Brandon Yale | G25: Heather Swift
E28: 30 | F28: 1 | G28: 2 | H28: 3 | I28: 4 | J28: 5 | K28: 6
H29: Shery Nathan

Sheet CalI
E2: Calendar
E5: 2025 | F5: JUNE
E7: MON | F7: TUE | G7: WED | H7: THU | I7: FRI | J7: SAT | K7: SUN
E8: 26 | F8: 27 | G8: 28 | H8: 29 | I8: 30 | J8: 31 | K8: 1
E12: 2 | F12: 3 | G12: 4 | H12: 5 | I12: 6 | J12: 7 | K12: 8
E16: 9 | F16: 10 | G16: 11 | H16: 12 | I16: 13 | J16: 14 | K16: 15
K17: Jeffery Albany
E20: 16 | F20: 17 | G20: 18 | I20: 20 | J20: 21 | K20: 22
H21: Jeffery Albany
E24: 23 | F24: 24 | G24: 25 | H24: 26 | I24: 27 | J24: 28 | K24: 29
E25: Timothy Charlston
E28: 30 | F28: 1 | G28: 2 | H28: 3 | I28: 4 | J28: 5 | K28: 6

Sheet CalB
E2: Calendar
E5: 2025 | F5: JUNE
E7: MON | F7: TUE | G7: WED | H7: THU | I7: FRI | J7: SAT | K7: SUN
E8: 26 | F8: 27 | G8: 28 | H8: 29 | I8: 30 | J8: 31 | K8: 1
I9: Davis Trent
E12: 2 | F12: 3 | G12: 4 | H12: 5 | I12: 6 | J12: 7 | K12: 8
I13: Susan Voysey | K13: Patrick Ewans
E16: 9 | F16: 10 | G16: 11 | H16: 12 | I16: 13 | J16: 14 | K16: 15
G17: Hazel Gator | J17: Samantha Farley
E20: 16 | F20: 17 | G20: 18 | I20: 20 | J20: 21 | K20: 22
J21: Jeffrey Albany
E24: 23 | F24: 24 | G24: 25 | H24: 26 | I24: 27 | J24: 28 | K24: 29
F25: Timothy Charleton | G25: Brandon Yale | I25: Heather Graham
F26: Candy Grallance
E28: 30 | F28: 1 | G28: 2 | H28: 3 | I28: 4 | J28: 5 | K28: 6

Sheet LB
A1: `
E2: Birthday List - December
E4: Records Found - 10
F6: Action | G6: Name | I6: Date Of Birth | J6: Age | K6: Client Status | L6: Mobile No | N6: Contact No | O6: Home No | P6: Email Address | Q6: Medium | R6: Wish Status | S6: Date Done
G7: Davis Trent | I7: 29371 | J7: =(TODAY()-I7)/365 -> 45.427397 | K7: Active | L7: 2713214 | M7: Y | N7: 4232323 | P7: Davis.trent@yahoo.com | Q7: Wattsapp | R7: Not Done
G8: Susan Voysey | I8: 30108 | J8: =(TODAY()-I8)/365 -> 43.408219 | K8: Active | L8: 2511777 | M8: Y | Q8: Wattsapp | R8: Done | S8: 45632
G9: Patrick Ewans | I9: 28284 | J9: =(TODAY()-I9)/365 -> 48.405479 | K9: Active | L9: 2817324 | N9: 2711511 | Q9: SMS | R9: Not Done
G10: Hazel Gator | I10: 32670 | J10: =(TODAY()-I10)/365 -> 36.389041 | K10: Dormant | L10: 2558722 | N10: 4378645 | Q10: SMS | R10: Not Done
G11: Samantha Farley | I11: 32308 | J11: =(TODAY()-I11)/365 -> 37.380822 | K11: Active | L11: 2883204 | N11: 4378645 | P11: sfarley99@gmail.com | Q11: Email | R11: Sent | S11: =I11 -> 32308
G12: Jeffrey Albany | I12: 28662 | J12: =(TODAY()-I12)/365 -> 47.369863 | K12: Active | L12: 2751112 | M12: Y | O12: 4754332 | Q12: Call | R12: Done | S12: =I12 -> 28662
G13: Timothy Charleton | I13: 33779 | J13: =(TODAY()-I13)/365 -> 33.350685 | K13: Active | O13: 4617232 | Q13: Call | R13: No Reply
G14: Candy Grallance | I14: 28665 | J14: =(TODAY()-I14)/365 -> 47.361644 | K14: Active | L14: 2731213 | M14: Y | O14: 4783299 | Q14: Call | R14: Done | S14: =I14 -> 28665
G15: Brandon Yale | I15: 34510 | J15: =(TODAY()-I15)/365 -> 31.347945 | K15: Active | L15: 2563213 | M15: Y | O15: 4612329 | Q15: Call | R15: Done | S15: =I15 -> 34510
G16: Heather Graham | I16: 30860 | J16: =(TODAY()-I16)/365 -> 41.347945 | K16: Active | L16: 2810654 | Q16: SMS | R16: Done | S16: =I16 -> 30860

Sheet LT
A1: `
F2: Tasks
F4: Records Found - 14
E6: No | G6: Action | H6: Task ID | I6: Task ID | J6: Category | K6: Description | L6: Name | M6: Contact No | N6: Due Date | O6: Time | P6: Due in | Q6: Assignee | R6: Task Status | S6: Date Done | T6: Repeat | U6: Frequency | X6: Rpt Date | Y6: Rpt Stop Date | Z6: Task ID
E7: 1 | I7: TK24088 | J7: Payment | K7: P.O. Box Rental | L7: Seychelles Postal Services | M7: 2765997 | N7: =TODAY()+14 -> 45966 | P7: =N7-TODAY() -> 14 | Q7: Mandy | R7: Not Done | T7: Y | U7: Annually | X7: 45701 | Z7: TK24088
E8: 2 | I8: TK24087 | J8: Report | K8: Beneficial Owner Report | L8: FIU | M8: 4282828 | N8: =TODAY()+12 -> 45964 | P8: =N8-TODAY() -> 12 | Q8: Mandy | R8: Not Done | T8: Y | U8: Bi Annually | X8: 45699 | Z8: TK24087
E9: 3 | I9: TK24086 | J9: Payment | K9: Brokers License | L9: FSA | M9: 4378645 | N9: =TODAY()+8 -> 45960 | P9: =N9-TODAY() -> 8 | Q9: Simon | R9: Not Done | T9: Y | U9: Annually | X9: 45695 | Z9: TK24086
E10: 4 | I10: TK24085 | J10: Event | K10: Presentation | L10: Hunt Deltel | M10: 4232323 | N10: =TODAY()+8 -> 45960 | O10: 1600 | P10: 12 | Q10: Mandy | R10: Not Done | T10: N | Z10: TK24085
E11: 5 | I11: TK24084 | J11: Payment | K11: PI Insurance Renewal | L11: Alliance | M11: 4223434 | N11: =TODAY()+7 -> 45959 | P11: =N11-TODAY() -> 7 | Q11: Mandy | R11: Not Done | T11: Y | U11: Annually | X11: 45694 | Z11: TK24084
E12: 6 | I12: TK24083 | J12: Payment | K12: Annual Registration Fee | L12: Registrar Of Companies | M12: 2711511 | N12: =TODAY()+4 -> 45956 | P12: 13 | Q12: Mandy | R12: Not Done | T12: Y | U12: Annually | X12: 45691 | Z12: TK24083
E13: 7 | I13: TK24082 | J13: Report | K13: Financial Audit Report | L13: FSA | M13: 4378645 | N13: =TODAY()+1 -> 45953 | P13: =N13-TODAY() -> 1 | Q13: Simon | R13: Not Done | T13: Y | U13: Annually | X13: 45688 | Z13: TK24082
E14: 8 | I14: TK24081 | J14: Report | K14: Bi Annuall CFT Report | L14: FSA | M14: 4378645 | N14: =TODAY()-3 -> 45949 | P14: =N14-TODAY() -> -3 | Q14: Simon | R14: Not Done | T14: Y | U14: Bi Annually | X14: 45687 | Z14: TK24081
E15: 9 | I15: TK24080 | J15: Report | K15: Tax Return | L15: Seychelles Revenue Commission | M15: 4287555 | N15: =TODAY()-1 -> 45951 | P15: =N15-TODAY() -> -1 | Q15: Simon | R15: In Progress | T15: Y | U15: Annually | X15: 45685 | Z15: TK24080
E16: 10 | I16: TK24079 | J16: Report | K16: Compliance Report | L16: FSA | M16: 4378645 | N16: 45672 | Q16: Mandy | R16: Completed | S16: 45682 | T16: Y | U16: Annually | X16: 45672 | Z16: TK24079
E17: 11 | I17: TK24078 | J17: Payment | K17: Deposit Premium | L17: Randy Crax | M17: 4756599 | N17: 45669 | O17: 1130 | Q17: Simon | R17: Completed | S17: 45669 | T17: N | Z17: TK24078
E18: 12 | I18: TK24077 | J18: Payment | K18: Deposit Premium | L18: Bella Vista | M18: 2727254 | N18: 45664 | Q18: Simon | R18: Completed | S18: 45664 | T18: N | X18: 45664 | Z18: TK24077
E19: 13 | I19: TK24076 | J19: Payment | K19: Deposit Premium | L19: Deep Divers | M19: 2815655 | N19: 45661 | Q19: Simon | R19: Completed | S19: 45661 | T19: N | X19: 45661 | Z19: TK24076
E20: 14 | I20: TK24075 | J20: Meeting | K20: Life Proposal | L20: Sam Anadro | M20: 2711090 | N20: 45651 | O20: 1030 | Q20: Simon | R20: Completed | S20: 46016 | T20: N | Z20: TK24075

Sheet AT
A1: `
E2: Tasks
E4: Records Found - 14
J6: Task ID | K6: Category | L6: Item | M6: Name | N6: Contact No | O6: Reminder | P6: Due Date | Q6: Due in | R6: Assignee | S6: Task Status | T6: Done Date | U6: Repeat | V6: Frequency
J7: TK24088 | K7: Payment | L7: P.O. Box Rental | M7: Seychelles Postal Services | N7: 2765997 | O7: =P7-30 -> 45936 | P7: =TODAY()+14 -> 45966 | Q7: =P7-TODAY() -> 14 | R7: Mandy | S7: Not Done | U7: Y | V7: Annually
J8: TK24087 | K8: Report | L8: Beneficial Owner Report | M8: FIU | N8: 4282828 | O8: =P8-30 -> 45934 | P8: =TODAY()+12 -> 45964 | Q8: =P8-TODAY() -> 12 | R8: Mandy | S8: Not Done | U8: Y | V8: Bi Annually
J9: TK24086 | K9: Payment | L9: Brokers License | M9: FSA | N9: 4378645 | O9: =P9-30 -> 45930 | P9: =TODAY()+8 -> 45960 | Q9: =P9-TODAY() -> 8 | R9: Simon | S9: Not Done | U9: Y | V9: Annually
J10: TK24085 | K10: To Do | L10: Presentation | M10: Hunt Deltel | N10: 4232323 | O10: =P10-30 -> 45930 | P10: =TODAY()+8 -> 45960 | Q10: 12 | R10: Mandy | S10: Not Done | U10: N
J11: TK24084 | K11: Payment | L11: PI Insurance Renewal | M11: Alliance | N11: 4223434 | O11: =P11-30 -> 45929 | P11: =TODAY()+7 -> 45959 | Q11: =P11-TODAY() -> 7 | R11: Mandy | S11: Not Done | U11: Y | V11: Annually
J12: TK24083 | K12: Payment | L12: Annual Registration Fee | M12: Registrar Of Companies | N12: 2711511 | O12: =P12-30 -> 45926 | P12: =TODAY()+4 -> 45956 | Q12: 13 | R12: Mandy | S12: Not Done | U12: Y | V12: Annually
J13: TK24082 | K13: Report | L13: Financial Audit Report | M13: FSA | N13: 4378645 | O13: =P13-30 -> 45923 | P13: =TODAY()+1 -> 45953 | Q13: =P13-TODAY() -> 1 | R13: Simon | S13: Not Done | U13: Y | V13: Annually
J14: TK24081 | K14: Report | L14: Bi Annuall CFT Report | M14: FSA | N14: 4378645 | O14: =P14-30 -> 45922 | P14: =TODAY()+0 -> 45952 | Q14: 14 | R14: Simon | S14: Not Done | U14: Y | V14: Bi Annually
J15: TK24080 | K15: To Do | L15: Tax Return | M15: Seychelles Trevenue Commission | N15: 4287555 | O15: =P15-30 -> 45920 | P15: =TODAY()-2 -> 45950 | Q15: =P15-TODAY() -> -2 | R15: Simon | S15: In Progress | U15: Y | V15: Annually
J16: TK24079 | K16: Report | L16: Compliance Report | M16: FSA | N16: 4378645 | O16: =P16-30 -> 45642 | P16: 45672 | R16: Mandy | S16: Completed | U16: Y | V16: Annually
J17: TK24078 | K17: Follow Up | L17: Life Proposal | M17: Randy Crax | N17: 4756599 | O17: =P17-30 -> 45639 | P17: 45669 | R17: Simon | S17: Completed | U17: N
J18: TK24077 | K18: Renewal | L18: Send Renewal Notice | M18: Bella Vista | N18: 2727254 | O18: =P18-30 -> 45634 | P18: 45664 | R18: Simon | S18: Completed | U18: Y | V18: Annually
J19: TK24076 | K19: Reminder | L19: Send Reminder | M19: Deep Divers | N19: 2815655 | O19: =P19-30 -> 45631 | P19: 45661 | R19: Simon | S19: Completed | U19: Y | V19: Annually
J20: TK24075 | K20: Meeting | L20: Life Proposal | M20: Sam Anadro | N20: 2711090 | O20: =P20-30 -> 45621 | P20: 45651 | R20: Simon | S20: Completed | U20: N

Sheet VT
A1: `
E2: Tasks
E4: Records Found - 14
J6: Task ID | K6: Category | L6: Task Note | M6: Target | N6: Contact No | O6: Due Date | P6: Due in | Q6: Assignee | R6: Task Status | S6: Done Date | T6: Repeat | U6: Frequency | X6: RptStopDate
J7: TK24088 | K7: Payment | L7: P.O. Box Rental | M7: Seychelles Postal Services | N7: 2765997 | O7: =TODAY()+14 -> 45966 | P7: =O7-TODAY() -> 14 | Q7: Mandy | R7: Not Done | T7: Y
J8: TK24087 | K8: Report | L8: Beneficial Owner Report | M8: FIU | N8: 4282828 | O8: =TODAY()+12 -> 45964 | P8: =O8-TODAY() -> 12 | Q8: Mandy | R8: Not Done | T8: Y | U8: Bi Annually
J9: TK24086 | K9: Payment | L9: Brokers License | M9: FSA | N9: 4378645 | O9: =TODAY()+8 -> 45960 | P9: =O9-TODAY() -> 8 | Q9: Simon | R9: Not Done | T9: Y | U9: Annually
J10: TK24085 | K10: To Do | L10: Presentation | M10: Hunt Deltel | N10: 4232323 | O10: =TODAY()+8 -> 45960 | P10: 12 | Q10: Mandy | R10: Not Done | T10: N
J11: TK24084 | K11: Payment | L11: PI Insurance Renewal | M11: Alliance | N11: 4223434 | O11: =TODAY()+7 -> 45959 | P11: =O11-TODAY() -> 7 | Q11: Mandy | R11: Not Done | T11: Y | U11: Annually
J12: TK24083 | K12: Payment | L12: Annual Registration Fee | M12: Registrar Of Companies | N12: 2711511 | O12: =TODAY()+4 -> 45956 | P12: 13 | Q12: Mandy | R12: Not Done | T12: Y | U12: Annually
J13: TK24082 | K13: Report | L13: Financial Audit Report | M13: FSA | N13: 4378645 | O13: =TODAY()+1 -> 45953 | P13: =O13-TODAY() -> 1 | Q13: Simon | R13: Not Done | T13: Y | U13: Annually
J14: TK24081 | K14: Report | L14: Bi Annuall CFT Report | M14: FSA | N14: 4378645 | O14: =TODAY()+0 -> 45952 | P14: 14 | Q14: Simon | R14: Not Done | T14: Y | U14: Bi Annually
J15: TK24080 | K15: To Do | L15: Tax Return | M15: Seychelles Trevenue Commission | N15: 4287555 | O15: =TODAY()-2 -> 45950 | P15: =O15-TODAY() -> -2 | Q15: Simon | R15: In Progress | T15: Y | U15: Annually
J16: TK24079 | K16: Report | L16: Compliance Report | M16: FSA | N16: 4378645 | O16: 45672 | Q16: Mandy | R16: Completed | T16: Y | U16: Annually
J17: TK24078 | K17: Follow Up | L17: Life Proposal | M17: Randy Crax | N17: 4756599 | O17: 45669 | Q17: Simon | R17: Completed | T17: N
J18: TK24077 | K18: Renewal | L18: Send Renewal Notice | M18: Bella Vista | N18: 2727254 | O18: 45664 | Q18: Simon | R18: Completed | T18: Y | U18: Annually
J19: TK24076 | K19: Reminder | L19: Send Reminder | M19: Deep Divers | N19: 2815655 | O19: 45661 | Q19: Simon | R19: Completed | T19: Y | U19: Annually
J20: TK24075 | K20: Meeting | L20: Life Proposal | M20: Sam Anadro | N20: 2711090 | O20: 45651 | Q20: Simon | R20: Completed | T20: N

Sheet LTO
A1: `
E2: Tasks - Overdue
E4: Records Found - 2
F6: Action | G6: Task ID | H6: Category | I6: Item | J6: Name | K6: Contact No | L6: Due Date | M6: Time | N6: Due in | O6: Assignee | P6: Task Status | Q6: Done Date | R6: Repeat | S6: Frequency | V6: Rpt Stop Date
G7: TK24081 | H7: Report | I7: Bi Annuall CFT Report | J7: FSA | K7: 4378645 | L7: =TODAY()-3 -> 45949 | N7: =L7-TODAY() -> -3 | O7: Simon | P7: Not Done | R7: Y | S7: Bi Annually
G8: TK24080 | H8: To Do | I8: Tax Return | J8: Seychelles Revenue Commission | K8: 4287555 | L8: =TODAY()-1 -> 45951 | N8: =L8-TODAY() -> -1 | O8: Simon | P8: In Progress | R8: Y | S8: Annually

Sheet DT
A1: `
E2: Tasks
E4: Records Found - 5
F6: Action | G6: Task ID | H6: Task ID | I6: Task ID | J6: Category | K6: Item | L6: Name | M6: Contact No | N6: Due Date | O6: Time | P6: Due in | Q6: Assignee | R6: Task Status | S6: Date Done | T6: Repeat | U6: Frequency | X6: Rpt Date | Y6: Rpt Stop Date
I7: TK24085 | J7: Event | K7: Presentation | L7: Hunt Deltel | M7: 4232323 | N7: =TODAY() -> 45952 | O7: 1600 | P7: 12 | Q7: Mandy | R7: Not Done | T7: N | X7: 45701
I8: TK24084 | J8: Payment | K8: PI Insurance Renewal | L8: Alliance | M8: 4223434 | N8: 45733 | P8: 7 | Q8: Mandy | R8: Not Done | T8: Y | U8: Annually | X8: 45699
I9: TK24083 | J9: Payment | K9: Annual Registration Fee | L9: Registrar Of Companies | M9: 2711511 | N9: 45730 | P9: 13 | Q9: Mandy | R9: Not Done | T9: Y | U9: Annually | X9: 45695
I10: TK24082 | J10: Report | K10: Financial Audit Report | L10: FSA | M10: 4378645 | N10: 45727 | P10: 1 | Q10: Simon | R10: Not Done | T10: Y | U10: Annually
I11: TK24081 | J11: Report | K11: Bi Annuall CFT Report | L11: FSA | M11: 4378645 | N11: 45726 | P11: 14 | Q11: Simon | R11: Not Done | T11: Y | U11: Bi Annually | X11: 45694
X12: 45691
X13: 45688
X14: 45687
X15: 45685
X16: 45672
X18: 45664
X19: 45661

Sheet LFU
A1: `
E2: Follow Ups
E4: Records 1 to 15 of 24
F6: Action | G6: FUID | H6: FUID | I6: FUID | J6: Due Date | K6: Due in | L6: Category | M6: Name | N6: Follow Up Note | O6: Contact No | P6: Policy No | Q6: FU Status | R6: Date Done | S6: Comment
I7: FU25033 | J7: 45278 | K7: =J7-TODAY() -> -674 | L7: Proposal | M7: Thomas Burns | N7: Follow Up On Offer | O7: 2765997 | Q7: Not Done | R7: 45730
I8: FU25032 | J8: =TODAY()+36 -> 45988 | K8: =J8-TODAY() -> 36 | L8: Proposal | M8: Oscar Medin | N8: Follow Up On Offer | O8: 2713397 | P8: PL-030-1-0000231 | Q8: Not Done | R8: 45762
I9: FU25031 | J9: =TODAY()+8 -> 45960 | K9: =J9-TODAY() -> 8 | L9: Proposal | M9: Sierra Fox | O9: 4378645 | P9: MTP-23-HEA-P0000321 | Q9: Not Done | R9: 45734
I10: FU25030 | J10: 45608 | K10: 12 | L10: Proposal | M10: Wayne Costa | N10: Sony Cosya's ID | O10: 2545412 | Q10: Not Done | R10: 45608
I11: FU25029 | J11: =TODAY()+17 -> 45969 | K11: =J11-TODAY() -> 17 | L11: Contact | M11: Autocars (Pty) Ltd | N11: Company registration documents | O11: 4223434 | Q11: Not Done | R11: 45743
I12: FU25028 | J12: =TODAY()+28 -> 45980 | K12: =J12-TODAY() -> 28 | L12: Contact | M12: Trevor Kanot | N12: To start life policy | O12: 2711511 | Q12: Not Done | R12: 45754
I13: FU25027 | J13: =TODAY()+32 -> 45984 | K13: =J13-TODAY() -> 32 | L13: Contact | M13: Ted David | N13: Confirm meeting | O13: 2643234 | Q13: Not Done | R13: 45758
I14: FU25026 | J14: =TODAY()+32 -> 45984 | K14: =J14-TODAY() -> 32 | L14: Contact | M14: Monica Bird | N14: When to meet | O14: 2711511 | Q14: Not Done | R14: 45758
I15: FU25025 | J15: =TODAY()+34 -> 45986 | K15: =J15-TODAY() -> 34 | L15: Contact | M15: Peter Cox | N15: Awaiting Deposit | O15: 4223456 | Q15: Not Done | R15: 45760
I16: FU25024 | J16: =TODAY()+32 -> 45984 | K16: =J16-TODAY() -> 32 | L16: Contact | M16: George Bash | N16: Awaiting Deposit | O16: 2514231 | Q16: FU25031 | R16: FU25028
I17: FU25023 | J17: =TODAY()+34 -> 45986 | K17: =J17-TODAY() -> 34 | L17: Contact | M17: Shana Green | N17: Awaiting Document | O17: 2643234 | Q17: Not Done | R17: 45765
I18: FU25022 | J18: =TODAY()+32 -> 45984 | K18: =J18-TODAY() -> 32 | L18: Contact | M18: Keystone Brokers(Pty) Ltd | O18: 2717171 | Q18: Not Done | R18: 45766
I19: FU25021 | J19: =TODAY()+41 -> 45993 | K19: =J19-TODAY() -> 41 | L19: Contact | M19: Walton Wild | O19: 4223456 | Q19: Not Done | R19: 45767
I20: FU25020 | J20: =TODAY()+42 -> 45994 | K20: =J20-TODAY() -> 42 | L20: Contact | M20: William Scott | O20: 2514231 | P20: PL-030-1-0094837 | Q20: Not Done | R20: 45768

Sheet PFU
E2: Contacts - To Follow Up
E4: Records Found - 11
F6: Action | G6: Contact Name | H6: Contact No | I6: Type | J6: Source | K6: Acquired | L6: Status | M6: 1st Called | N6: Rank | O6: 2FU | P6: Next FU | R6: Occupation | U6: Status | V6: Employer | W6: Agency | X6: Address | Y6: Contact ID | Z6: Savings Budget | AA6: Married | AB6: Children | AC6: Children Details | AD6: Vehicle | AE6: House | AF6: Business | AG6: Other | AH6: Source Name
G7: Wanda Lucas | H7: 4423212 | I7: Prospect | J7: Referal | K7: 45778 | L7: Proposal Made | M7: 45781 | N7: Warm | O7: Y | P7: 45393 | R7: Driver | U7: Active | V7: SEYPEC | W7: Keystone | X7: Beau Vallon | Y7: LD24-0077
G8: Debra Grey | H8: 2511611 | I8: Lead | J8: Direct | K8: 45778 | L8: Not Contacted | N8: Hot | R8: Accountant | U8: Active | V8: Cable & Wireless | W8: Keystone | X8: Mont Fleuri | Y8: LD24-0076 | AH8: Blake Seven
G9: Sheila Ewang | H9: 2765432 | I9: Lead | J9: Referal | K9: =TODAY()-3 -> 45949 | L9: Qualified | M9: 45453 | N9: Warm | O9: Y | P9: 45325 | R9: Customer Service Officer | U9: Active | V9: AIRTEL | W9: Keystone | X9: Beau Vallon | Y9: LD24-0075 | AH9: Yvon Coburn
G10: Kirk Patrick | H10: 4373234 | I10: Lead | J10: Walk In | K10: 45711 | L10: In Discussion | M10: 45432 | N10: Warm | O10: Y | P10: 45432 | R10: Contractor | U10: Active | W10: Keystone | X10: Cascade | Y10: LD24-0074
G11: Scott Svenson | H11: 4378645 | I11: Lead | J11: Referal | K11: 45709 | L11: Keep In View | M11: 45387 | N11: Cool | O11: Y | P11: 42908 | R11: Technician | U11: In Active | W11: Keystone | X11: Victoria | Y11: LD24-0073 | AH11: Kim Walton
G12: Samuel Hill | H12: 2514231 | I12: Lead | J12: Referal | K12: 45704 | L12: In Discussion | M12: 45440 | N12: Warm | O12: Y | P12: 45446 | R12: Payroll Officier | U12: Active | V12: SPTC | X12: Mont Fleuri | Y12: LD24-0073 | AH12: Samantha Dopilo
G13: Kaste McEwan | H13: 2765887 | I13: Prospect | J13: Referal | K13: 45691 | L13: Proposal Made | M13: 45439 | N13: Warm | O13: Y | P13: 45427 | R13: Boat Charter | U13: Active | V13: Inter Island Boats | W13: Keystone | X13: Beau Vallon | Y13: LD24-0072 | AH13: Trevor Crusher
G14: Mary Trader | H14: 4373234 | I14: Prospect | J14: Walk In | K14: 45684 | L14: Proposal Made | M14: 45432 | N14: Warm | O14: Y | P14: 45432 | R14: Contractor | U14: Active | W14: Keystone | X14: Providence | Y14: LD24-0071
G15: Damien Kinmo | H15: 2787653 | I15: Lead | J15: Direct | K15: 45680 | L15: Differed | M15: 30602 | N15: Warm | O15: Y | P15: 45943 | R15: Human Resources Manager | U15: Active | W15: Keystone | X15: Grand Anse | Y15: LD24-0070
G16: Dua Gomez | H16: 4378645 | I16: Lead | J16: Referal | K16: 45556 | L16: Open | M16: 45387 | N16: KIV | O16: Y | P16: 42908 | R16: Technician | U16: Active | V16: SPTC | X16: Mont Fleuri | Y16: LD24-0073 | AH16: Kim Walton
G17: Cox Santana | H17: 4378677 | I17: Lead | J17: Referal | K17: =TODAY()-44 -> 45908 | L17: Open | M17: 45387 | N17: Warm | O17: Y | P17: 42908 | R17: Technician | U17: Active | V17: Inter Island Boats | W17: Keystone | X17: Beau Vallon | Y17: LD24-0072 | AH17: Barry Marks
U18: Active | W18: Keystone | X18: Providence | Y18: LD24-0071
U19: Active | W19: Keystone | X19: Grand Anse | Y19: LD24-0070
U20: Active | W20: Keystone | X20: Anse Aux Pins | Y20: LD24-0069
U21: Active | W21: Keystone | X21: Grand Anse | Y21: LD24-0070

Sheet LFUD
A1: `
E2: Follow Ups
E4: Records 1 to 15 of 24
J6: FUID | K6: Name | L6: Contact No | M6: Policy No | N6: Category | O6: Due Date | P6: Due in | Q6: Follow Up Note | R6: FU Status | S6: Date Done
J7: FU25033 | K7: Keven Minion | L7: 2765997 | M7: MPV-23-PRO-P0003452 | N7: Reminder | O7: =TODAY()+4 -> 45956 | P7: =O7-TODAY() -> 4 | Q7: Renewal Reminder | R7: Not Done | S7: 45730
J8: FU25032 | K8: Oscar Medin | L8: 2713397 | M8: PL-030-1-0000231 | N8: Reminder | O8: =TODAY()+36 -> 45988 | P8: =O8-TODAY() -> 36 | Q8: Renewal Reminder | R8: Not Done | S8: 45762
J9: FU25031 | K9: Sierra Fox | L9: 4378645 | M9: MTP-23-HEA-P0000321 | N9: Reminder | O9: =TODAY()+8 -> 45960 | P9: =O9-TODAY() -> 8 | Q9: Renewal Reminder | R9: Not Done | S9: 45734
J10: FU25030 | K10: Wayne Costa | L10: 2545412 | N10: Reminder | O10: 45608 | P10: 12 | Q10: Sony Cosya's ID | R10: Not Done | S10: 45608
J11: FU25029 | K11: Autocars (Pty) Ltd | L11: 4223434 | N11: Reminder | O11: =TODAY()+17 -> 45969 | P11: =O11-TODAY() -> 17 | Q11: Company registration documents | R11: Not Done | S11: 45743
J12: FU25028 | K12: Trevor Kanot | L12: 2711511 | N12: To Do | O12: =TODAY()+28 -> 45980 | P12: =O12-TODAY() -> 28 | Q12: To start life policy | R12: Not Done | S12: 45754
J13: FU25027 | K13: Ted David | L13: 2643234 | N13: Discussion | O13: =TODAY()+32 -> 45984 | P13: =O13-TODAY() -> 32 | Q13: Confirm meeting | R13: Not Done | S13: 45758
J14: FU25026 | K14: Monica Bird | L14: 2711511 | N14: Discussion | O14: =TODAY()+32 -> 45984 | P14: =O14-TODAY() -> 32 | Q14: When to meet | R14: Not Done | S14: 45758
J15: FU25025 | K15: Peter Cox | L15: 4223456 | N15: Follow up | O15: =TODAY()+34 -> 45986 | P15: =O15-TODAY() -> 34 | Q15: Ready to start Life policy | R15: Not Done | S15: 45760
J16: FU25024 | K16: George Bash | L16: 2514231 | N16: Follow up | O16: =TODAY()+32 -> 45984 | P16: =O16-TODAY() -> 32 | Q16: Ready for 1st deposit | R16: FU25031 | S16: FU25028
J17: FU25023 | K17: Shana Green | L17: 2643234 | N17: Follow up | O17: =TODAY()+34 -> 45986 | P17: =O17-TODAY() -> 34 | R17: Not Done | S17: 45765
J18: FU25022 | K18: Keystone Brokers(Pty) Ltd | L18: 2717171 | N18: To Do | O18: =TODAY()+32 -> 45984 | P18: =O18-TODAY() -> 32 | R18: Not Done | S18: 45766
J19: FU25021 | K19: Walton Wild | L19: 4223456 | N19: Report | O19: =TODAY()+41 -> 45993 | P19: =O19-TODAY() -> 41 | R19: Not Done | S19: 45767
J20: FU25020 | K20: William Scott | L20: 2514231 | M20: PL-030-1-0094837 | N20: Reminder | O20: =TODAY()+42 -> 45994 | P20: =O20-TODAY() -> 42 | R20: Not Done | S20: 45768

Sheet AFU
E2: Follow Ups
E4: Records 1 to 15 of 143
J6: Task ID | K6: Task Type | L6: Due Date | M6: Due in | N6: Task Note | O6: Task Status | P6: Repeat | Q6: Policy No | R6: Contact | S6: Contact No
J7: TK24088 | K7: Renewal | L7: =TODAY()+4 -> 45956 | M7: =L7-TODAY() -> 4 | N7: S4396 | O7: Not Done | P7: Y | Q7: MPV-23-HEA-P003453 | R7: Adbul Jumaye | S7: 2765997
J8: TK24087 | K8: Renewal Notice | L8: =TODAY()+6 -> 45958 | M8: =L8-TODAY() -> 6 | O8: Sent by SMS | P8: Y | Q8: MPV-23-HEA-P0002132 | R8: Jean Grey | S8: 4373234
J9: TK24086 | K9: Reminder | L9: =TODAY()+8 -> 45960 | M9: =L9-TODAY() -> 8 | O9: Sent to Wattsapp | P9: Y | Q9: MTP-23-HEA-P0000321 | R9: Agricultural Corporative | S9: 4378645
J10: TK24085 | K10: Presentation | L10: =TODAY()+12 -> 45964 | M10: =L10-TODAY() -> 12 | N10: 10am at Hunt Deltel | O10: Booked
J11: TK24084 | K11: Follow Up | L11: =TODAY()+17 -> 45969 | M11: =L11-TODAY() -> 17 | O11: SMS Reminder Sent | P11: Y | Q11: PLI-23-P00023432 | R11: Autocars (Pty) Ltd | S11: 4223434
J12: TK24083 | K12: To Do | L12: =TODAY()+28 -> 45980 | M12: =L12-TODAY() -> 28 | N12: Broker Lisence | O12: Not Done | P12: Y | R12: Keystone Broker (Pty) Ltd | S12: 2711511
J13: TK24082 | K13: Renewal Notice | L13: =TODAY()+32 -> 45984 | M13: =L13-TODAY() -> 32 | O13: Not Done | P13: Y | Q13: CAR-PL-003234 | R13: Tween David | S13: 2643234
J14: TK24081 | K14: To Do | L14: =TODAY()+32 -> 45984 | M14: =L14-TODAY() -> 32 | N14: Annual Registration Fee | O14: Not Done | P14: Y | R14: Keystone Brokers(Pty) Ltd | S14: 2717171
J15: TK24080 | K15: To Do | L15: =TODAY()+34 -> 45986 | M15: =L15-TODAY() -> 34 | N15: Bi Annual CCF Report | O15: Not Done | P15: Y | R15: FSA | S15: 4223456
J16: TK24079 | K16: Reminder | L16: =TODAY()+36 -> 45988 | M16: =L16-TODAY() -> 36 | O16: Not Done | P16: Y | Q16: PL-030-1-0000231 | R16: Oscar Medin | S16: 2514231
J17: TK24078 | K17: Renewal Notice | L17: =TODAY()+39 -> 45991 | M17: =L17-TODAY() -> 39 | O17: Not Done | P17: Y | Q17: CAR-PL-003234 | R17: Shana Green | S17: 2643234
J18: TK24077 | K18: To Do | L18: =TODAY()+40 -> 45992 | M18: =L18-TODAY() -> 40 | O18: Not Done | P18: Y | R18: Keystone Brokers(Pty) Ltd | S18: 2717171
J19: TK24076 | K19: Report | L19: =TODAY()+41 -> 45993 | M19: =L19-TODAY() -> 41 | O19: Not Done | P19: Y | R19: Walton Wild | S19: 4223456
J20: TK24075 | K20: Reminder | L20: =TODAY()+42 -> 45994 | M20: =L20-TODAY() -> 42 | O20: Not Done | Q20: PL-030-1-0094837 | R20: William Scott | S20: 2514231

Sheet DFR
E2: Policies Due For Renewal
E4: Records Found - 5
F6: Action | G6: Policy No | H6: End Date | I6: Due In | J6: Status | K6: Client Name | L6: Insurer | M6: Policy Class | N6: Policy Plan | O6: Item | P6: Premium
G7: MPV-23-PRO-P000231 | H7: =TODAY()-2 -> 45950 | I7: =H7-TODAY() -> -2 | J7: Expired | K7: Lindsey Blake | L7: SACOS | M7: Motor | N7: Comprehensive | O7: S44444 | P7: 11455.893
G8: FSP-18-00010-P73422 | H8: =TODAY()+7 -> 45959 | I8: =H8-TODAY() -> 7 | J8: DFR | K8: Island Hideaway | L8: Hsavy | M8: General | N8: House Insurance | O8: House at Beau Vallon | P8: =T8*1.16 -> 0
G9: HS1-070-1-0029321 | H9: =TODAY()+10 -> 45962 | I9: =H9-TODAY() -> 10 | J9: DFR | K9: Island Hideaway | L9: Alliance | M9: General | N9: Public Liability | P9: =T9*1.16 -> 0
G10: HS1-070-1-0318323 | H10: =H9 -> 45962 | I10: =H10-TODAY() -> 10 | J10: DFR | K10: Island Hideaway | L10: Alliance | M10: General | N10: Employer's Liabilithy | P10: 2900
G11: FFA-00-HEA-P92322 | H11: =TODAY()+23 -> 45975 | I11: =H11-TODAY() -> 23 | J11: DFR | K11: The Lodge | L11: SACOS | M11: General | N11: Fire & Special Perils | O11: Guest House at Sans Soucis | P11: 27034

Sheet LID
E2: Premium Instalments Due
E4: Records Found - 5
F6: Action | G6: Debit Note | H6: Debit Note | I6: Debit Note | J6: Policy Number | K6: Clients Name | L6: Payment Type | M6: No | N6: Date Due | O6: Due In | P6: Amount Due | Q6: Status | R6: Comments
G7: 1 | I7: DN24100 | J7: MPV-23-HEA-P0002132 | K7: Jean Grey | L7: Instalment | M7: 2 | N7: 45640 | O7: =N7-TODAY() -> -312 | P7: 5727.9466 | Q7: Overdue
G8: 2 | I8: DN25021 | J8: MPV-23-HEA-P0001011 | K8: Thomas Hardy | L8: Instalment | M8: 3 | N8: =TODAY()+8 -> 45960 | O8: =N8-TODAY() -> 8 | P8: 3375 | Q8: Unpaid
G9: 3 | I9: DN25020 | J9: FSP-22-HEA-P0000033 | K9: Camilla Brody | L9: Instalment | M9: 2 | N9: 45275 | O9: =N9-TODAY() -> -677 | P9: 2654.5 | Q9: Unpaid
G10: 4 | I10: DN25019 | J10: PLI-23-HEA-P00003001 | K10: Judy Basil | L10: Instalment | M10: 2 | N10: =TODAY()+33 -> 45985 | O10: =N10-TODAY() -> 33 | P10: 2340 | Q10: Unpaid
G11: 5 | I11: DN25018 | J11: MPV-23-HEA-P0002132 | K11: Suesan Norton | L11: Instalment | M11: 4 | N11: =TODAY()+44 -> 45996 | O11: =N11-TODAY() -> 44 | P11: 3338 | Q11: Unpaid

Sheet LRN
A1: `
E2: Renewals
E4: Records Found - 14
F6: Action | G6: Task ID | H6: Task ID | I6: Task ID | J6: Category | K6: Item | L6: Name | M6: Contact No | N6: Due Date | O6: Time | P6: Due in | Q6: Task Status | R6: Date Done | S6: Repeat | T6: Frequency | W6: Rpt Date | X6: Rpt Stop Date | Y6: Assignee
I7: TK24088 | J7: Renewals | K7: P.O. Box Rental | L7: Seychelles Postal Services | M7: 2765997 | N7: =TODAY()+14 -> 45966 | P7: =N7-TODAY() -> 14 | Q7: Not Done | S7: Y | T7: Annually | W7: 45701 | Y7: Mandy
I8: TK24087 | J8: Renewals | K8: Beneficial Owner Report | L8: FIU | M8: 4282828 | N8: =TODAY()+12 -> 45964 | P8: =N8-TODAY() -> 12 | Q8: Not Done | S8: Y | T8: Bi Annually | W8: 45699 | Y8: Mandy
I9: TK24086 | J9: Renewals | K9: Brokers License | L9: FSA | M9: 4378645 | N9: =TODAY()+8 -> 45960 | P9: =N9-TODAY() -> 8 | Q9: Not Done | S9: Y | T9: Annually | W9: 45695 | Y9: Simon
I10: TK24085 | J10: Renewals | K10: Presentation | L10: Hunt Deltel | M10: 4232323 | N10: =TODAY()+8 -> 45960 | O10: 1600 | P10: 12 | Q10: Not Done | S10: N | Y10: Mandy
I11: TK24084 | J11: Renewals | K11: PI Insurance Renewal | L11: Alliance | M11: 4223434 | N11: =TODAY()+7 -> 45959 | P11: =N11-TODAY() -> 7 | Q11: Not Done | S11: Y | T11: Annually | W11: 45694 | Y11: Mandy
I12: TK24083 | J12: Renewals | K12: Annual Registration Fee | L12: Registrar Of Companies | M12: 2711511 | N12: =TODAY()+4 -> 45956 | P12: 13 | Q12: Not Done | S12: Y | T12: Annually | W12: 45691 | Y12: Mandy
I13: TK24082 | J13: Renewals | K13: Financial Audit Report | L13: FSA | M13: 4378645 | N13: =TODAY()+1 -> 45953 | P13: =N13-TODAY() -> 1 | Q13: Not Done | S13: Y | T13: Annually | W13: 45688 | Y13: Simon
I14: TK24081 | J14: Renewals | K14: Bi Annuall CFT Report | L14: FSA | M14: 4378645 | N14: =TODAY()+0 -> 45952 | P14: 14 | Q14: Not Done | S14: Y | T14: Bi Annually | W14: 45687 | Y14: Simon
I15: TK24080 | J15: Renewals | K15: Tax Return | L15: Seychelles Revenue Commission | M15: 4287555 | N15: =TODAY()-2 -> 45950 | P15: =N15-TODAY() -> -2 | Q15: In Progress | S15: Y | T15: Annually | W15: 45685 | Y15: Simon
I16: TK24079 | J16: Renewals | K16: Compliance Report | L16: FSA | M16: 4378645 | N16: 45672 | Q16: Completed | R16: 45682 | S16: Y | T16: Annually | W16: 45672 | Y16: Mandy
I17: TK24078 | J17: Renewals | K17: Deposit Premium | L17: Randy Crax | M17: 4756599 | N17: 45669 | O17: 1130 | Q17: Completed | R17: 45669 | S17: N | Y17: Simon
I18: TK24077 | J18: Renewals | K18: Deposit Premium | L18: Bella Vista | M18: 2727254 | N18: 45664 | Q18: Completed | R18: 45664 | S18: N | W18: 45664 | Y18: Simon
I19: TK24076 | J19: Renewals | K19: Deposit Premium | L19: Deep Divers | M19: 2815655 | N19: 45661 | Q19: Completed | R19: 45661 | S19: N | W19: 45661 | Y19: Simon
I20: TK24075 | J20: Renewals | K20: Life Proposal | L20: Sam Anadro | M20: 2711090 | N20: 45651 | O20: 1030 | Q20: Completed | R20: 46016 | S20: N | Y20: Simon

Sheet LL
E2: Contacts
E4: Records Found - 102
F6: Action | G6: Contact Name | H6: Contact No | I6: Type | J6: Occupation | K6: Employer | L6: Acquired | M6: Source | N6: Status | O6: Rank | P6: 1st Contact | Q6: Next FU | U6: COID | V6: DOB | W6: CT | X6: Source Name | Y6: Agency | Z6: Agent | AA6: Address | AB6: email Address | AC6: Contact ID | AD6: Savings Budget | AE6: Married | AF6: Children | AG6: Children Details | AH6: Vehicle | AI6: House | AJ6: Business | AK6: Other
G7: Wanda Lucas | H7: 4423212 | I7: Prospect | J7: Driver | K7: SEYPEC | L7: 45778 | M7: Referal | N7: Proposal Made | O7: VIP | P7: 45781 | Q7: =TODAY()-7 -> 45945 | U7: CT179 | V7: 31090 | W7: Mrs | Y7: Keystone | AA7: Beau Vallon | AC7: LD24-0077
G8: Debra Grey | H8: 2511611 | I8: Lead | J8: Accountant | K8: Cable & Wireless | L8: 45778 | M8: Direct | N8: Not Contacted | U8: CT178 | V8: 31109 | W8: Mrs | X8: Blake Seven | Y8: Keystone | AA8: Mont Fleuri | AC8: LD24-0076
G9: Sheila Ewang | H9: 2765432 | I9: Lead | J9: Customer Service Officer | K9: AIRTEL | L9: =TODAY()-3 -> 45949 | M9: Referal | N9: RNR | O9: Medium | P9: 45453 | Q9: =TODAY()-3 -> 45949 | U9: CT177 | V9: 39407 | W9: Mrs | X9: Yvon Coburn | Y9: Keystone | AA9: Beau Vallon | AC9: LD24-0075
G10: Itoh San | H10: 3798111 | I10: Lead | J10: Real Estate Agent | L10: =TODAY()-7 -> 45945 | M10: Direct | N10: Archived | O10: Froze | P10: 45326 | U10: CT176 | V10: 36317 | W10: Mr | Y10: Keystone | AA10: Cascade | AC10: LD24-0074
G11: Jude Brown | H11: 4665321 | I11: Lead | J11: Rock Breaker | L11: =TODAY()-10 -> 45942 | M11: Presentation | N11: Archived | O11: High | P11: 45450 | U11: CT175 | V11: 32069 | W11: Mr | X11: Hypermarket | Y11: Keystone | AA11: Victoria | AC11: LD24-0073
G12: Mark Valance | H12: 2514231 | I12: Contact | J12: Payroll Officier | K12: SPTC | M12: Direct | U12: CT174 | V12: 29901 | W12: Mr | X12: Samantha Dopilo | AA12: Mont Fleuri | AC12: LD24-0073
G13: Anna Salom | H13: 2765887 | I13: Prospect | J13: Boat Charter | K13: Inter Island Boats | L13: =TODAY()-10 -> 45942 | M13: Referal | N13: In Discussion | O13: Medium | P13: 45439 | Q13: =TODAY()+2 -> 45954 | U13: CT173 | V13: 34211 | W13: Ms | X13: Trevor Crusher | Y13: Keystone | AA13: Beau Vallon | AC13: LD24-0072
G14: Kirk Patrick | H14: 4373234 | I14: Prospect | J14: Contractor | L14: =TODAY()-13 -> 45939 | M14: Walk In | N14: In Discussion | O14: Medium | P14: 45432 | Q14: =TODAY()+2 -> 45954 | U14: CT172 | V14: 38521 | W14: Mr | Y14: Keystone | AA14: Providence | AC14: LD24-0071
G15: Scott Svenson | H15: 4378645 | I15: Prospect | J15: Technician | L15: =TODAY()-15 -> 45937 | M15: Referal | N15: Keep In View | O15: Low | P15: 45387 | Q15: =TODAY()+5 -> 45957 | U15: CT171 | V15: 42831 | W15: Mr | X15: Kim Walton | Y15: Keystone | AA15: Grand Anse | AC15: LD24-0070
G16: Samuel Hill | H16: 2514231 | I16: Contact | J16: Payroll Officier | K16: SPTC | U16: CT170 | V16: 47141 | W16: Mr | X16: Samantha Dopilo | AA16: Mont Fleuri | AC16: LD24-0073
G17: Kaste McEwan | H17: 2765887 | I17: Prospect | J17: Boat Charter | K17: Inter Island Boats | L17: =TODAY()-33 -> 45919 | M17: Referal | N17: Proposal Made | O17: Medium | P17: 45439 | Q17: =TODAY()+9 -> 45961 | U17: CT169 | V17: 51451 | W17: Miss | X17: Trevor Crusher | Y17: Keystone | AA17: Beau Vallon | AC17: LD24-0072
G18: Mary Trader | H18: 4373234 | I18: Prospect | J18: Tecnician | L18: =TODAY()-40 -> 45912 | M18: Walk In | N18: Proposal Made | O18: Low | P18: 45432 | Q18: =TODAY()+11 -> 45963 | U18: CT168 | V18: 55761 | W18: Miss | Y18: Keystone | AA18: Providence | AC18: LD24-0071
G19: Emilie LaCruz | H19: 4378645 | I19: Contact | J19: Paymaster | M19: Direct | U19: CT167 | V19: 60071 | W19: Miss | Y19: Keystone | AA19: Grand Anse | AC19: LD24-0070
G20: Damien Kinmo | H20: 2787653 | I20: Lead | J20: Human Resources Manager | K20: Avani Hotel | L20: =TODAY()-44 -> 45908 | M20: Direct | N20: Differed | O20: Warm | P20: 30602 | Q20: =TODAY()+11 -> 45963 | U20: CT166 | V20: 64381 | W20: Mr | Y20: Keystone | AA20: Anse Aux Pins | AC20: LD24-0069

Sheet AL
E2: Contacts
E4: Records Found - 102
F6: Action | G6: Contact Name | H6: Contact No | I6: Type | J6: Occupation | K6: Employer | L6: Acquired | M6: Status | N6: 1st Contact | O6: Rank | P6: 2FU | Q6: Next FU | U6: COID | W6: Source Name | X6: Agency | Y6: Address | Z6: email Address | AA6: Contact ID | AB6: Savings Budget | AC6: Married | AD6: Children | AE6: Children Details | AF6: Vehicle | AG6: House | AH6: Business | AI6: Other | AJ6: Source
G7: Wanda Lucas | H7: 4423212 | I7: Prospect | J7: Driver | K7: SEYPEC | L7: 45778 | M7: Proposal Made | N7: 45781 | O7: VIP | P7: Y | Q7: =TODAY()-7 -> 45945 | U7: CT179 | X7: Keystone | Y7: Beau Vallon | AA7: LD24-0077 | AJ7: Referal
G8: Debra Grey | H8: 2511611 | I8: Lead | J8: Accountant | K8: Cable & Wireless | L8: 45778 | M8: Not Contacted | U8: CT178 | W8: Blake Seven | X8: Keystone | Y8: Mont Fleuri | AA8: LD24-0076 | AJ8: Direct
G9: Sheila Ewang | H9: 2765432 | I9: Lead | J9: Customer Service Officer | K9: AIRTEL | L9: =TODAY()-3 -> 45949 | M9: RNR | N9: 45453 | O9: Medium | P9: Y | Q9: =TODAY()-3 -> 45949 | U9: CT177 | W9: Yvon Coburn | X9: Keystone | Y9: Beau Vallon | AA9: LD24-0075 | AJ9: Referal
G10: Itoh San | H10: 3798111 | I10: Lead | J10: Real Estate Agent | L10: =TODAY()-7 -> 45945 | M10: Archived | N10: 45326 | O10: Froze | P10: N | U10: CT176 | X10: Keystone | Y10: Cascade | AA10: LD24-0074 | AJ10: Direct
G11: Jude Brown | H11: 4665321 | I11: Lead | J11: Rock Breaker | L11: =TODAY()-10 -> 45942 | M11: Archived | N11: 45450 | O11: High | P11: N | U11: CT175 | W11: Hypermarket | X11: Keystone | Y11: Victoria | AA11: LD24-0073 | AJ11: Presentation
G12: Mark Valance | H12: 2514231 | I12: Contact | J12: Payroll Officier | K12: SPTC | U12: CT174 | W12: Samantha Dopilo | Y12: Mont Fleuri | AA12: LD24-0073 | AJ12: Direct
G13: Anna Salom | H13: 2765887 | I13: Prospect | J13: Boat Charter | K13: Inter Island Boats | L13: =TODAY()-10 -> 45942 | M13: In Discussion | N13: 45439 | O13: Medium | P13: Y | Q13: =TODAY()+2 -> 45954 | U13: CT173 | W13: Trevor Crusher | X13: Keystone | Y13: Beau Vallon | AA13: LD24-0072 | AJ13: Referal
G14: Kirk Patrick | H14: 4373234 | I14: Prospect | J14: Contractor | L14: =TODAY()-13 -> 45939 | M14: In Discussion | N14: 45432 | O14: Medium | P14: Y | Q14: =TODAY()+2 -> 45954 | U14: CT172 | X14: Keystone | Y14: Providence | AA14: LD24-0071 | AJ14: Walk In
G15: Scott Svenson | H15: 4378645 | I15: Prospect | J15: Technician | L15: =TODAY()-15 -> 45937 | M15: Keep In View | N15: 45387 | O15: Low | P15: Y | Q15: =TODAY()+5 -> 45957 | U15: CT171 | W15: Kim Walton | X15: Keystone | Y15: Grand Anse | AA15: LD24-0070 | AJ15: Referal
G16: Samuel Hill | H16: 2514231 | I16: Contact | J16: Payroll Officier | K16: SPTC | U16: CT170 | W16: Samantha Dopilo | Y16: Mont Fleuri | AA16: LD24-0073
G17: Kaste McEwan | H17: 2765887 | I17: Prospect | J17: Boat Charter | K17: Inter Island Boats | L17: =TODAY()-33 -> 45919 | M17: Proposal Made | N17: 45439 | O17: Medium | P17: Y | Q17: =TODAY()+9 -> 45961 | U17: CT169 | W17: Trevor Crusher | X17: Keystone | Y17: Beau Vallon | AA17: LD24-0072 | AJ17: Referal
G18: Mary Trader | H18: 4373234 | I18: Prospect | J18: Tecnician | L18: =TODAY()-40 -> 45912 | M18: Proposal Made | N18: 45432 | O18: Low | P18: Y | Q18: =TODAY()+11 -> 45963 | U18: CT168 | X18: Keystone | Y18: Providence | AA18: LD24-0071 | AJ18: Walk In
G19: Emilie LaCruz | H19: 4378645 | I19: Contact | J19: Paymaster | U19: CT167 | X19: Keystone | Y19: Grand Anse | AA19: LD24-0070 | AJ19: Direct
G20: Damien Kinmo | H20: 2787653 | I20: Lead | J20: Human Resources Manager | K20: Avani Hotel | L20: =TODAY()-44 -> 45908 | M20: Differed | N20: 30602 | O20: Warm | P20: Y | Q20: =TODAY()+11 -> 45963 | U20: CT166 | X20: Keystone | Y20: Anse Aux Pins | AA20: LD24-0069 | AJ20: Direct

Sheet VL
E2: Contact - Wanda Lucas
E6: CONTACT DETAILS | K6: OTHER DETAILS | O6: PROSPECT DETAILS | T6: LEAD STATUS
E8: Contact Type | F8: Prospect | K8: Date Of Birth | L8: 29460 | O8: Savings Budget | Q8: 1000 | T8: Date Acquired | U8: 45774
E10: Mobile No | F10: 2511611 | K10: Occupation | L10: Driver | O10: Children | Q10: Alex | T10: Contact Status | U10: Qualified
E12: Contact No | F12: 4423212 | K12: Employer | L12: Cable & Wireless | T12: Rank | U12: VIP
E14: Email Address | K14: Source | L14: Referal | O14: Vehicle House Business | T14: 1st Contcat | U14: 45777
E16: Address | F16: Anse Boileau | K16: Source Name | L16: Blake Seven | O16: Other | T16: Next Follow Up | U16: =TODAY()+1 -> 45953
E21: Follow Ups

Sheet EL
E2: Contact - Wanda Lucas - Edit
E6: CONTACT DETAILS | K6: OTHER DETAILS | P6: PROSPECT DETAILS | T6: LEAD STATUS
E8: Contact Type | F8: Prospect | K8: Date Of Birth | L8: 29460 | P8: Savings Budget | R8: 1000 | T8: Date Acquired | U8: 45774
E10: Mobile No | F10: 2511611 | K10: Occupation | L10: Driver | P10: Children | R10: Alex | T10: Contact Status | U10: Qualified
E12: Contact No | F12: 4423212 | K12: Employer | L12: Cable & Wireless | T12: Rank | U12: VIP
E14: Email Address | K14: Source | L14: Referal | P14: Vehicle House Business | T14: 1st Contcat | U14: 45777
E16: Address | F16: Anse Boileau | K16: Source Name | L16: Blake Seven | P16: Other | T16: Next Follow Up | U16: =TODAY()+1 -> 45953
E21: Follow Ups

Sheet VLn
E2: Contact - Barry Walters
E6: CONTACT DETAILS | K6: OTHER DETAILS | O6: PROSPECT DETAILS | T6: LEAD MANAGEMENT
E8: Contact Type | F8: Lead | K8: Date Of Birth | O8: Savings Budget | Q8: 1000 | T8: Date Acquired | U8: =TODAY() -> 45952
E10: Mobile No | F10: 2526543 | K10: Occupation | O10: Children | Q10: Alex | T10: Contact Status | U10: Not Contacted
E12: Contact No | F12: Glacis | K12: Employer | T12: 1st Contacted | U12: =U8+3 -> 45955
E14: Email Address | K14: Source | O14: Vehicles House | R14: Business | T14: Rank | U14: Medium
E16: Address | F16: Fisherman | K16: Source Name | O16: Other | T16: Next Follow Up
E21: Follow Ups

Sheet LC
E2: Clients
E4: Records Found - 143
F6: Action | G6: Client Name | H6: Client Name | I6: Client Name | J6: Client Type | K6: NIN/BCRN | L6: DOB/DOR | M6: MobileNo | N6: WA | O6: District | P6: Occupation | Q6: Source | R6: Status | U6: Signed Up | V6: Employer | W6: CLID | X6: Contact Person | Y6: Income Source | Z6: Married | AA6: Spouses Name | AB6: Alternate No | AC6: Email Address | AD6: Location | AE6: Island | AF6: Country | AG6: P.O. Box No | AH6: PEP | AI6: PEP Comment | AJ6: Image | AK6: Salutation | AL6: First Name | AM6: Other Names | AN6: Surname | AO6: Passport No
G7: 1 | I7: Jean Grey | J7: Individual | K7: 971-0122-1-0-56 | L7: 26182 | M7: 2511611 | O7: Beau Vallon | P7: Accountant | Q7: Direct | R7: Active | U7: =TODAY()-320 -> 45632 | V7: SeyBake | W7: CL99 | Y7: Salary | Z7: No | AD7: Rose Estate | AE7: Mahe | AF7: Seychelles | AH7: No
G8: 2 | I8: Island Tours (Pty) Ltd | J8: Company | K8: C757372 | L8: 42866 | M8: 4373234 | O8: Providence | P8: Tour Guide Services | Q8: Direct | R8: Active | U8: =TODAY()-325 -> 45627 | V8: Inter Island Boats | W8: CL98 | Y8: Salary | Z8: No | AE8: Mahe | AF8: Seychelles | AH8: No
G9: 3 | I9: Agricultural Corporative | J9: Business | K9: B645728 | L9: 41447 | M9: 4378645 | O9: Grand Anse | P9: Agricultural Research | Q9: Referal | R9: Dormant | U9: =TODAY()+10 -> 45962 | W9: CL97 | X9: Chang Wong | AE9: Praslin | AF9: Seychelles | AH9: No
G10: 4 | I10: Atom Imports | J10: Business | K10: B43542 | L10: 43170 | M10: 4384056 | O10: Anse Etoile | P10: Retailer | Q10: Walk In | R10: Active | U10: =TODAY()+14 -> 45966 | W10: CL133 | X10: Walter Spark | Z10: No | AE10: Mahe | AF10: Seychelles | AH10: No
G11: 5 | I11: Andy Kramer | J11: Individual | K11: 974-0064-1-1-23 | L11: 2643234 | M11: 2765887 | O11: Grand Barb | P11: Boat Skipper | Q11: Direct | R11: Active | U11: =TODAY()-370 -> 45582 | V11: Inter Island Boats | W11: CL93 | Y11: Salary | Z11: Yes | AA11: Helen Kramer | AE11: Silhouette | AF11: Seychelles | AH11: No
G12: 6 | I12: Bradon Sony | J12: Individual | K12: 004-0022-1-1-76 | L12: 30602 | M12: 2787653 | O12: Anse Aux Pins | P12: Human Resources Manager | Q12: Direct | R12: Active | U12: =TODAY()-330 -> 45622 | V12: Avani Hotel | W12: CL94 | Y12: Salary | Z12: No | AD12: Reef Estate | AE12: Mahe | AF12: Seychelles | AH12: No
G13: 7 | I13: Brian Trapper | J13: Individual | K13: 993-0099-1-1-33 | L13: 32740 | M13: 2514231 | O13: Mont Fleuri | P13: Bus Driver | Q13: Walk In | R13: Dormant | U13: =TODAY()-70 -> 45882 | V13: SPTC | W13: CL88 | Z13: No | AE13: Mahe | AF13: Seychelles | AH13: No
G14: 8 | I14: Clive Bird | J14: Individual | K14: 954-0023-1-1-32 | L14: 26182 | M14: 2554365 | O14: Foret Noire | P14: Accountant | Q14: Direct | R14: Active | U14: =TODAY()-310 -> 45642 | V14: Bird Island | W14: CL103 | Z14: No | AE14: Mahe | AF14: Seychelles | AH14: No
G15: 9 | I15: Island Taste | J15: Business | K15: B645728 | L15: 42908 | M15: 4378645 | O15: Grand Anse | P15: Take Away | Q15: Referal | R15: Active | U15: =TODAY()-280 -> 45672 | W15: CL105 | X15: Sue kalida | AE15: Mahe | AF15: Seychelles | AH15: No
G16: 10 | I16: Ken Charters | J16: Business | K16: B075643 | L16: 26182 | M16: 4665321 | O16: La Passe | P16: Boat Charter | Q16: Direct | R16: Active | U16: =TODAY()-150 -> 45802 | W16: CL106 | X16: Ken Sommers | AE16: La Digue | AF16: Seychelles | AH16: No
G17: 11 | I17: Sam's Spa | J17: Business | K17: B075643 | L17: 26182 | M17: 4665321 | O17: Victoria | P17: Wellness Center | Q17: Direct | R17: Active | X17: Samantha Lang | AD17: Tobruk Club | AF17: Seychelles | AH17: No
G18: 12 | I18: Siloso (Pty) Ltd | J18: Company | K18: C757372 | L18: 2717171 | M18: 4373234 | O18: Providence | P18: Shop & Office Rentals | Q18: Walk In | R18: Active | X18: Barry Blade | AF18: Seychelles | AH18: No
G19: 13 | I19: Thomas Ball | J19: Individual | K19: 993-0099-1-1-33 | L19: 32740 | M19: 2514231 | O19: Mont Fleuri | P19: Bus Driver | Q19: Walk In | R19: Dormant | V19: SPTC | Z19: No | AF19: Seychelles | AH19: No
G20: 14 | I20: Thomas Samson | J20: Individual | K20: 978-0097-1-1-80 | L20: 2643234 | M20: 2765432 | O20: Beau Vallon | P20: Customer Service Officer | Q20: Referal | R20: Active | V20: AIRTEL | Z20: No | AF20: Seychelles | AH20: No
Z21: Yes | AF21: Seychelles | AH21: No

Sheet IE
E2: Expired IDs
E4: Records Found - 1
F6: Client Name | G6: ID Type | H6: Expiry Date | I6: Status | J6: MobileNo | K6: WA | L6: Alternate No | M6: Address | N6: District | O6: Occupation | P6: Employer | S6: Signed Up | T6: Employer | U6: CLID | V6: Contact Person | W6: Income Source | X6: Married | Y6: Spouses Name | Z6: Alternate No | AA6: Email Address | AB6: Location | AC6: Island | AD6: Country | AE6: P.O. Box No | AF6: PEP | AG6: PEP Comment | AH6: Image | AI6: Salutation | AJ6: First Name | AK6: Other Names | AL6: Surname | AM6: Passport No
F7: Jean Grey | G7: ID Card | H7: =TODAY()-2 -> 45950 | I7: =IF(H7<TODAY(),"Expired","") -> Expired | J7: 2511611 | M7: Panorama Estate | N7: Beau Vallon | O7: Accountant | P7: SayBake | S7: =TODAY()-320 -> 45632 | T7: SeyBake | U7: CL99 | W7: Salary | X7: No | AB7: Rose Estate | AC7: Mahe | AD7: Seychelles | AF7: No
S8: =TODAY()-325 -> 45627 | T8: Inter Island Boats | U8: CL98 | W8: Salary | X8: No | AC8: Mahe | AD8: Seychelles | AF8: No
S9: =TODAY()+10 -> 45962 | U9: CL97 | V9: Chang Wong | AC9: Praslin | AD9: Seychelles | AF9: No
S10: =TODAY()+14 -> 45966 | U10: CL133 | V10: Walter Spark | X10: No | AC10: Mahe | AD10: Seychelles | AF10: No
S11: =TODAY()-370 -> 45582 | T11: Inter Island Boats | U11: CL93 | W11: Salary | X11: Yes | Y11: Helen Kramer | AC11: Silhouette | AD11: Seychelles | AF11: No
S12: =TODAY()-330 -> 45622 | T12: Avani Hotel | U12: CL94 | W12: Salary | X12: No | AB12: Reef Estate | AC12: Mahe | AD12: Seychelles | AF12: No
S13: =TODAY()-70 -> 45882 | T13: SPTC | U13: CL88 | X13: No | AC13: Mahe | AD13: Seychelles | AF13: No
S14: =TODAY()-310 -> 45642 | T14: Bird Island | U14: CL103 | X14: No | AC14: Mahe | AD14: Seychelles | AF14: No
S15: =TODAY()-280 -> 45672 | U15: CL105 | V15: Sue kalida | AC15: Mahe | AD15: Seychelles | AF15: No
S16: =TODAY()-150 -> 45802 | U16: CL106 | V16: Ken Sommers | AC16: La Digue | AD16: Seychelles | AF16: No
V17: Samantha Lang | AB17: Tobruk Club | AD17: Seychelles | AF17: No
V18: Barry Blade | AD18: Seychelles | AF18: No
T19: SPTC | X19: No | AD19: Seychelles | AF19: No
T20: AIRTEL | X20: No | AD20: Seychelles | AF20: No
X21: Yes | AD21: Seychelles | AF21: No

Sheet FUC
E2: Clients
E4: Records Found - 143
F6: Action | G6: Client Name | H6: Client Name | I6: Client Name | J6: Client Type | K6: NIN/BCRN | L6: DOB/DOR | M6: MobileNo | N6: WA | O6: District | P6: Occupation | Q6: Source | R6: Status | V6: Signed Up | W6: Employer | X6: CLID | Y6: Contact Person | Z6: Income Source | AA6: Married | AB6: Spouses Name | AC6: Children | AD6: Children Details | AE6: Alternate No | AF6: Email Address | AG6: Location | AH6: Island | AI6: Country | AJ6: P.O. Box No | AK6: PEP | AL6: PEP Comment | AM6: Image | AN6: Salutation | AO6: First Name | AP6: Other Names | AQ6: Surname | AR6: Passport No | AS6: PIC | AT6: Industry
G7: 1 | I7: Jean Grey | J7: Individual | K7: 971-0122-1-0-56 | L7: 26182 | M7: 2511611 | O7: Beau Vallon | P7: Accountant | Q7: Direct | R7: Active | V7: =TODAY()-320 -> 45632 | W7: SeyBake | X7: CL99 | Z7: Salary | AA7: No | AG7: Rose Estate | AH7: Mahe | AI7: Seychelles | AK7: No | AS7: SEY
G8: 2 | I8: Island Tours (Pty) Ltd | J8: Company | K8: C757372 | L8: 42866 | M8: 4373234 | O8: Providence | P8: Tour Guide Services | Q8: Direct | R8: Active | V8: =TODAY()-325 -> 45627 | W8: Inter Island Boats | X8: CL98 | Z8: Salary | AA8: No | AH8: Mahe | AI8: Seychelles | AK8: No | AS8: SEY
G9: 3 | I9: Agricultural Corporative | J9: Business | K9: B645728 | L9: 41447 | M9: 4378645 | O9: Grand Anse | P9: Agricultural Research | Q9: Referal | R9: Dormant | V9: =TODAY()+10 -> 45962 | X9: CL97 | Y9: Chang Wong | AH9: Praslin | AI9: Seychelles | AK9: No
G10: 4 | I10: Atom Imports | J10: Business | K10: B43542 | L10: 43170 | M10: 4384056 | O10: Anse Etoile | P10: Retailer | Q10: Walk In | R10: Active | V10: =TODAY()+14 -> 45966 | X10: CL133 | Y10: Walter Spark | AA10: No | AH10: Mahe | AI10: Seychelles | AK10: No
G11: 5 | I11: Andy Kramer | J11: Individual | K11: 974-0064-1-1-23 | L11: 2643234 | M11: 2765887 | O11: Grand Barb | P11: Boat Skipper | Q11: Direct | R11: Active | V11: =TODAY()-370 -> 45582 | W11: Inter Island Boats | X11: CL93 | Z11: Salary | AA11: Yes | AB11: Helen Kramer | AH11: Silhouette | AI11: Seychelles | AK11: No
G12: 6 | I12: Bradon Sony | J12: Individual | K12: 004-0022-1-1-76 | L12: 30602 | M12: 2787653 | O12: Anse Aux Pins | P12: Human Resources Manager | Q12: Direct | R12: Active | V12: =TODAY()-330 -> 45622 | W12: Avani Hotel | X12: CL94 | Z12: Salary | AA12: No | AG12: Reef Estate | AH12: Mahe | AI12: Seychelles | AK12: No
G13: 7 | I13: Brian Trapper | J13: Individual | K13: 993-0099-1-1-33 | L13: 32740 | M13: 2514231 | O13: Mont Fleuri | P13: Bus Driver | Q13: Walk In | R13: Dormant | V13: =TODAY()-70 -> 45882 | W13: SPTC | X13: CL88 | AA13: No | AH13: Mahe | AI13: Seychelles | AK13: No
G14: 8 | I14: Clive Bird | J14: Individual | K14: 954-0023-1-1-32 | L14: 26182 | M14: 2554365 | O14: Foret Noire | P14: Accountant | Q14: Direct | R14: Active | V14: =TODAY()-310 -> 45642 | W14: Bird Island | X14: CL103 | AA14: No | AH14: Mahe | AI14: Seychelles | AK14: No
G15: 9 | I15: Island Taste | J15: Business | K15: B645728 | L15: 42908 | M15: 4378645 | O15: Grand Anse | P15: Take Away | Q15: Referal | R15: Active | V15: =TODAY()-280 -> 45672 | X15: CL105 | Y15: Sue kalida | AH15: Mahe | AI15: Seychelles | AK15: No
G16: 10 | I16: Ken Charters | J16: Business | K16: B075643 | L16: 26182 | M16: 4665321 | O16: La Passe | P16: Boat Charter | Q16: Direct | R16: Active | V16: =TODAY()-150 -> 45802 | X16: CL106 | Y16: Ken Sommers | AH16: La Digue | AI16: Seychelles | AK16: No
G17: 11 | I17: Sam's Spa | J17: Business | K17: B075643 | L17: 26182 | M17: 4665321 | O17: Victoria | P17: Wellness Center | Q17: Direct | R17: Active | Y17: Samantha Lang | AG17: Tobruk Club | AI17: Seychelles | AK17: No
G18: 12 | I18: Siloso (Pty) Ltd | J18: Company | K18: C757372 | L18: 2717171 | M18: 4373234 | O18: Providence | P18: Shop & Office Rentals | Q18: Walk In | R18: Active | Y18: Barry Blade | AI18: Seychelles | AK18: No
G19: 13 | I19: Thomas Ball | J19: Individual | K19: 993-0099-1-1-33 | L19: 32740 | M19: 2514231 | O19: Mont Fleuri | P19: Bus Driver | Q19: Walk In | R19: Dormant | W19: SPTC | AA19: No | AI19: Seychelles | AK19: No
G20: 14 | I20: Thomas Samson | J20: Individual | K20: 978-0097-1-1-80 | L20: 2643234 | M20: 2765432 | O20: Beau Vallon | P20: Customer Service Officer | Q20: Referal | R20: Active | W20: AIRTEL | AA20: No | AI20: Seychelles | AK20: No
AA21: Yes | AI21: Seychelles | AK21: No

Sheet LCB
E2: Birthdays Today
E4: Records Found - 1
F6: Client Name | G6: DOB | H6: Age | I6: MobileNo | J6: WA | K6: Alternate No | L6: Email Address | M6: District | N6: Occupation | O6: Wished | P6: Medium | S6: Signed Up | T6: Employer | U6: CLID | V6: Contact Person | W6: Income Source | X6: Married | Y6: Spouses Name | Z6: Children | AA6: Children Details | AB6: Alternate No | AC6: Email Address | AD6: Location | AE6: Island | AF6: Country | AG6: P.O. Box No | AH6: PEP | AI6: PEP Comment | AJ6: Image | AK6: Salutation | AL6: First Name | AM6: Other Names | AN6: Surname | AO6: Passport No | AP6: PIC | AQ6: Industry
F7: Samantha Trent | G7: =TODAY()-19723.25 -> 26228.75 | H7: =(TODAY()-G7)/365.25 -> 53.999316 | I7: 2511611 | K7: 2511611 | M7: Beau Vallon | N7: Accountant | P7: WA Msg | S7: =TODAY()-320 -> 45632 | T7: SeyBake | U7: CL99 | W7: Salary | X7: No | AD7: Rose Estate | AE7: Mahe | AF7: Seychelles | AH7: No | AP7: SEY
S8: =TODAY()-325 -> 45627 | T8: Inter Island Boats | U8: CL98 | W8: Salary | X8: No | AE8: Mahe | AF8: Seychelles | AH8: No | AP8: SEY
S9: =TODAY()+10 -> 45962 | U9: CL97 | V9: Chang Wong | AE9: Praslin | AF9: Seychelles | AH9: No
S10: =TODAY()+14 -> 45966 | U10: CL133 | V10: Walter Spark | X10: No | AE10: Mahe | AF10: Seychelles | AH10: No
S11: =TODAY()-370 -> 45582 | T11: Inter Island Boats | U11: CL93 | W11: Salary | X11: Yes | Y11: Helen Kramer | AE11: Silhouette | AF11: Seychelles | AH11: No
S12: =TODAY()-330 -> 45622 | T12: Avani Hotel | U12: CL94 | W12: Salary | X12: No | AD12: Reef Estate | AE12: Mahe | AF12: Seychelles | AH12: No
S13: =TODAY()-70 -> 45882 | T13: SPTC | U13: CL88 | X13: No | AE13: Mahe | AF13: Seychelles | AH13: No
S14: =TODAY()-310 -> 45642 | T14: Bird Island | U14: CL103 | X14: No | AE14: Mahe | AF14: Seychelles | AH14: No
S15: =TODAY()-280 -> 45672 | U15: CL105 | V15: Sue kalida | AE15: Mahe | AF15: Seychelles | AH15: No
S16: =TODAY()-150 -> 45802 | U16: CL106 | V16: Ken Sommers | AE16: La Digue | AF16: Seychelles | AH16: No
V17: Samantha Lang | AD17: Tobruk Club | AF17: Seychelles | AH17: No
V18: Barry Blade | AF18: Seychelles | AH18: No
T19: SPTC | X19: No | AF19: Seychelles | AH19: No
T20: AIRTEL | X20: No | AF20: Seychelles | AH20: No
X21: Yes | AF21: Seychelles | AH21: No

Sheet AC
D2: Client - Add New
D4: Client Type | H4: Name | L4: Surname | N4: Other Names | R4: Salutation
D5: Individual
D6: DOB | H6: NIN | L6: ID Document Type | N6: ID Expiry Date | R6: Income Source
A8: 4 | D8: Monthly Income | H8: Occupation | L8: Employer | N8: Married | R8: Spouse's Name
D10: PEP | H10: PEP Details | N10: Passport No | R10: Issuing Country
R11: Seychelles SEY
D12: Mobile No | H12: On Wattsapp | L12: Alternate No | N12: Email Address | R12: P.O. Box Number
D14: District | H14: Location | L14: Island | N14: Country | R14: Notes
D16: Sign Up Date | H16: Agency | L16: Agent | N16: Source
N18: Source Name
D19: Insurables | E19: Vehicle House Business Boat
D22: Documents

Sheet acx
D2: Client - Add New
D4: Client Type | H4: Name | L4: Surname | P4: Other Names | T4: Salutation
D5: Individual
D6: DOB | H6: NIN | L6: ID Document Type | P6: ID Expiry Date | T6: Passport No | X6: Issuing Country
T7: N9687387 | X7: Seychelles | Z7: SEY
A8: 4 | D8: Income Source | H8: Monthly Income | L8: Occupation | P8: Employer | T8: Married | X8: Spouse's Name
D10: PEP | E10: PEP Details
D12: Mobile No | H12: Wattsapp | L12: Alternate No | P12: Email Address | T12: P.O. Box Number
D14: District | H14: Location | L14: Island | P14: Country | T14: Notes
D16: Sign Up Date | H16: Agency | L16: Agent | P16: Source
P18: Source Name
D19: Insurables | F19: Vehicle House Business Boat
D22: Documents

Sheet ACE
D2: Client - Add New
D4: Client Type | H4: Name | L4: BCRN | N4: Contact Person | R4: Designation
D5: Business
D6: Mobile No | H6: Wattsapp | L6: Alternate No | N6: Email address | R6: P.O. Box Location
A8: 4 | D8: District | H8: Location | L8: Island | N8: Country | R8: Notes
D10: Sign Up Date | H10: Agency | L10: Agent | N10: Source
N12: Source Name
D13: Insurables | E13: Vehicle Home Business Boat
D17: Documents

Sheet VBC
E2: Client - Island Tours (Pty) Ltd
E6: CUSTOMER DETAILS | M6: CONTACT DETAILS | R6: ADDRESS DETAILS | X6: OTHER DETAILS
E8: Client Type | H8: Company | M8: Mobile No | O8: 2711511 | R8: District | T8: Beau Vallon | X8: Sign Up Date | Z8: 44193
E10: DOB/DOR | H10: 44070 | K10: =(TODAY()-H10)/365.25 -> 5.1526352 | M10: Alternate No No | R10: Address Location | T10: Mare Anglaise | X10: Source | Z10: Direct
E12: NIN/BCRN | H12: C8428891 | M12: Email Address | O12: keystone.sey@gmail.com | R12: Location | T12: Mahe | X12: Source Name
E14: ID Expiry Date | H14: =TODAY()+33 -> 45985 | M14: Contact Person | O14: Hilda Valdo | R14: Country | T14: Seychelles | X14: Agency
E16: Client Status | H16: Active | M16: Designation | O16: Managing Director | R16: P.O. Box No | T16: 777, Victoria, Mahe | X16: Agent
E19: Documents
E22: COI AOA MOA POD POA ID-Thomas ID-Wendy ID-Travis

Sheet VBCx
E2: Client - Island Tours (Pty) Ltd
E6: CUSTOMER DETAILS | M6: CONTACT DETAILS | R6: ADDRESS DETAILS | X6: OTHER DETAILS
E8: Client Type | M8: Mobile No | R8: District | X8: Sign Up Date
E9: Company | M9: 2711511 | R9: Beau Vallon | X9: 44193
E10: DOB/DOR | M10: Alternate No No | R10: Address Location | X10: Source
E11: 44070 | K11: =(TODAY()-E11)/365.25 -> 5.1526352 | R11: Mare Anglaise | X11: Direct
E12: NIN/BCRN | M12: Email Address | R12: Location | X12: Source Name
E13: C8428891 | M13: keystone.sey@gmail.com | R13: Mahe
E14: ID Expiry Date | M14: Contact Person | R14: Country | X14: Agency
E15: =TODAY()+33 -> 45985 | M15: Hilda Valdo | R15: Seychelles
E16: Client Status | M16: Designation | R16: P.O. Box No | X16: Agent
E17: Active | M17: Managing Director | R17: 777, Victoria, Mahe
E20: Documents
E23: COI AOA MOA POD POA ID-Thomas ID-Wendy ID-Travis

Sheet VC
E2: Client - Jean Grey
E6: CUSTOMER DETAILS | K6: CONTACT DETAILS | O6: ADDRESS DETAILS | S6: REGISTRATION DETAILS
E8: Client Type | F8: Individual | K8: Mobile No | L8: 2564321 | O8: District | Q8: Beau Vallon | S8: Sign Up Date | U8: 40807
E10: DOB/DOR | F10: 26182 | I10: =(TODAY()-F10)/365.25 -> 54.12731 | K10: On Wattsapp | O10: Address | Q10: Mare Anglaise | S10: Agency | U10: Keystone
E12: NIN/BCRN | F12: 971-0122-1-0-56 | K12: Alternate No | L12: 4323232 | O12: Island | Q12: Mahe | S12: Agent | U12: Mandy
E14: ID Expiry Date | F14: =TODAY()+33 -> 45985 | I14: =F14-TODAY() -> 33 | K14: Email Address | L14: jeangrey@gmail.com | O14: Country | Q14: Seychelles | S14: Source | U14: Referal
E16: Client Status | F16: Active | K16: Contact Person | O16: P.O. Box No | Q16: 1244, Victoria, Mahe | S16: Source Name | U16: Yvon Thorn
E18: INDIVIDUAL DETAILS | K18: INCOME DETAILS | O18: OTHER DETAILS | S18: INSURABLES
E20: Salutation | F20: Mrs | K20: Occupation | L20: Accountant | O20: Married | S20: Vehicle House Business
E22: First Name | F22: Jean | K22: Income Source | L22: Employment | O22: Spouse's Name | Q22: Warren Grey | S22: Boat
E24: Other Names | F24: Christine Stephanie Ellie | K24: Employer | L24: SeyBake | O24: PEP | Q24: PEP Details | S24: Notes
E26: Surname | F26: Grey | K26: Monthly Income | L26: 10,000 to 20,000 | O26: Married to minister Parker
E28: Passport No | F28: N9687387 | I28: SEY
E31: Documents
E35: ID Card | F35: Proof Of Address

Sheet Sheet4
E2: Client - Jean Grey
E6: CUSTOMER DETAILS | K6: CONTACT DETAILS | O6: ADDRESS DETAILS | S6: REGISTRATION DETAILS
E8: Client Type | F8: Individual | K8: Mobile No | L8: 2564321 | O8: District | Q8: Beau Vallon | S8: Sign Up Date | U8: 40807
E10: DOB/DOR | F10: 26182 | I10: =(TODAY()-F10)/365.25 -> 54.12731 | K10: On Wattsapp | O10: Address | Q10: Mare Anglaise | S10: Agency | U10: Keystone
E12: NIN/BCRN | F12: 971-0122-1-0-56 | K12: Alternate No | L12: 4323232 | O12: Island | Q12: Mahe | S12: Agent | U12: Mandy
E14: ID Expiry Date | F14: =TODAY()+33 -> 45985 | I14: =F14-TODAY() -> 33 | K14: Email Address | L14: jeangrey@gmail.com | O14: Country | Q14: Seychelles | S14: Source | U14: Referal
E16: Client Status | F16: Active | K16: Contact Person | O16: P.O. Box No | Q16: 1244, Victoria, Mahe | S16: Source Name | U16: Yvon Thorn
E18: INDIVIDUAL DETAILS | K18: INCOME DETAILS | O18: OTHER DETAILS | S18: INSURABLES
E20: Salutation | F20: Mrs | K20: Occupation | L20: Accountant | O20: Married | S20: Vehicle House Business
E22: First Name | F22: Jean | K22: Income Source | L22: Employment | O22: Spouse's Name | Q22: Warren Grey | S22: Boat
E24: Other Names | F24: Christine Stephanie Ellie | K24: Employer | L24: SeyBake | O24: PEP | S24: Notes
E26: Surname | F26: Grey | K26: Monthly Income | L26: 10,000 to 20,000 | O26: PEP Details | Q26: Married to minister Parker
E28: Passport No | F28: SEY | G28: N9687387
E31: Documents
E35: ID Card | F35: Proof Of Address

Sheet ABOA
E2: Beneficial Owners
E4: Records Found - 3
F6: Action | G6: Full Name | H6: Full Name | I6: Full Name | J6: DOB | K6: Age | L6: NIN/Passport No | M6: Country | N6: Expiry Date | O6: Status | P6: Position | Q6: Shares | R6: PEP | S6: PEP Details | T6: Date Added | U6: Removed
G7: 1 | I7: Thomas Scalen | J7: 21685 | K7: =DATEDIF(J7,NOW(),"Y") -> 66 | L7: SWD8362829 | M7: Sweden | N7: =TODAY()-5 -> 45947 | O7: =IF(N7<TODAY(),"Expired","") -> Expired | P7: Director | Q7: 0.51 | R7: Y | S7: CEO of Central Bank | T7: 1462
G8: 2 | I8: Max Van Dem | J8: 26309 | K8: =DATEDIF(J8,NOW(),"Y") -> 53 | L8: N-6732882 | M8: Holland | N8: 47211 | P8: Director | Q8: 0.25 | T8: 1462
I9: Willis Samuels | J9: 28390 | K9: =DATEDIF(J9,NOW(),"Y") -> 48 | L9: 977-0128-1-0-24 | M9: Seychelles | N9: 46707 | P9: Shareholder | Q9: 0.24 | T9: 1462
E17: Documents
G19: PP | I19: ID Card ID Card | J19: ID Card

Sheet ABO
E2: Client - Island Tours (Pty) Ltd
E6: CUSTOMER DETAILS | M6: CONTACT DETAILS | R6: ADDRESS DETAILS | X6: OTHER DETAILS
E8: Client Type | H8: Company | M8: Mobile No | O8: 2711511 | R8: District | T8: Beau Vallon | X8: Sign Up Date | Z8: 44193
E10: DOB/DOR | H10: 44070 | K10: =(TODAY()-H10)/365.25 -> 5.1526352 | M10: Alternate No No | R10: Address Location | T10: Mare Anglaise | X10: Source | Z10: Direct
E12: NIN/BCRN | H12: C8428891 | M12: Email Address | O12: keystone.sey@gmail.com | R12: Location | T12: Mahe | X12: Source Name
E14: ID Expiry Date | H14: =TODAY()+33 -> 45985 | M14: Contact Person | O14: Hilda Valdo | R14: Country | T14: Seychelles | X14: Agency
E16: Client Status | H16: Active | M16: Designation | O16: Managing Director | R16: P.O. Box No | T16: 777, Victoria, Mahe | X16: Agent
E19: Documents
E23: COI | F23: AOA | H23: MOA | I23: POD&S | K23: POA | M23: ID Mandy | O23: ID Simon | P23: ID Adam

Sheet EC
E2: Client - Jean Grey
E6: CUSTOMER DETAILS | K6: CONTACT DETAILS | O6: ADDRESS DETAILS | S6: REGISTRATION DETAILS
E8: Client Type | F8: Individual | K8: Mobile No | L8: 2564321 | O8: District | Q8: Beau Vallon | S8: Sign Up Date | U8: 40807
E10: DOB/DOR | F10: 26182 | I10: =(TODAY()-F10)/365.25 -> 54.12731 | K10: On Wattsapp | O10: Address | Q10: Mare Anglaise | S10: Agency | U10: Keystone
E12: NIN/BCRN | F12: 971-0122-1-0-56 | K12: Alternate No | L12: 4323232 | O12: Island | Q12: Mahe | S12: Agent | U12: Mandy
E14: ID Expiry Date | F14: =TODAY()+33 -> 45985 | I14: =F14-TODAY() -> 33 | K14: Email Address | L14: jeangrey@gmail.com | O14: Country | Q14: Seychelles | S14: Source | U14: Referal
E16: Client Status | F16: Active | K16: Contact Person | O16: P.O. Box No | Q16: 1244, Victoria, Mahe | S16: Source Name | U16: Yvon Thorn
E18: INDIVIDUAL DETAILS | K18: INCOME DETAILS | O18: OTHER DETAILS | S18: INSURABLES
E20: Salutation | F20: Mrs | K20: Occupation | L20: Accountant | O20: Married | S20: Vehicle House Business
E22: First Name | F22: Jean | K22: Income Source | L22: Employment | O22: Spouse's Name | Q22: Warren Grey | S22: Boat
E24: Other Names | F24: Christine Stephanie Ellie | K24: Employer | L24: SeyBake | O24: PEP | S24: Notes
E26: Surname | F26: Grey | K26: Monthly Income | L26: 10,000 to 20,000 | O26: PEP Details | Q26: Married to minister Parker
E28: Passport No | F28: SEY | G28: N9687387
E31: Documents

Sheet Sheet2
D2: Client - Add New
D5: Client Type | F5: Salutation | H5: Name | L5: Surname | P5: Other Names | T5: Client Status
D6: Individual | F6: Mrs
D7: DOB | F7: Age | H7: NIN | L7: ID Document Type | P7: ID Expiry Date | R7: Days | T7: Passport No | V7: Country
T8: N654258 | V8: SEY
D9: Contact & Address Details
D10: Mobile No | F10: Wattsapp | H10: Alternate No | L10: Email Address | P10: P.O. Box No
D12: District | H12: Location | L12: Island | P12: Country
D14: Source Of Income
A15: 4 | D15: Income Source | H15: Occupation | L15: Employer | P15: Monthly Income
D17: PEP | H17: PEP Details | L17: Married | P17: Spouse's Name
D20: Insurables | E20: Vehicle House Business Boat
D21: Sign Up Date | H21: Agency | L21: Agent | P21: Source | T21: Source Name
D27: Documents
N28: Notes

Sheet Sheet1
C4: CT | D4: BENEFICIAL OWNERS | E4: DOB | F4: Age | G4: Country | H4: NIN/Passport No | I4: Shares | J4: Interest | K4: PEP | L4: PEP Details | M4: DateAdded | N4: Removed
C5: Mr | D5: Dominique Van De Startzan | E5: 33097 | F5: =(TODAY()-E5)/365.25 -> 35.195072 | G5: Sechelles | H5: 990-0012-1-1-23 | I5: 51 | J5: Director/Shareholder | K5: N | M5: 38241
C6: Mr | D6: Maxwell Maurice De St Claire | E6: 30262 | F6: =(TODAY()-E6)/365.25 -> 42.956879 | G6: Ukraine | H6: UKR84362743 | I6: 19 | J6: Director/Shareholder | K6: Y | L6: Brother Of Ukrainian Mins Of Defense | M6: 38241
C7: Mrs | D7: Samantha De Ville | E7: 30743 | F7: =(TODAY()-E7)/365.25 -> 41.639973 | G7: England | H7: GBR64738221 | I7: 15 | J7: Shareholder | K7: N | M7: 38241
C8: Mr | D8: Travis McGiven | E8: 25610 | F8: =(TODAY()-E8)/365.25 -> 55.693361 | G8: Scotish | H8: GBR17362888 | I8: 15 | J8: Shareholder | K8: N | M8: 38241

Sheet EBO
E2: Client - Island Tours (Pty) Ltd
E6: CUSTOMER DETAILS | L6: CONTACT DETAILS | Q6: ADDRESS DETAILS | V6: ACCOUNT DETAILS
E8: Client Type | G8: Company | L8: Mobile No | N8: 2711511 | Q8: District | S8: Beau Vallon | V8: Sign Up Date | X8: 44193
E10: DOB/DOR | G10: 44070 | J10: =(TODAY()-G10)/365.25 -> 5.1526352 | L10: Alternate No No | Q10: Address Location | S10: Mare Anglaise | V10: Source | X10: Direct
E12: NIN/BCRN | G12: C8428891 | L12: Email Address | N12: keystone.sey@gmail.com | Q12: Location | S12: Mahe | V12: Source Name
E14: ID Expiry Date | G14: =TODAY()+33 -> 45985 | L14: Contact Person | N14: Hilda Valdo | Q14: Country | S14: Seychelles | V14: Agency
E16: Client Status | G16: Active | L16: Designation | N16: Managing Director | Q16: P.O. Box No | S16: 777, Victoria, Mahe | V16: Agent
E19: Beneficial Owners
E30: Documents
E34: COI | F34: AOA | G34: MOA | H34: POD&S | J34: POA | L34: ID Mandy | N34: ID Simon | O34: ID Adam

Sheet LPFU
E2: Clients - To Follow Up
E4: Records Found - 2
F6: Action | G6: Client Name | H6: Client Name | I6: Client Name | J6: Client Type | K6: MobileNo | L6: Address | M6: Occupation | O6: Notification | P6: Date Due | Q6: Status | U6: Signed Up | V6: Contact Person | W6: Income Source | X6: Married | Y6: Spouses Name | Z6: Children | AA6: Children Details | AB6: Alternate No | AC6: Email Address | AD6: Location | AE6: State | AF6: Country | AG6: P.O. Box No | AH6: Agency | AI6: Agent | AJ6: PEP | AK6: PEP Comment | AL6: Image | AM6: Salutation | AN6: First Name | AO6: Other Names | AP6: Surname | AQ6: Passport No | AR6: PIC
G7: 1 | I7: Andy Kramer | J7: Individual | K7: 2765887 | L7: Grand Barb | M7: Boat Skipper | P7: Direct | Q7: Active | U7: =TODAY()-320 -> 45632 | W7: Salary | X7: No | AD7: Rose Estate | AE7: Mahe | AF7: Seychelles | AH7: Keystone | AI7: Mandy | AJ7: No | AR7: SEY
G8: 2 | I8: Siloso (Pty) Ltd | J8: Company | K8: 4373234 | L8: Providence | M8: Shop & Office Rentals | P8: Walk In | Q8: Active | U8: =TODAY()-325 -> 45627 | W8: Salary | X8: No | AE8: Mahe | AF8: Seychelles | AH8: Keystone | AI8: Mandy | AJ8: No | AR8: SEY
U9: =TODAY()+10 -> 45962 | V9: Chang Wong | AE9: Praslin | AF9: Seychelles | AH9: Keystone | AI9: Mandy | AJ9: No
U10: =TODAY()+14 -> 45966 | V10: Walter Spark | X10: No | AE10: Mahe | AF10: Seychelles | AH10: Keystone | AI10: Mandy | AJ10: No
U11: =TODAY()-370 -> 45582 | W11: Salary | X11: Yes | Y11: Helen Kramer | AE11: Silhouette | AF11: Seychelles | AH11: Keystone | AI11: Mandy | AJ11: No
U12: =TODAY()-330 -> 45622 | W12: Salary | X12: No | AD12: Reef Estate | AE12: Mahe | AF12: Seychelles | AH12: Keystone | AI12: Simon | AJ12: No
U13: =TODAY()-70 -> 45882 | X13: No | AE13: Mahe | AF13: Seychelles | AH13: Keystone | AI13: Simon | AJ13: No
U14: =TODAY()-310 -> 45642 | X14: No | AE14: Mahe | AF14: Seychelles | AH14: Keystone | AI14: Mandy | AJ14: No
U15: =TODAY()-280 -> 45672 | V15: Sue kalida | AE15: Mahe | AF15: Seychelles | AH15: Keystone | AI15: Mandy | AJ15: No
U16: =TODAY()-150 -> 45802 | V16: Ken Sommers | AE16: La Digue | AF16: Seychelles | AH16: Keystone | AI16: Mandy | AJ16: No
V17: Samantha Lang | AD17: Tobruk Club | AF17: Seychelles | AH17: Keystone | AI17: Mandy | AJ17: No
V18: Barry Blade | AF18: Seychelles | AH18: Keystone | AI18: Mandy | AJ18: No
X19: No | AF19: Seychelles | AH19: Keystone | AI19: Mandy | AJ19: No
X20: No | AF20: Seychelles | AH20: Keystone | AI20: Mandy | AJ20: No
X21: Yes | AF21: Seychelles | AH21: Keystone | AI21: Mandy | AJ21: No

Sheet VCP
E2: Policies - Jean Grey
E4: Records Found - 3
F6: Action | G6: Policy Number | H6: Policy Number | I6: Policy Number | J6: Insurer | K6: Class | L6: Insurance Plan | N6: Start Date | O6: End Date | P6: Total Premium | Q6: Base | R6: Insured Item | T6: Status
G7: 1 | I7: MPV-23-HEA-P0002132 | J7: SACOS | K7: Motor | L7: Comprehensive | N7: 45255 | O7: 45620 | P7: 11455.89 | Q7: =P7/1.16 -> 9875.7672 | R7: S4444 Suzuki Fronx | T7: In Force
G8: 2 | I8: FSP-21-P0003243 | J8: Hsavy | K8: General | L8: Fire & Special Perils | N8: 45180 | O8: 45545 | P8: 7830 | Q8: =P8/1.16 -> 6750 | R8: Office & Shop complex at Providence | T8: Expired
G9: 3 | I9: S012218 | J9: SACOS | K9: Life | L9: Endowment | N9: 43192 | O9: 13971 | P9: 1325 | Q9: =P9/1.16 -> 1142.2414 | T9: In Force

Sheet VCPP
E2: Payments - Jean Grey
E4: Records Found - 10
F6: Action | G6: Debit Note | H6: Debit Note | I6: Debit Note | J6: Payment Type | K6: Date Due | L6: Amount Due | M6: Status | N6: Amount Paid | O6: Date Paid | P6: Payment Mode | Q6: Cheque No | R6: Policy Number | S6: Comments
G7: 1 | I7: DN24100 | J7: Instalment | K7: 45640 | L7: 5727.9466 | M7: Unpaid | R7: MPV-23-HEA-P0002132
G8: 2 | I8: DN24099 | J8: Instalment | K8: 45610 | L8: 5727.9466 | M8: Paid | N8: 5727.9466 | O8: 45610 | P8: Cheque | Q8: NB0002413 | R8: MPV-23-HEA-P0002132
G9: 3 | I9: DN23078 | J9: Full payment | K9: 45219 | L9: 11455.893 | M9: Paid | N9: 11455.893 | O9: 45219 | P9: Transfer | R9: MPV-23-HEA-P0002132
G10: 4 | I10: DN22066 | J10: Full payment | K10: 44854 | L10: 12268.74 | M10: Paid | N10: 12268.74 | O10: 44854 | P10: Cheque | R10: MPV-23-HEA-P0002132
G11: 5 | I11: DN21061 | J11: Full payment | K11: 44488 | L11: 14383.095 | M11: Paid | N11: 14383.095 | O11: 44488 | P11: Cheque | R11: MPV-23-HEA-P0002132
G12: 6 | I12: DN24080 | J12: Full payment | K12: 45579 | L12: 7830 | M12: Paid | N12: 7830 | O12: 45579 | P12: Cheque | R12: FSP-21-P0003243
G13: 7 | I13: DN23075 | J13: Full payment | K13: 45213 | L13: 7830 | M13: Paid | N13: 7830 | O13: 45213 | P13: Cheque | R13: FSP-21-P0003244
G14: 8 | I14: DN22066 | J14: Full payment | K14: 44848 | L14: 7830 | M14: Paid | N14: 7830 | O14: 44848 | P14: Cheque | R14: FSP-21-P0003245
G15: 9 | I15: DN21055 | J15: Full payment | K15: 44483 | L15: 5727.9466 | M15: Paid | N15: 5727.9466 | O15: 44483 | P15: Cash | R15: FSP-21-P0003246
G16: 10 | I16: DN18072 | J16: Full payment | K16: 43162 | L16: 5727.9466 | M16: Paid | N16: 12679 | O16: 43162 | P16: Transfer | R16: HI-18-HEA-P0024251

Sheet VCPV
E2: Vehciles - Jean Grey
E4: Records Found - 4
F6: Action | G6: Regn No | H6: Regn No | I6: Regn No | J6: Make | K6: Model | L6: Type | M6: Useage | N6: Year | O6: Value | P6: Engine Type | Q6: Engine CC | R6: Chassis No | S6: Date Sold | T6: Policy Number | Y6: Engine No | Z6: Seating | AA6: Color
G7: 1 | I7: S4444 | J7: Suzuki | K7: Fronx | L7: SUV | M7: Private | N7: 2024 | O7: 360000 | P7: Hybrid | Q7: 1462 | R7: KB15HS67TT5 | T7: MPV-23-HEA-P0002132 | Z7: 5 | AA7: White
G8: 2 | I8: S32454 | J8: Suzuki | K8: Grand Vitara | L8: Sedan | M8: For Hire | N8: 2023 | O8: 1200000 | P8: Petrol | Q8: 3120 | R8: KB15HS6251G | S8: 44388 | T8: MPV-23-HEA-P0002132 | Z8: 5 | AA8: Red
G9: 3 | I9: S17234 | J9: Toyota | K9: Corolla | L9: Sedan | M9: Private | N9: 2015 | O9: 410000 | P9: Petrol | Q9: 1898 | R9: THJ6278GHGH6 | S9: 43172 | T9: MVC-15-HEA-P0001723 | Z9: 5 | AA9: Silver
G10: 4 | I10: S21214 | J10: Honda | K10: Accord | L10: Sedan | M10: Private | N10: 2012 | O10: 435000 | P10: Petrol | Q10: 1595 | R10: EH 6282HG 56 | S10: 42297 | T10: MVT-12-HEA-P0001123 | Z10: 5 | AA10: Red

Sheet VCPC
E2: Claims - Jean Grey
E4: Records Found - 2
F6: Action | G6: Claim No | H6: Claim No | I6: Claim No | J6: Policy No | K6: Loss Date | L6: Claim Date | M6: Claim Amount | N6: Claim Summary | Q6: Stage | R6: Status | S6: Amount Paid | T6: Date Paid | W6: Comment
G7: 1 | I7: CM18011 | J7: MPV-23-HEA-P0002132 | K7: 43177 | L7: 43178 | M7: 57654.88 | N7: Damage caused by accident with S32432 | Q7: Closed | R7: Paid Out | S7: 50654.88 | T7: 43205
G8: 2 | I8: CM18255 | J8: MPV-23-HEA-P0002132 | K8: 43360 | L8: 43360 | M8: 43567.25 | N8: Damage caused by accident with S17765 | Q8: Closed | R8: Paid Out | S8: 37567.25 | T8: 43378

Sheet LPrFU
E2: Proposals
E4: Records Found - 7
A6: 4 | F6: Action | G6: Proposer's Name | H6: Insurer | I6: Policy Plan | J6: Sum Assured | K6: Term | L6: Add Ons | M6: Offer Date | N6: Premium | O6: Freq | P6: Stage | Q6: Submitted | R6: Age | S6: Status | V6: Source Of Payment | W6: MCR | X6: Doctor | Y6: Date Sent | Z6: Date Completed | AA6: Notes | AB6: Agnecy | AC6: PRID | AD6: Class
G7: Trevor Scott | H7: Hsavy | I7: My Security | J7: 150000 | K7: 15 | L7: TPD FIBT | M7: 45848 | N7: 833 | O7: M | P7: Form Filled | R7: 9 | V7: Hunt Deltel | W7: N | AB7: KSB | AC7: PR25008 | AD7: Life
G8: Andy Moller | H8: SACOS | I8: Endowment | J8: 600000 | K8: 20 | M8: 45842 | N8: 788 | O8: M | P8: Form Filled | R8: 15 | V8: Policyholder | W8: N | AB8: KSB | AC8: PR25007 | AD8: Life
G9: Sylvie La Coadou | H9: Hsavy | I9: My Legacy | J9: 300000 | K9: 20 | L9: FIBT | M9: 45837 | N9: 1572 | O9: M | P9: Awaiting deposit | R9: 20 | S9: Awaiting deposit | V9: MCB | W9: Y | X9: Jivan | AA9: Hign BMI | AB9: KSB | AC9: PR25006 | AD9: Life
G10: Steven Drax | H10: SACOS | I10: SACOS Exclusive | J10: 150000 | K10: 21 | M10: 45828 | N10: 3332 | O10: M | P10: Awaiting POA | R10: 29 | V10: MCB | W10: N | AB10: KSB | AC10: PR25005 | AD10: Life
G11: Alistair Jacobs | H11: SACOS | I11: Endowment | J11: 180000 | K11: 22 | M11: 45828 | N11: 688 | O11: M | P11: Differred | R11: 29 | S11: Differred | V11: Nouvobanq | W11: N | AB11: LIS | AC11: PR25004 | AD11: Life
G12: Curtis Bradley | H12: SACOS | I12: SACOS Junior | J12: 250000 | K12: 20 | M12: 45826 | N12: 9968 | O12: A | P12: Awaiting deposit | V12: SEYPEC | W12: Y | X12: Chetty | AA12: Hypetension | AB12: LIS | AC12: PR25003 | AD12: Life
V13: Policyholder | W13: N | AB13: LIS | AC13: PR25002 | AD13: Life
V14: Airtel | W14: Y | X14: Murthy | AB14: LIS | AC14: PR25001 | AD14: Life
V15: Mins Of Finance | W15: N | AB15: LIS | AC15: PR24120 | AD15: Life
V16: Sey Brew | W16: N | AB16: LIS | AC16: PR24119 | AD16: Life
V17: Hunt Deltel | W17: Y | X17: Jivan | AA17: Gama GT outside norm | AB17: KSB | AC17: PR24118 | AD17: Life
V18: ABSA | W18: N | AB18: LIS | AC18: PR24117 | AD18: Life
V19: MCB | W19: Y | X19: Chetty | AB19: LIS | AC19: PR24116 | AD19: Life
V20: MCB | W20: Y | X20: Chetty | AB20: LIS | AC20: PR24115 | AD20: Life

Sheet LPrS
E2: Proposals - Submitted
E4: Records Found - 3
A6: 4 | F6: Action | G6: PRID | H6: Proposer's Name | I6: Insurer | J6: Class | K6: Policy Plan | L6: Sum Assured | M6: Term | N6: Period | O6: Premium | P6: Freq | Q6: Offer Date | R6: Ageing | S6: Submitted | T6: Status | V6: Stage | Y6: Source Of Payment
G7: PR25008 | H7: Wanda Lucas | I7: SACOS | J7: Life | K7: Special Endowment | L7: 200000 | M7: 20 | N7: Years | O7: 999 | P7: M | Q7: =TODAY()-6 -> 45946 | R7: =TODAY()-Q7 -> 6 | S7: =Q7+4 -> 45950 | T7: Awaiting Policy | V7: Processing | Y7: Policyholder
G8: PR25002 | H8: Daniel Blast | I8: Hsavy | J8: Life | K8: Endowment | L8: 200000 | M8: 15 | N8: Years | O8: 423 | P8: M | Q8: =TODAY()-20 -> 45932 | R8: =TODAY()-Q8 -> 20 | S8: =TODAY()-3 -> 45949 | T8: Awaiitng Medical | V8: Awaiting Medical | Y8: Airtel
G9: PR25001 | H9: Judy Wallace | I9: SACOS | J9: Life | K9: Double Security | L9: 400000 | M9: 20 | N9: Years | O9: 2433 | P9: M | Q9: =TODAY()-27 -> 45925 | R9: =TODAY()-Q9 -> 27 | S9: =TODAY()-7 -> 45945 | T9: Awaiting Medical | V9: Awaiting Medical | Y9: Mins Of Finance
V10: Awaiting POA | Y10: Sey Brew
V11: Processing | Y11: Hunt Deltel
V12: Processing | Y12: ABSA
V13: Processing | Y13: MCB
V14: Processing | Y14: MCB
V15: Processing

Sheet LPPr
E2: Proposals - To Follow Up
E4: Records Found - 1
A6: 4 | F6: Action | G6: Proposer's Name | H6: Class | I6: Policy Plan | J6: Insurer | K6: Term | L6: Period | M6: Sum Assured | N6: Premium | O6: Freq | P6: Offer Date | Q6: Ageing | R6: Status | S6: Submitted | T6: Stage | W6: Source Of Payment | X6: PRID
G7: Wanda Lucas | H7: Life | I7: Special Endowment | J7: SACOS | K7: 20 | L7: Years | M7: 200000 | N7: 999 | O7: M | P7: =TODAY()-6 -> 45946 | Q7: =TODAY()-P7 -> 6 | R7: Submitted | S7: 45682 | T7: Awaiting Medical | W7: Hunt Deltel | X7: PR25008
W8: Policyholder
W9: MCB
W10: MCB
W11: Nouvobanq
W12: SEYPEC
W13: Policyholder
W14: Airtel
W15: Mins Of Finance
W16: Sey Brew
W17: Hunt Deltel
W18: ABSA
W19: MCB
... W21: Policyholder

Sheet LPr
E2: Life Proposals
E4: Records Found - 17
A6: 4 | F6: Action | G6: Proposer's Name | H6: Insurer | I6: Policy Plan | J6: Sum Assured | K6: Term | L6: Add Ons | M6: Offer Date | N6: Premium | O6: Freq | P6: Stage | Q6: Date | R6: Age | S6: Status | V6: Source Of Payment | W6: MCR | X6: Doctor | Y6: Date Sent | Z6: Date Completed | AA6: Notes | AB6: Agnecy | AC6: PRID | AD6: Class
G7: Wanda Lucas | H7: SACOS | I7: Special Endowment | J7: 200000 | K7: 20 | M7: =TODAY()-6 -> 45946 | N7: 998 | O7: M | P7: Submitted | Q7: =TODAY()-2 -> 45950 | R7: =TODAY()-M7 -> 6 | S7: Awaiting Policy | V7: Hunt Deltel | W7: N | AB7: KSB | AC7: PR25008 | AD7: Life
G8: Trevor Scott | H8: Hsavy | I8: My Security | J8: 150000 | K8: 15 | L8: TPD FIBT | M8: =TODAY()-9 -> 45943 | N8: 833 | O8: M | P8: Form Filled | R8: =TODAY()-M8 -> 9 | V8: Policyholder | W8: N | AB8: KSB | AC8: PR25007 | AD8: Life
G9: Andy Moller | H9: SACOS | I9: Endowment | J9: 600000 | K9: 20 | M9: =TODAY()-15 -> 45937 | N9: 788 | O9: M | P9: Form Filled | R9: =TODAY()-M9 -> 15 | V9: MCB | W9: Y | X9: Jivan | AA9: Hign BMI | AB9: KSB | AC9: PR25006 | AD9: Life
G10: Sebastien Grey | H10: SACOS | I10: SACOS Special | J10: 100000 | K10: 25 | M10: =TODAY()-20 -> 45932 | N10: 503 | O10: M | P10: Awaiting deposit | R10: =TODAY()-M10 -> 20 | V10: MCB | W10: N | AB10: KSB | AC10: PR25005 | AD10: Life
G11: Anna Descours | H11: SACOS | I11: SACOS Junior | J11: 275000 | K11: 18 | M11: =TODAY()-20 -> 45932 | N11: 1183 | O11: M | P11: Awaiting deposit | R11: =TODAY()-M11 -> 20 | V11: Nouvobanq | W11: N | AB11: LIS | AC11: PR25004 | AD11: Life
G12: Sylvie La Coadou | H12: Hsavy | I12: My Legacy | J12: 300000 | K12: 20 | L12: FIBT | M12: =TODAY()-20 -> 45932 | N12: 1572 | O12: M | P12: Awaiting deposit | R12: =TODAY()-M12 -> 20 | V12: SEYPEC | W12: Y | X12: Chetty | AA12: Hypetension | AB12: LIS | AC12: PR25003 | AD12: Life
G13: Daniel Blast | H13: Hsavy | I13: Endowment | J13: 200000 | K13: 15 | M13: =TODAY()-20 -> 45932 | N13: 423 | O13: M | P13: Submitted | Q13: =TODAY()-3 -> 45949 | R13: =TODAY()-M13 -> 20 | S13: Awaiting Medical | V13: Policyholder | W13: N | AB13: LIS | AC13: PR25002 | AD13: Life
G14: Judy Wallace | H14: SACOS | I14: Double Security | J14: 400000 | K14: 20 | M14: =TODAY()-27 -> 45925 | N14: 2433 | O14: M | P14: Submitted | Q14: =TODAY()-7 -> 45945 | R14: =TODAY()-M14 -> 27 | S14: Awaiting Medical | V14: Airtel | W14: Y | X14: Murthy | AB14: LIS | AC14: PR25001 | AD14: Life
G15: Steven Drax | H15: SACOS | I15: SACOS Exclusive | J15: 150000 | K15: 21 | M15: =TODAY()-29 -> 45923 | N15: 3332 | O15: M | P15: Awaiting POA | R15: =TODAY()-M15 -> 29 | V15: Mins Of Finance | W15: N | AB15: LIS | AC15: PR24120 | AD15: Life
G16: Alistair Jacobs | H16: SACOS | I16: Endowment | J16: 180000 | K16: 22 | M16: =TODAY()-29 -> 45923 | N16: 688 | O16: M | P16: Differred | R16: =TODAY()-M16 -> 29 | V16: Sey Brew | W16: N | AB16: LIS | AC16: PR24119 | AD16: Life
G17: Emanuelle Maize | H17: SACOS | I17: Special Endowment | J17: 300000 | K17: 15 | L17: ADB | M17: =TODAY()-33 -> 45919 | N17: 1877 | O17: M | P17: Withdrawn | Q17: =TODAY()-15 -> 45937 | R17: =TODAY()-M17 -> 33 | S17: Withdrawn | V17: Hunt Deltel | W17: Y | X17: Jivan | AA17: Gama GT outside norm | AB17: KSB | AC17: PR24118 | AD17: Life
G18: Lucy Karlton | H18: SACOS | I18: SACOS Junior | J18: 100000 | K18: 19 | M18: =TODAY()-33 -> 45919 | N18: 498 | O18: M | P18: Submitted | Q18: =TODAY()-25 -> 45927 | R18: =TODAY()-M18 -> 33 | S18: Awaiting Medical | V18: ABSA | W18: N | AB18: LIS | AC18: PR24117 | AD18: Life
G19: Karlos Lobo | H19: SACOS | I19: Endowment | J19: 400000 | K19: 20 | L19: TPDWoP | M19: =TODAY()-37 -> 45915 | N19: 1966 | O19: M | P19: Declined | Q19: =TODAY()-35 -> 45917 | R19: =TODAY()-M19 -> 37 | S19: Declined | V19: MCB | W19: Y | X19: Chetty | AB19: LIS | AC19: PR24116 | AD19: Life
G20: Beth Mayer | H20: SACOS | I20: Mortgage | J20: 2500000 | K20: 15 | M20: =TODAY()-37 -> 45915 | N20: 35467 | O20: S | P20: Processing | Q20: =TODAY()-35 -> 45917 | R20: =TODAY()-M20 -> 37 | S20: Awaiting Policy | V20: MCB | W20: Y | X20: Chetty | AB20: LIS | AC20: PR24115 | AD20: Life

Sheet VPro
E2: Life Proposal - Wanda Lucas
E6: PROPOSED PLAN | K6: PROVISIONAL PAYMENT PLAN | O6: PROPOSAL STATUS | S6: MEDICAL DETAILS
E8: Insurer | F8: SACOS | K8: Pay Plan | L8: Monthly | O8: Offer Date | Q8: =TODAY()-6 -> 45946 | S8: Medical Required
E10: Policy Plan | F10: Special Endowment | K10: Base Premium | L10: 988 | O10: Proposal Stage | Q10: Submitted | S10: Clinic | T10: Jivan
E12: Term | F12: 20 | K12: Total Premium | L12: 998 | O12: Submitted Date | Q12: =Q8+4 -> 45950 | S12: Referred Date | T12: 45678
E14: Sum Assured | F14: 200000 | K14: Payment Method | L14: Salary Deduction | O14: Application Status | Q14: Awaiting Policy | S14: Completion Date | T14: 45684
E16: Add Ons | F16: TPD, FIBT | K16: Premium Source | L16: Hunt Deltel | O16: Close Date | Q16: =Q12+4 -> 45954 | S16: Exam Notes | T16: High BMI and asthmatric
E19: Documents

Sheet APro
D2: Life Proposal - New/Update
D4: Proposer's Details
D5: Proposer's Name | F5: Salutation | H5: DOB | J5: Insurer | L5: Policy Plan | P5: Term | R5: Sum Assured | T5: Age | U5: Sex | V5: ANB
D6: Wanda Lucas | F6: Mrs | H6: =VL!L8 -> 29460 | J6: SACOS | L6: Special Endowment | P6: 20 | R6: 1000000 | T6: =DATEDIF(LL!V7,TODAY(),"Y") -> 40 | U6: =IF(F6="Mr","M","F") -> F | V6: =IF(U6="M",T6+1,T6-2) -> 38
D8: Additional Riders | F8: ADB | H8: AcDB | J8: TPD | L8: TPDWoP | N8: FIBT | P8: FIBD | R8: CIB
D9: Rider Premiums | F9: 200 | H9: 135 | J9: 400 | L9: 500 | N9: 600 | P9: 1355 | R9: 800
D10: Annual Premium | T10: Total
D11: 6610 | J11: 400 | N11: 600 | T11: =D11+F11+H11+J11+L11+N11+P11+R11+L22 -> 8584
D12: Offer Date | F12: Proposal Stage | J12: Agency | N12: Source | R12: Source Name
D13: =TODAY()-15 -> 45937 | F13: Submitted | J13: Keystone | N13: Referal | R13: Travis Port-Louis
D14: Payment Plan
D15: Frequency Of Payment | F15: Method Of Payment | J15: Source Of Payment | N15: Base Premium | P15: Admin Fee | R15: Total Premium
D16: Monthly | F16: Salary Deduction | J16: Hunt Deltel | N16: =ROUND(0.0875*T11,0) -> 751 | P16: =ROUND(0.01*N16,0) -> 8 | R16: =N16+P16 -> 759
D17: Medical Examination Required?
D18: Clinic | F18: Date Referred | J18: Date Completed | N18: Exam Notes
D19: Jivan | F19: =TODAY()-5 -> 45947 | J19: =TODAY()-1 -> 45951 | N19: High BMI and Asthmatic
D20: Application Details
D21: Date | F21: Proposal Status | J21: Policy No | L21: Loading Premium | N21: Start Date | P21: Maturity Date
D22: =TODAY()-3 -> 45949 | F22: Awaiting Policy | J22: S007825 | L22: 974 | N22: =TODAY()-15 -> 45937 | P22: =N22+(365.25*P6)-1 -> 53241
D25: Documents

Sheet AProx
D2: Life Proposal - New/Update
D4: Proposer's Details
D5: Proposer's Name | H5: Salutation | K5: Insurer | O5: Policy Plan | T5: Sum Assured | W5: Term | Y5: Age | AA5: Gender | AC5: ANB - A
D6: Wanda Lucas | H6: Miss | K6: SACOS | O6: Special Endowment | T6: 1000000 | W6: 20 | Y6: =DATEDIF(LL!V7,TODAY(),"Y") -> 40 | AA6: =IF(H6="Mr","M","F") -> F | AC6: =IF(AA6="M",Y6+1,Y6-2) -> 38
D8: Additional Riders | F8: ADB | H8: AcDB | K8: TPD | M8: TPDWoP | O8: FIBT | R8: FIBD | T8: CIB | Y8: Notes
D9: Rider Premiums | F9: 200 | H9: 300 | K9: 400 | M9: 500 | O9: 600 | R9: 700 | T9: 800
D10: Annual Premium | V10: Total Premium
D11: 6610 | K11: 400 | O11: 600 | V11: =D11+F11+H11+K11+M11+O11+R11+T11+O22 -> 8378
D12: Offer Date | F12: Proposal Stage | K12: Agency | O12: Source | T12: Source Name
D13: =TODAY()-15 -> 45937 | F13: Submitted | K13: Keystone | O13: Referal | T13: Travis Port-Louis
D14: Payment Plan
D15: Frequency Of Payment | F15: Method Of Payment | K15: Source Of Payment | O15: Base Premium | R15: Admin Fee | T15: Total Premium
D16: Monthly | F16: Salary Deduction | K16: Hunt Deltel | O16: =ROUND(0.0875*V11,0) -> 733 | R16: =ROUND(0.01*O16,0) -> 7 | T16: =O16+R16 -> 740
D17: Medical Examination Required?
D18: Clinic | F18: Date Referred | K18: Date Completed | O18: Exam Notes
D19: Jivan | F19: =TODAY()-5 -> 45947 | K19: =TODAY()-1 -> 45951 | O19: High BMI and Asthmatic
D20: Application Details
D21: Date | F21: Proposal Status | K21: Policy No | O21: Loading Premium | T21: Start Date | Y21: Maturity Date
D22: =TODAY()-3 -> 45949 | F22: Awaiting Policy | K22: S007825 | O22: 768 | T22: =TODAY()-15 -> 45937 | Y22: =TODAY()+(365.25*W6) -> 53257
D25: Documents

Sheet GLP
E2: Policy No : | G2: S02327725
E6: PARTIES AND CLASS | L6: POLICY NOTE | R6: BUSINESS DETAILS | X6: OTHER DETAIL
E8: Policyholder | H8: =APro!D6 -> Wanda Lucas | J8: ▼ | L8: Application Date | N8: =TODAY()-2 -> 45950 | R8: Agency | S8: Keystone | X8: Loading Applied | Y8: =IF(APro!L22>0,"Yes","No") -> Yes
E10: Insurer | H10: =APro!J6 -> SACOS | J10: ▼ | L10: Business Type | N10: Transfer | R10: Agent | S10: Mandy | X10: Reason | Y10: High BMI & asthmatic
E12: Insurance Class | H12: Life | I12: .. | J12: ▼ | L12: Policy Status | N12: In Force | P12: =IF(N24-TODAY()<30,"DFR","") -> DFR | R12: Source | S12: Referal
E14: Policy Type | H14: Fixed Term | L14: Renewal Notices | N14: =IF(Y24="A","Yes","No") -> No | O14: Channel | P14: Email | R14: Source Name | S14: Sam Dickson
E17: Policy Schedule
E18: PLAN & VALUE DETAILS | L18: PERIOD OF COVER | R18: ADD ONS | X18: PREMIUM & PAYMENT PLAN
E20: Year | H20: 2023 | L20: Term | N20: 20 | O20: Years | R20: TPD | S20: 1000000 | X20: Base Premium | Y20: =APro!N16 -> 751
E22: Policy Plan | H22: =APro!L6 -> Special Endowment | J22: ▼ | L22: Start Date | N22: 44276 | R22: FIBT | S22: =H24*0.03 -> 30000 | X22: Premium | Y22: =APro!R16 -> 759
E24: Sum Insured | H24: =APro!R6 -> 1000000 | L24: Maturity Date | N24: 15055 | X24: FOP / MOP | Y24: M | Z24: Salary Deduction
E26: Last Endorsement | H26: Change Benficiary | L26: Cancelled Date | X26: SOP | Y26: Cable & Wireless
E29: Documents
F32: Proposal Debit Note Receipt Schedule

Sheet VLP
E2: Policy No : | G2: =GLP!G2 -> S02327725
E6: PARTIES AND CLASS | L6: POLICY NOTE | R6: AGENCY & SOURCE | X6: OTHER DETAILS
E8: Policyholder | H8: =APro!D6 -> Wanda Lucas | L8: Application Date | N8: =TODAY()-2 -> 45950 | R8: Agency | S8: Keystone | X8: Loading Applied | Y8: =IF(APro!L22>0,"Yes","No") -> Yes
E10: Insurer | H10: =APro!J6 -> SACOS | L10: Business Type | N10: Transfer | R10: Agent | S10: Mandy | X10: Reason | Y10: High BMI
E12: Insurance Class | H12: Life | I12: .. | L12: Policy Status | N12: In Force | P12: =IF(N24-TODAY()<30,"DFR","") -> DFR | R12: Source | S12: Referal
E14: Policy Type | H14: Fixed Term | L14: Renewal Notices | N14: =IF(Y24="M","No","Yes") -> No | O14: Channel | P14: Email | R14: Source Name | S14: Sam Dickson
E17: Policy Schedule
E18: PLAN & VALUE DETAILS | L18: PERIOD OF COVER | R18: ADD ONS | X18: PREMIUM & PAYMENT PLAN
E20: Year | H20: 2023 | L20: Term | N20: 20 | O20: Years | R20: TPD | S20: 1000000 | X20: Base Premium | Y20: =APro!N16 -> 751
E22: Policy Plan | H22: =APro!L6 -> Special Endowment | J22: ▼ | L22: Start Date | N22: 44276 | R22: FIBT | S22: =H24*0.03 -> 30000 | X22: Premium | Y22: =APro!R16 -> 759
E24: Sum Insured | H24: =APro!R6 -> 1000000 | L24: Maturity Date | N24: 15055 | X24: FOP / MOP | Y24: M | Z24: Salary Deduction
E26: Last Endorsement | H26: TPD, FIBT | L26: Cancelled Date | X26: SOP | Y26: Cable & Wireless
E29: Documents
F32: Proposal Debit Note Receipt Schedule

Sheet C2LPx
E2: Life Policy - Add New
E4: Class - Life
E6: PARTIES AND CLASS | L6: POLICY NOTE | R6: BUSINESS DETAILS | X6: RENEWAL NOTICES
E8: Policyholder | H8: Wanda Lucas | R8: Agency | S8: =#REF! -> #REF! | X8: Renewal Notices | Z8: Annually
E10: Insurer | H10: =#REF! -> #REF! | L10: Application Date | N10: =#REF! -> #REF! | R10: Agent | S10: =#REF! -> #REF! | X10: Days Notice | Y10: 21 | Z10: 45664
E12: Policy No | H12: S002325 | L12: Policy Status | N12: In Force | P12: DFR | X12: Delivery Channel | Y12: SMS
E15: Policy Schedule
E16: COVER DETAILS | L16: PERIOD OF COVER | R16: OTHER DETAILS | X16: PREMIUM & PAYMENT PLAN
E18: Year | H18: 2023 | L18: Term | N18: =#REF! -> #REF! | O18: Year | X18: Base Premium | Y18: =#REF! -> #REF!
E20: Policy Plan | H20: =#REF! -> #REF! | L20: Start Date | N20: =TODAY() -> 45952 | X20: Full Premium | Y20: =#REF! -> #REF!
E22: Sum Insured | H22: =#REF! -> #REF! | L22: End Date | N22: =N20+364 -> 46316 | X22: Plan Type | Y22: Regular
E24: Add Ons | H24: =#REF! -> #REF! | L24: Cancelled Date | R24: Annual Premium | X24: Frequency | Y24: Monthly
E27: Debit Notes | L27: Premium Payments
E28: Debit Note | G28: Amount Due | I28: Date Due | J28: Status | L28: Amount Paid | M28: Date Paid | O28: Payment Type | R28: Payment Mode | T28: Cheque No | V28: Payment Notes
E29: DN-23099 | G29: =Y20/Y24 -> #REF! | I29: =N20 -> 45952 | J29: Paid | L29: =G29 -> #REF! | M29: =I29 -> 45952 | O29: Instalment | Q29: ▼ | R29: Cheque | S29: ▼ | T29: BOB-000234 | V29: 1st instalment
E30: DN-230100 | G30: =Y20/Y24 -> #REF! | I30: =N20+30 -> 45982 | J30: Unpaid
E33: Documents
F36: Proposal | H36: Debit Note | J36: Receipt | K36: Schedule

Sheet LIP
E2: Policy No - S796722
E6: PARTIES AND CLASS | L6: POLICY NOTE | R6: AGENCY & SOURCE | AA6: OTHER DETAILS
E8: Policyholder | H8: Barbara Walton | L8: Application Date | N8: =TODAY()-2 -> 45950 | R8: Agency | U8: Keystone | AA8: Loading Applied | AB8: Yes
E10: Insurer | H10: SACOS | L10: Business Type | N10: Transfer | R10: Agent | U10: Mandy | AA10: Reason | AB10: High BMI
E12: Insurance Class | H12: Life | I12: .. | L12: Policy Status | N12: In Force | P12: =IF(N24-TODAY()<30,"DFR","") -> DFR | R12: Source | U12: Referal
E14: Policy Type | H14: Fixed Term | L14: Renewal Notices | N14: No | O14: Channel | P14: SMS | R14: Source Name | U14: Sam Dickson
A15: 4
E17: Policy Schedule
E18: PLAN & VALUE DETAILS | L18: PERIOD OF COVER | R18: ADD ONS | AA18: PREMIUM & PAYMENT PLAN
E20: Year | H20: 2023 | L20: Term | N20: 20 | O20: Years | R20: TPD | U20: 1000000 | AA20: Base Premium | AB20: 1002
E22: Policy Plan | H22: Special Endowment | L22: Start Date | N22: 44276 | R22: FIBT | U22: 30000 | AA22: Premium | AB22: =ROUND(AB20*1.01,0) -> 1012
E24: Sum Insured | H24: 1000000 | L24: Maturity Date | N24: 15055 | AA24: FOP / MOP | AB24: M | AC24: Salary Deduction
E26: Last Endorsement | L26: Cancelled Date | AA26: SOP | AB26: Cable & Wireless
E29: Debit Notes | L29: Premium Payments
E30: Debit Note | G30: Amount Due | I30: Date Due | J30: Status | L30: Amount Paid | M30: Date Paid | O30: Payment Type | R30: Payment Mode | W30: Payment Notes
E31: DN-23099 | G31: =#REF!/AB26 -> #REF! | I31: =N22 -> 44276 | J31: Paid | L31: =G31 -> #REF! | M31: =I31 -> 44276 | O31: Instalment | Q31: ▼ | R31: Cheque | U31: ▼ | W31: 1st instalment
E32: DN-230100 | G32: =#REF!/AB26 -> #REF! | I32: =N22+30 -> 44306 | J32: Unpaid
E35: Documents
F38: Proposal Debit Note Receipt Schedule

Sheet VPD
E2: Policy No - MPV-23-HEA-P0002132
E6: PARTIES AND CLASS | L6: POLICY DETAILS | R6: AGENCY & SOURCE | X6: OTHER DETAILS
E8: Policyholder | H8: Jean Grey | L8: Application Date | N8: =TODAY()-2 -> 45950 | R8: Agency | T8: Keystone
E10: Insurer | H10: SACOS | L10: Business Type | N10: Transfer | R10: Agent | T10: Simon
E12: Insurance Class | H12: Motor | L12: Policy Status | N12: In Force | P12: =IF(N24-TODAY()<30,"DFR","") -> DFR | R12: Source | T12: Referal
E14: Insured | H14: S4444 Suzuki Fronx | L14: Renewal Notices | O14: Channel | P14: SMS | R14: Source Name | T14: Steve Rastore
E17: Policy Schedule
E18: PLAN & VALUE DETAILS | L18: PERIOD OF COVER | R18: ADD ONS ( Motor ) | X18: PREMIUM & PAYMENT PLAN
E20: Year | H20: 2024 | L20: Term | N20: 1 | O20: Year | R20: WSC | U20: 10000 | X20: Base Premium | Y20: 9875.77
E22: Policy Plan | H22: Comprehensive | L22: Start Date | N22: =N24-364 -> 45588 | R22: LOU | U22: 15000 | X22: Total Premium | Y22: =1.16*Y20 -> 11455.893
E24: Sum Insured | H24: 475000 | L24: End Date | N24: =TODAY() -> 45952 | R24: PA | U24: 250000 | X24: Payment Plan | Y24: Instalments
E26: Last Endorsement | H26: Sum insured reduced | L26: Cancelled Date | X26: NOP & Interval | Y26: 2 | Z26: Monthly
E29: Debit Notes | L29: Premium Payments
E30: Debit Note | G30: Amount Due | I30: Date Due | J30: Status | L30: Amount Paid | M30: Date Paid | O30: Payment Type | R30: Payment Mode | U30: Cheque No | V30: Payment Notes
E31: DN-23099 | G31: =Y22/#REF! -> #REF! | I31: =N22 -> 45588 | J31: Paid | L31: =G31 -> #REF! | M31: =I31 -> 45588 | O31: Instalment | Q31: ▼ | R31: Cheque | T31: ▼ | U31: BOB-000234 | V31: 1st instalment
E32: DN-230100 | G32: =Y22/#REF! -> #REF! | I32: =N22+30 -> 45618 | J32: Unpaid
E35: Documents
F38: Proposal Debit Note Receipt Schedule

Sheet LP
E2: Policies
E4: Records Found - 121 | P4: `
F6: Action | G6: Policy No | H6: Policy No | I6: Policy No | J6: Client Name | K6: Insurer | L6: Policy Class | M6: Policy Plan | N6: Sum Insured | O6: Start Date | P6: End Date | Q6: Insured | R6: Policy Status | U6: Date Registered | V6: PolicyID | W6: Insured Item | X6: Renewable | Y6: Biz Type | Z6: Term | AA6: Term | AB6: Base Premium | AC6: Loading | AD6: Premium | AE6: Freq | AF6: Pay Plan | AG6: Agency | AH6: Agent | AI6: Notes
G7: 1 | I7: MPV-23-HEA-P0002132 | J7: Jean Grey | K7: SACOS | L7: Motor | M7: Comprehensive | N7: 390000 | O7: =P7-364 -> 45588 | P7: =TODAY() -> 45952 | Q7: S44444 | R7: =IF(P7-TODAY()<30,"DFR","") -> DFR | U7: =O7 -> 45588 | V7: PL111 | W7: Suzuki Fronx | X7: Yes | Y7: Direct | Z7: 1 | AA7: Year | AB7: 9875.77 | AD7: =AB7*1.16 -> 11455.893 | AE7: Annually | AF7: Full
G8: 2 | I8: FSP-21-P00012999 | J8: Barbara Walton | K8: SACOS | L8: General | M8: Householder's | N8: 2500000 | O8: 44307 | P8: 48324 | R8: In Force | U8: =O8-368 -> 43939 | V8: PL110 | W8: Residence at Anse Royal | X8: Yes | Y8: Direct | Z8: 1 | AA8: Year | AB8: 7650 | AD8: 35467 | AE8: Annually | AF8: Full
G9: 3 | I9: PL-22-ALP-000033 | J9: Cornerstone (Pty) Ltd | K9: Alliance | L9: General | M9: Public Liability | N9: 2000000 | O9: 45245 | P9: =TODAY()+9 -> 45961 | R9: DFR | U9: =O9-350 -> 44895 | V9: PL109 | X9: Yes | Y9: Direct | Z9: 1 | AA9: Year | AB9: 5000 | AD9: =AB9*1.16 -> 5800 | AE9: Annually | AF9: Full
G10: 4 | I10: HS1-23-P00023132 | J10: Cornerstone (Pty) Ltd | K10: Alliance | L10: General | M10: Employer's Liabilithy | N10: 1000000 | O10: 45247 | P10: =TODAY()+9 -> 45961 | R10: DFR | U10: =O10-370 -> 44877 | V10: PL108 | X10: Yes | Y10: Direct | Z10: 1 | AA10: Year | AB10: 2500 | AD10: 2900 | AE10: Annually | AF10: Instalments
G11: 5 | I11: FSP-19-P00024 | J11: Anna's Spa | K11: SACOS | L11: General | M11: Fire & Special Perils | N11: 1500000 | O11: 45205 | P11: 45570 | R11: Expired | U11: =O11-366 -> 44839 | V11: PL107 | W11: SPA at English River | X11: Yes | Y11: Direct | Z11: 1 | AA11: Year | AB11: 3750 | AD11: =AB11*1.16 -> 4350 | AE11: Annually | AF11: Full
G12: 6 | I12: MVC-18-000331 | J12: Brian Trapper | K12: Hsavy | L12: Motor | M12: Comprehensive | N12: 285000 | O12: 45245 | P12: 45610 | Q12: S260 | R12: In Force | U12: =O12-365 -> 44880 | V12: PL106 | W12: Toyota Hyrider | X12: Yes | Y12: Direct | Z12: 1 | AA12: Year | AB12: 6652 | AD12: =AB12*1.16 -> 7716.32 | AE12: Annually | AF12: Full
G13: 7 | I13: MTC-22-000012 | J13: Adbul Juma | K13: Alliance | L13: Motor | M13: Third Party | N13: 0 | O13: 45180 | P13: 45545 | Q13: S32453 | R13: Cancelled | U13: =O13-365 -> 44815 | V13: PL105 | W13: Hyundai Creta | X13: Yes | Y13: Transfer | Z13: 1 | AA13: Year | AB13: 1500 | AD13: 1827 | AE13: Annually | AF13: Full
G14: 8 | I14: MVT-21-000324 | J14: Beta Center | K14: Hsavy | L14: General | M14: Fire & Special Perils | N14: 7000000 | O14: 45265 | P14: 45630 | R14: In Force | U14: =O14-367 -> 44898 | V14: PL104 | W14: Shop Office Complex Prividence | X14: Yes | Y14: Transfer | Z14: 1 | AA14: Year | AB14: 14377 | AD14: =AB14*1.16 -> 16677.32 | AE14: Annually | AF14: Full
G15: 9 | I15: MVT-21-000324 | J15: Steven Drax | K15: Hsavy | L15: General | M15: House Insurance | N15: 2978000 | O15: 45295 | P15: 45660 | R15: In Force | U15: =O15-365 -> 44930 | V15: PL103 | W15: Residence at Belombre | X15: Yes | Y15: Direct | Z15: 1 | AA15: Year | AB15: 8765.6 | AD15: =AB15*1.16 -> 10168.096 | AE15: Annually | AF15: Full
G16: 10 | I16: HS1-070-1-P0000435 | J16: Cold Cuts | K16: Alliance | L16: General | M16: Fire Industrial | N16: 2000000 | O16: 45156 | P16: 45521 | R16: Expired | U16: =O16-371 -> 44785 | V16: PL102 | X16: Yes | Y16: Transfer | Z16: 1 | AA16: Year | AB16: 4750 | AD16: =AB16*1.16 -> 5510 | AE16: Annually | AF16: Full
G17: 11 | I17: MVC-22-000023 | J17: Atlas Cars | K17: Alliance | L17: Motor | M17: Comprehensive | N17: 386000 | O17: 45154 | P17: 45519 | R17: In Force | U17: =O17-365 -> 44789 | V17: PL101 | X17: Yes | Y17: Direct | Z17: 1 | AA17: Year | AB17: 14325.55 | AD17: =1.16*AB17 -> 16617.638 | AE17: Annually | AF17: Full
G18: 12 | I18: TIP-23-P67367283 | J18: Trevor Thomas | K18: SACOS | L18: Travel | M18: World Wide Basic | O18: 45151 | P18: 45516 | R18: In Force | U18: =O18-372 -> 44779 | V18: PL100 | X18: No | Y18: Direct | Z18: 14 | AA18: Days | AB18: 1657.44 | AD18: 1657.44 | AE18: One Off | AF18: Full
G19: 13 | I19: PHV-22-P0000233 | J19: Walter Cox | K19: SACOS | L19: Marine | M19: Marine Hull | N19: 400000 | O19: 44715 | P19: 45080 | R19: In Force | U19: =O19-365 -> 44350 | V19: PL99 | X19: No | Y19: Direct | Z19: 20 | AA19: Year | AB19: 13456 | AD19: 13436 | AE19: Monthly | AF19: Regular
G20: 14 | I20: HS1-22-HIN-000321 | J20: Tom Blakley | K20: Hsavy | L20: General | M20: House Insurance | N20: 2500000 | O20: 45234 | P20: 45615 | R20: DFR | U20: =O20-366 -> 44868 | V20: PL98 | X20: No | Y20: Direct | Z20: 12 | AA20: Year | AB20: 35467 | AD20: 8874 | AE20: Single | AF20: Full

Sheet LLP
E2: Policies - Life
E4: Records Found - 239 | R4: `
F6: Action | G6: Policy No | H6: Policy No | I6: Policy No | J6: Client Name | K6: Insurer | L6: Policy Class | M6: Policy Plan | N6: Sum Insured | O6: Term | P6: Add Ons | Q6: Start Date | R6: End Date | S6: Policy Status | V6: Date Registered | W6: Base Premium | X6: Premium | Z6: PolicyID | AA6: Insured Item | AB6: Inclusions | AC6: Excess | AD6: Renewable | AE6: Biz Type | AF6: Term | AG6: Freq | AH6: Pay Plan | AI6: NOI | AJ6: Source | AK6: Source Name | AL6: Agency | AM6: Agent | AN6: Notes
G7: 1 | I7: S002120 | J7: Barbars Fox | K7: SACOS | L7: Life | M7: Special Endowment | N7: 400000 | O7: 20 | Q7: 43881 | R7: =Q7+(O7*365.25) -> 51186 | S7: Cancelled | V7: =Q7 -> 43881 | W7: 9875.77 | X7: =W7*1.16 -> 11455.893 | Z7: PL111 | AA7: Suzuki Fronx | AB7: WSC 10k, LOU 8k, PA 250k | AC7: 5000 or 10% | AD7: Yes | AE7: Renewal | AF7: 1 year | AG7: Annually | AH7: Full | AJ7: Referal
G8: 2 | I8: S004421 | J8: William Tell | K8: SACOS | L8: Life | M8: Endowment | N8: 200000 | O8: 15 | P8: CIB | Q8: 44285 | R8: =Q8+(O8*365.25) -> 49763.75 | S8: In Force | V8: =Q8-368 -> 43917 | W8: 7650 | X8: 35467 | Z8: PL110 | AA8: Residence at Anse Royal | AD8: Yes | AE8: Renewal | AF8: 1 year | AG8: Annually | AH8: Full
G9: 3 | I9: S009721 | J9: Beadley Sommer | K9: SACOS | L9: Life | M9: SACOS Exclusive | N9: 250000 | O9: 18 | Q9: 44398 | R9: =Q9+(O9*365.25) -> 50972.5 | S9: In Force | V9: =Q9-350 -> 44048 | W9: 5000 | X9: =W9*1.16 -> 5800 | Z9: PL109 | AD9: Yes | AE9: Renewal | AF9: 1 year | AG9: Annually | AH9: Full
G10: 4 | I10: S012320 | J10: Karen Cox | K10: SACOS | L10: Life | M10: SACOS Special | N10: 200000 | O10: 25 | Q10: 43903 | R10: =Q10+(O10*365.25) -> 53034.25 | S10: In Force | V10: =Q10-370 -> 43533 | W10: 2500 | X10: 2900 | Z10: PL108 | AD10: Yes | AE10: New | AF10: 1 year | AG10: Annually | AH10: Instalments | AI10: 4
G11: 5 | I11: S012721 | J11: Travis Michaels | K11: SACOS | L11: Life | M11: Dpuble Security Plan | N11: 150000 | O11: 18 | Q11: 44418 | R11: =Q11+(O11*365.25) -> 50992.5 | S11: In Force | V11: =Q11-366 -> 44052 | W11: 3750 | X11: =W11*1.16 -> 4350 | Z11: PL107 | AA11: SPA at English River | AD11: Yes | AE11: New | AF11: 1 year | AG11: Annually | AH11: Full
G12: 6 | I12: S000422 | J12: Drax Batista | K12: SACOS | L12: Life | M12: Special Endowment | N12: 300000 | O12: 25 | P12: FIBT TPD | Q12: 44662 | R12: =Q12+(O12*365.25) -> 53793.25 | S12: In Force | V12: =Q12-365 -> 44297 | W12: 6652 | X12: =W12*1.16 -> 7716.32 | Z12: PL106 | AA12: Toyota Hyrider | AD12: Yes | AE12: New | AF12: 1 year | AG12: Annually | AH12: Full
G13: 7 | I13: S002122 | J13: Oliver Farrel | K13: SACOS | L13: Life | M13: Special Endowment | N13: 240000 | O13: 20 | Q13: 44719 | R13: =Q13+(O13*365.25) -> 52024 | S13: In Force | V13: =Q13-365 -> 44354 | W13: 1500 | X13: 1827 | Z13: PL105 | AA13: Hyundai Creta | AD13: Yes | AE13: Transfer | AF13: 1 year | AG13: Annually | AH13: Full
G14: 8 | I14: S003322 | J14: Brenda Farsel | K14: SACOS | L14: Life | M14: Special Endowment | N14: 200000 | O14: 20 | Q14: 44729 | R14: =Q14+(O14*365.25) -> 52034 | S14: In Force | V14: =Q14-367 -> 44362 | W14: 14377 | X14: =W14*1.16 -> 16677.32 | Z14: PL104 | AA14: Shop Office Complex Prividence | AD14: Yes | AE14: Transfer | AF14: 1 year | AG14: Annually | AH14: Full
G15: 9 | I15: S004522 | J15: Manda Omandu | K15: SACOS | L15: Life | M15: Endowment | N15: 100000 | O15: 13 | Q15: 44761 | R15: =Q15+(O15*365.25) -> 49509.25 | S15: In Force | V15: =Q15-365 -> 44396 | W15: 8765.6 | X15: =W15*1.16 -> 10168.096 | Z15: PL103 | AA15: Residence at Belombre | AD15: Yes | AE15: New | AF15: 1 year | AG15: Annually | AH15: Full
G16: 10 | I16: S005722 | J16: Kevin Malom | K16: SACOS | L16: Life | M16: SACOS Junior | N16: 300000 | O16: 19 | P16: ADB | Q16: 44776 | R16: =Q16+(O16*365.25) -> 51715.75 | S16: In Force | V16: =Q16-371 -> 44405 | W16: 4750 | X16: =W16*1.16 -> 5510 | Z16: PL102 | AD16: Yes | AE16: Transfer | AF16: 1 year | AG16: Annually | AH16: Full
G17: 11 | I17: S006322 | J17: Jermie Wall | K17: SACOS | L17: Life | M17: SACOS Junior | N17: 250000 | O17: 17 | Q17: 44792 | R17: =Q17+(O17*365.25) -> 51001.25 | S17: In Force | V17: =Q17-365 -> 44427 | W17: 14325.55 | X17: =1.16*W17 -> 16617.638 | Z17: PL101 | AD17: Yes | AE17: Renewal | AF17: 1 year | AG17: Annually | AH17: Full
G18: 12 | I18: S007422 | J18: Harry Bradley | K18: SACOS | L18: Life | M18: Special Endowment | N18: 240000 | O18: 20 | Q18: 44796 | R18: =Q18+(O18*365.25) -> 52101 | S18: In Force | V18: =Q18-372 -> 44424 | W18: 1657.44 | X18: 1657.44 | Z18: PL100 | AD18: No | AE18: New | AF18: 14 days | AG18: One Off | AH18: Full
G19: 13 | I19: S007522 | J19: Walter Cox | K19: SACOS | L19: Life | M19: Endowment | N19: 400000 | O19: 20 | Q19: 44807 | R19: =Q19+(O19*365.25) -> 52112 | S19: In Force | V19: =Q19-365 -> 44442 | W19: 13456 | X19: 13436 | Z19: PL99 | AD19: No | AE19: New | AF19: 20 years | AG19: Monthly | AH19: Regular
G20: 14 | I20: H004342 | J20: Steve Stammeer | K20: Hsavy | L20: Life | M20: PLAN C | N20: 100000 | O20: 20 | Q20: 44818 | R20: =Q20+(O20*365.25) -> 52123 | S20: In Force | V20: =Q20-366 -> 44452 | W20: 35467 | X20: 8874 | Z20: PL98 | AD20: No | AE20: New | AF20: 12 years | AG20: Single | AH20: Full

Sheet Sheet6
D2: Policy -New
D4: Policy Number | I4: Proposer's Name | M4: Insurer | Q4: Insurance Class | V4: Insured Item | AA4: VRN
D5: MPV-23-P000231 | I5: William Caizonne | M5: SACOS | Q5: Motor | V5: Suzuki Fronx | AA5: S32345
D6: Application Date | I6: Business Type | M6: Agency | Q6: Agent | V6: Source | AA6: Source Name
D7: =TODAY()-15 -> 45937 | I7: Transfer | M7: Keystone | Q7: Simon | V7: Referal | AA7: Travis Port-Louis
D8: Schedule
D9: Year | I9: Plan | M9: Sum Insured | Q9: Term | V9: Start Date | AA9: End Date
D10: 2025 | I10: Comprehensive | M10: 350000 | Q10: 1 | S10: Year | V10: =TODAY()-1 -> 45951 | AA10: =V10+364 -> 46315
D11: Premium
D12: Base | I12: Total | M12: Payment Plan | Q12: NOP | S12: Interval | V12: Renewal Notices | AA12: Delivery Channel
D13: 19821 | I13: 21354 | M13: Instalments | Q13: 2 | S13: Monthly | X13: Annually | AA13: SMS
E16: Vehicle Details | Y16: Comprehensive Add Ons
E17: Vehicle Registration No | G17: Make | H17: Model | J17: Year | K17: Type | N17: Engine Type | Q17: CC | R17: Chassis No | V17: Useage | Y17: WSC | AA17: LOU | AC17: PA
E18: S3432 | G18: Toyota | H18: Raize | J18: 2025 | K18: Commuter Bus | N18: Hybrid | Q18: 1600 | R18: HMSGSGHAjdjjsjsajsjd | V18: Private | Y18: 10000 | AA18: 15000 | AC18: 250000
E21: Nominee Details
E22: Name | J22: NIN/Passport No | M22: DOB | N22: Realtionship | S22: Share | V22: Added | Y22: Removed
E23: Brandon Curtis DeCarozone | J23: 984-0012-5-1-33 | M23: 46021 | N23: Common Law Spouse | S23: 0.5 | V23: 15000 | Y23: 250000
G30: Payment Plan
E31: Frequency Of Payment | I31: Method Of Payment | M31: Source Of Payment | Q31: Base Premium | V31: Admin Fee | AA31: Total Premium
E32: Monthly | I32: Salary Deduction | M32: Hunt Deltel | Q32: =ROUND(0.0875*X18,0) -> 0 | V32: =ROUND(0.01*Q32,0) -> 0 | AA32: =Q32+V32 -> 0
E33: Payment Plan | V33: Add Ons
E34: Option | I34: Date Referred | M34: Date Completed | Q34: Exam Notes
E35: Jivan | I35: =TODAY()-5 -> 45947 | M35: =TODAY()-1 -> 45951 | Q35: High BMI and Asthmatic
E36: Application Details
E37: Date | I37: Proposal Status | M37: Policy No | Q37: Loading Premium | V37: Start Date | AA37: Maturity Date
E38: =TODAY()-3 -> 45949 | I38: Awaiting Policy | M38: S007825 | Q38: 768 | V38: =TODAY()-15 -> 45937 | AA38: =TODAY()+(365.25*#REF!) -> #REF!
G41: Documents

Sheet AP
D2: Policy - Add New
D4: Policy Number | H4: Clients Name | L4: Insurance Class | P4: Insurer | T4: Insured Asset / Destination
L5: ____ | M5: ___
D6: Application Date | H6: Business Type | L6: Agency | P6: Agent | T6: Source
D8: Source Name | L8: Delivery Channel | P8: Notes
H9: Renewal Notices Required?
D10: Schedule Details
D11: Year | H11: Plan | L11: Sum Insured | P11: Term | R11: Period | T11: Start Date
D13: WSC | F13: LOU | H13: PA | L13: Base Premium | P13: Total Premium
D15: Payment Plan
D16: Option | H16: No Of Instalments | L16: Interval | P16: Start Date | T16: End Date
D20: Documents

Sheet APV
E2: Add Policy
E6: PARTIES AND CLASS | L6: POLICY NOTE | R6: RENEWAL NOTICES | X6: BUSINESS DETAILS
E8: Policyholder | H8: Jean Grey | J8: ▼ | L8: Insured Item | N8: S4444 Suzuki Fronx | R8: Renewal Notices | T8: Annually | X8: Business | Y8: Keystone
E10: Insurer | H10: SACOS | J10: ▼ | L10: Application Date | N10: =TODAY()-2 -> 45950 | R10: Days Notice/Date | S10: 21 | T10: =N22-S10 -> 46295 | X10: Business Type | Y10: New
E12: Policy Class | H12: Motor | J12: ▼ | L12: Status | N12: In Force | P12: DFR | R12: Delivery Channel | S12: SMS, email | X12: Agent | Y12: Mandy
E15: Policy Schedule
E16: COVER DETAILS | L16: PERIOD OF COVER | R16: ADD ONS & EXCESS | X16: PREMIUM & PAYMENT PLAN
E18: Year | H18: 2023 | L18: Term | N18: 1 | O18: Year | R18: Add Ons | S18: WSC 10K, PA 100K, LOU 8K | X18: Base Premium | Y18: 9875.77
E20: Policy Plan | H20: Comprehensive | J20: ▼ | L20: Start Date | N20: =TODAY() -> 45952 | X20: Full Premium | Y20: =1.16*Y18 -> 11455.893
E22: Sum Insured | H22: 475000 | L22: End Date | N22: =N20+364 -> 46316 | R22: Excess | S22: 5000 or 10% | X22: Frequency | Y22: Annually
E24: Note | H24: Sum Insured reduced | L24: Cancelled Date | X24: Pay Plan | Y24: 2 | Z24: Monthly
E27: Debit Notes | L27: Premium Payments
E28: Debit Note | G28: Amount Due | I28: Date Due | J28: Status | L28: Amount Paid | M28: Date Paid | O28: Payment Type | R28: Payment Mode | T28: Cheque No | V28: Payment Notes
E29: DN-23099 | G29: =Y20/Y24 -> 5727.9466 | I29: =N20 -> 45952 | J29: Paid | L29: =G29 -> 5727.9466 | M29: =I29 -> 45952 | O29: Instalment | Q29: ▼ | R29: Cheque | S29: ▼ | T29: BOB-000234 | V29: 1st instalment
E30: DN-230100 | G30: =Y20/Y24 -> 5727.9466 | I30: =N20+30 -> 45982 | J30: Unpaid
E33: Documents
F36: Proposal | H36: Debit Note | J36: Receipt | K36: Schedule

Sheet VPDX
E2: Policy - MPV-23-HEA-P0002132
E6: PARTIES AND CLASS | L6: POLICY DETAILS | R6: OTHER DETAILS | X6: POLICY NOTES
E8: Policyholder | H8: Jean Grey | L8: Application Date | N8: =TODAY()-2 -> 45950 | R8: Agency | S8: Keystone
E10: Insurer | H10: SACOS | L10: Business Type | N10: Transfer | R10: Agent | S10: Simon
E12: Policy Class | H12: Motor | L12: Policy Status | N12: In Force | P12: =IF(N24-TODAY()<30,"DFR","") -> DFR | R12: Source | S12: Referal
E14: Insured | H14: S4444 Suzuki Fronx | L14: Renewal Notices | O14: Channel | P14: SMS | R14: Source Name | S14: Steve Rastore
E17: Policy Schedule
E18: PLAN & VALUE DETAILS | L18: PERIOD OF COVER | R18: OTHER DETAILS | X18: PREMIUM & PAYMENT PLAN
E20: Year | H20: 2024 | L20: Term | N20: 1 | O20: Year | R20: Add Ons | S20: WSC 10K, PA 100K, LOU 8K | X20: Base Premium | Y20: 9875.77
E22: Policy Plan | H22: Comprehensive | L22: Start Date | N22: =N24-364 -> 45588 | X22: Total Premium | Y22: =1.16*Y20 -> 11455.893
E24: Sum Insured | H24: 475000 | L24: End Date | N24: =TODAY() -> 45952 | X24: Payment Plan | Y24: Instalments
E26: Last Endorsement | H26: Sum Insured reduced | L26: Cancelled Date | X26: NOP & Interval | Y26: 2 | Z26: Monthly
E29: Debit Notes | L29: Premium Payments
E30: Debit Note | G30: Amount Due | I30: Date Due | J30: Status | L30: Amount Paid | M30: Date Paid | O30: Payment Type | R30: Payment Mode | T30: Cheque No | V30: Payment Notes
E31: DN-23099 | G31: =Y22/#REF! -> #REF! | I31: =N22 -> 45588 | J31: Paid | L31: =G31 -> #REF! | M31: =I31 -> 45588 | O31: Instalment | Q31: ▼ | R31: Cheque | S31: ▼ | T31: BOB-000234 | V31: 1st instalment
E32: DN-230100 | G32: =Y22/#REF! -> #REF! | I32: =N22+30 -> 45618 | J32: Unpaid
E35: Documents
F38: Proposal Debit Note Receipt Schedule

Sheet RP
E2: Renew Policy - MPV-23-HEA-P0002132
E6: PARTIES AND CLASS | L6: POLICY NOTE | R6: BUSINESS DETAILS | X6: RENEWAL NOTICES
E8: Policyholder | H8: Jean Grey | J8: ▼ | L8: Insured Item | N8: S4444 Suzuki Fronx | R8: Agency | S8: Keystone | X8: Renewal Notices | Z8: Annually
E10: Insurer | H10: SACOS | J10: ▼ | L10: Application Date | N10: =TODAY()-2 -> 45950 | R10: Agent | S10: Simon | X10: Days Notice | Y10: 21 | Z10: 45664
E12: Policy Class | H12: Motor | J12: ▼ | L12: Policy Status | N12: In Force | P12: DFR | R12: Business Type | S12: Transfer | X12: Channel | Y12: SMS
E14: Insured | H14: S4444 Suzuki Fronx | L14: Policy Status | N14: In Force | P14: =IF(N24-TODAY()<30,"DFR","") | R14: Source Name | S14: Referal
E17: Policy Schedule
E18: COVER DETAILS | L18: PERIOD OF COVER | R18: ADD ONS & EXCESS | X18: PREMIUM & PAYMENT PLAN
E20: Year | H20: 2025 | L20: Term | N20: 1 | O20: Year | R20: Add Ons | S20: WSC 10K, PA 100K, LOU 8K | X20: Base Premium | Y20: 10657.44
E22: Policy Plan | H22: Comprehensive | J22: ▼ | L22: Start Date | N22: =TODAY() -> 45952 | X22: Full Premium | Y22: =1.16*Y20 -> 12362.63
E24: Sum Insured | H24: 475000 | L24: End Date | N24: =N22+365 -> 46317 | R24: Excess | S24: 5000 or 10% | X24: Plan Type | Y24: Single
E26: Note | L26: Cancelled Date | X26: Frequency | Y26: 1 | Z26: Annual
E29: Debit Notes | L29: Premium Payments
E30: Debit Note | G30: Amount Due | I30: Date Due | J30: Status | L30: Amount Paid | M30: Date Paid | O30: Payment Type | R30: Payment Mode | T30: Cheque No | V30: Payment Notes
E31: DN-23070 | G31: =Y22/Y26 -> 12362.63 | I31: =N22 -> 45952 | J31: Paid | L31: =G31 -> 12362.63 | M31: =I31 -> 45952 | O31: Instalment | Q31: ▼ | R31: Cheque | S31: ▼ | T31: BOB-000324 | V31: 1st instalment
E32: DN-23071 | G32: =Y22/Y26 -> 12362.63 | I32: =N22+30 -> 45982 | J32: Unpaid
E33: DN-23072 | H33: =Y22/Y26 -> 12362.63 | I33: =N22+60 -> 46012 | J33: Unpaid
E36: Documents
F39: Proposal | H39: Debit Note | J39: Receipt | K39: Schedule

Sheet LPDFR
E2: Policies - Due For Renewal
E4: Records Found - 4
F6: Action | G6: Policy No | H6: Policy No | I6: Policy No | J6: Client Name | K6: Insurer | L6: Policy Class | M6: Policy Plan | N6: Sum Insured | O6: Start Date | P6: End Date | Q6: Insured Item | R6: Status | U6: Premium
G7: 1 | I7: MPV-23-HEA-P0002132 | J7: Jean Grey | K7: SACOS | L7: Motor | M7: Comprehensive | N7: 390000 | O7: =P7-365 -> 45587 | P7: =TODAY() -> 45952 | Q7: S44444 | R7: DFR | U7: 11455.893
G8: 2 | I8: PL-22-ALP-000033 | J8: Cornerstone (Pty) Ltd | K8: Alliance | L8: General | M8: Public Liability | N8: 2000000 | O8: 45245 | P8: 45899 | R8: DFR | U8: =V8*1.16 -> 0
G9: 3 | I9: HS1-23-P00023132 | J9: Cornerstone (Pty) Ltd | K9: Alliance | L9: General | M9: Employer's Liabilithy | N9: 1000000 | O9: 45247 | P9: 45900 | R9: DFR | U9: =V9*1.16 -> 0
G10: 4 | I10: HS1-22-HIN-000321 | J10: Tom Thumb | K10: Hsavy | L10: General | M10: House Insurance | N10: 2500000 | O10: 45234 | P10: 45894 | R10: DFR | U10: 2900

Sheet EPD
E2: Policy No - MPV-23-HEA-P0002132
E6: PARTIES AND CLASS | L6: POLICY DETAILS | R6: AGENCY & SOURCE | X6: OTHER DETAILS
E8: Policyholder | H8: Jean Grey | L8: Application Date | N8: =TODAY()-2 -> 45950 | R8: Agency | T8: Keystone
E10: Insurer | H10: SACOS | L10: Business Type | N10: Transfer | R10: Agent | T10: Simon
E12: Insurance Class | H12: Motor | L12: Policy Status | N12: In Force | P12: =IF(N24-TODAY()<30,"DFR","") -> DFR | R12: Source | T12: Referal
E14: Insured | H14: S4444 Suzuki Fronx | L14: Renewal Notices | O14: Channel | P14: SMS | R14: Source Name | T14: Steve Rastore
E17: Policy Schedule
E18: PLAN & VALUE DETAILS | L18: PERIOD OF COVER | R18: ADD ONS | X18: PREMIUM & PAYMENT PLAN
E20: Year | H20: 2024 | L20: Term | N20: 1 | O20: Year | R20: WSC | U20: 10000 | X20: Base Premium | Y20: 9875.77
E22: Policy Plan | H22: Comprehensive | L22: Start Date | N22: =N24-364 -> 45588 | R22: LOU | U22: 15000 | X22: Total Premium | Y22: =1.16*Y20 -> 11455.893
E24: Sum Insured | H24: 475000 | L24: End Date | N24: =TODAY() -> 45952 | R24: PA | U24: 250000 | X24: Payment Plan | Y24: Instalments
E26: Last Endorsement | H26: Sum Insured reduced | L26: Cancelled Date | X26: NOP & Interval | Y26: 2 | Z26: Monthly
E29: Documents
F32: Proposal Debit Note Receipt Schedule

Sheet DP
E2: Policy - MPV-23-HEA-P0002132
E6: PARTIES AND CLASS | L6: POLICY NOTE | R6: BUSINESS DETAILS | X6: RENEWAL NOTICES
E8: Policyholder | H8: Jean Grey | L8: Application Date | N8: =TODAY()-2 -> 45950 | R8: Agency | S8: Keystone | X8: Renewal Notices
E10: Insurer | H10: SACOS | L10: Business Type | N10: Transfer | R10: Agent | S10: Simon | X10: Channel | Y10: SMS
E12: Policy Class | H12: Motor | R12: Source | S12: Referal
E14: Insured | H14: S4444 Suzuki Fronx | L14: Policy Status | N14: In Force | P14: =IF(N24-TODAY()<30,"DFR","") -> DFR | R14: Source Name | S14: Steve Rastore
E17: Policy Schedule
E18: PLAN & VALUE DETAILS | L18: PERIOD OF COVER | R18: OTHER DETAILS | X18: PREMIUM & PAYMENT PLAN
E20: Year | H20: 2024 | L20: Term | N20: 1 | O20: Year | R20: Add Ons | S20: WSC 10K, PA 100K, LOU 8K | X20: Base Premium | Y20: 9875.77
E22: Policy Plan | H22: Comprehensive | L22: Start Date | N22: =N24-364 -> 45588 | X22: Total Premium | Y22: =1.16*Y20 -> 11455.893
E24: Sum Insured | H24: 475000 | L24: End Date | N24: =TODAY() -> 45952 | R24: Notes | X24: Payment Plan | Y24: Instalments
E26: Last Endorsement | H26: Sum Insured reduced | L26: Cancelled Date | X26: NOP & Interval | Y26: 2 | Z26: Monthly
E29: Documents
F32: Proposal Debit Note Receipt Schedule

Sheet VPPn
E2: Policy - MPV-23-HEA-P0002132 - Payments
E4: Records Found - 5
H6: Line | I6: Action | J6: Debit Note | K6: Payment Type | L6: Date Due | M6: Amount Due | N6: Status | O6: Amount Paid | P6: Date Paid | Q6: Payment Mode | R6: Cheque No | S6: Policy Number | T6: Comments
H7: 1 | J7: DN24100 | K7: Instalment | L7: 45640 | M7: 5727.9466 | N7: Unpaid | S7: MPV-23-HEA-P0002132
H8: 2 | J8: DN24099 | K8: Instalment | L8: 45610 | M8: 5727.9466 | N8: Paid | O8: 5727.9466 | P8: 45610 | Q8: Cheque | R8: NB0002413 | S8: MPV-23-HEA-P0002132
H9: 3 | J9: DN23078 | K9: Full payment | L9: 45219 | M9: 11455.893 | N9: Paid | O9: 11455.893 | P9: 45219 | Q9: Transfer | S9: MPV-23-HEA-P0002132
H10: 4 | J10: DN22066 | K10: Full payment | L10: 44854 | M10: 12268.74 | N10: Paid | O10: 12268.74 | P10: 44854 | Q10: Cheque | S10: MPV-23-HEA-P0002132
H11: 5 | J11: DN21061 | K11: Full payment | L11: 44488 | M11: 14383.095 | N11: Paid | O11: 14383.095 | P11: 44488 | Q11: Cheque | S11: MPV-23-HEA-P0002132

Sheet VPPP
E2: Policy No - MPV-23-HEA-P0002132
E4: Records 1 to 5 to 5
H6: Line | I6: Action | J6: Debit Note | K6: Date Due | L6: Amount Due | M6: Status | N6: Amount Paid | O6: Date Paid | P6: Payment Type | R6: Payment Mode | S6: Cheque No | T6: Payment Notes
H7: 1 | J7: DN24100 | K7: 45285 | L7: 5727.9466 | M7: Unpaid
H8: 2 | J8: DN24099 | K8: 45255 | L8: 5727.9466 | M8: Paid | N8: 5727.9466 | O8: 45255 | P8: Instalment | R8: Cheque | S8: NB0002413
H9: 3 | J9: DN22095 | K9: 44890 | L9: 11455.893 | M9: Paid | N9: =L9 -> 11455.893 | O9: 44887 | P9: Full payment | R9: Cheque
H10: 4 | J10: DN21080 | K10: 44525 | L10: 12268.74 | M10: Paid | N10: =L10 -> 12268.74 | O10: 44520 | P10: Full payment | R10: Cheque
H11: 5 | J11: DN20063 | K11: 44160 | L11: 14383.095 | M11: Paid | N11: =L11 -> 14383.095 | O11: 44156 | P11: Full payment | R11: Cheque

Sheet APCo
E2: Policy - MPV-23-HEA-P0002132 - Commission
E4: Records Found - 5
H6: Line | I6: Action | J6: Invoice | K6: Policy Number | L6: Insurer | M6: Grouping | N6: Date Due | O6: Basic Premium | P6: Rate | Q6: Amount Due | R6: Status | S6: Amount Paid | T6: Date Paid | U6: Mode | V6: State No | W6: Select | Z6: Note
H7: 1 | J7: CN23090 | K7: MPV-23-HEA-P0002132 | L7: SACOS | M7: Motor | N7: 45316 | O7: 4937.89 | P7: 0.1 | Q7: 740.68 | R7: Unpaid
H8: 2 | J8: CN22070 | K8: MPV-23-HEA-P0002132 | L8: SACOS | M8: Motor | N8: 44920 | O8: 9875.77 | P8: 0.1 | Q8: 1481.3655 | R8: Paid | S8: 1481.36 | T8: 44931 | U8: Bank Transfer | V8: SG-2212 | Z8: Part Commission
H9: 3 | J9: CN21052 | K9: MPV-23-HEA-P0002132 | L9: SACOS | M9: Motor | N9: 44555 | O9: 10576.5 | P9: 0.1 | Q9: 1586.475 | R9: Paid | S9: 1481.36 | T9: 44578 | U9: Bank Transfer | V9: SG-2112
H10: 4 | J10: CN20045 | K10: MPV-23-HEA-P0002132 | L10: SACOS | M10: Motor | N10: 44190 | O10: 12399.22 | P10: 0.1 | Q10: 1859.883 | R10: Paid | S10: 1481.36 | T10: 44208 | U10: Bank Transfer | V10: SG-2012
H11: 5

Sheet EPCo
E2: Policy No - MPV-23-HEA-P0002132
E4: Records 1 to 5 of 5
H6: Line | I6: Action | J6: Invoice | K6: Policy Number | L6: Insurer | M6: Grouping | N6: Date Due | O6: Basic Premium | P6: Rate | Q6: Amount Due | R6: Status | S6: Amount Paid | T6: Date Paid | U6: Mode | V6: State No | W6: Select
H7: 1 | J7: CN23090 | K7: MPV-23-HEA-P0002132 | L7: SACOS | M7: Motor | N7: 45316 | O7: 4937.89 | P7: 0.1 | Q7: 740.68 | R7: Unpaid
H8: 2 | J8: CN23089 | K8: MPV-23-HEA-P0002132 | L8: SACOS | M8: Motor | N8: 45285 | O8: =O9-O7 -> 4937.88 | P8: 0.1 | Q8: 740.67 | R8: Unpaid
H9: 3 | J9: CN22070 | K9: MPV-23-HEA-P0002132 | L9: SACOS | M9: Motor | N9: 44920 | O9: 9875.77 | P9: 0.1 | Q9: =0.15*O9 -> 1481.3655 | R9: Paid | S9: 1481.36 | T9: 44931 | U9: Bank Transfer | V9: SG-2212
H10: 4 | J10: CN21052 | K10: MPV-23-HEA-P0002132 | L10: SACOS | M10: Motor | N10: 44555 | O10: 10576.5 | P10: 0.1 | Q10: =0.15*O10 -> 1586.475 | R10: Paid | S10: 1481.36 | T10: 44578 | U10: Bank Transfer | V10: SG-2112
H11: 5 | J11: CN20045 | K11: MPV-23-HEA-P0002132 | L11: SACOS | M11: Motor | N11: 44190 | O11: 12399.22 | P11: 0.1 | Q11: =0.15*O11 -> 1859.883 | R11: Paid | S11: 1481.36 | T11: 44208 | U11: Bank Transfer | V11: SG-2012

Sheet VPCA
E2: Policy No - MPV-23-HEA-P0002132 - Claim
E4: Records 1 to 1 of 1
H6: Line | I6: Action | J6: Claim No | K6: Loss Date | L6: Claim Date | M6: Claim Amount | N6: Claim Summary | Q6: Stage | R6: Status | S6: Amount Paid | T6: Date Paid | U6: Comment
H7: 1 | J7: CM18011 | K7: 43177 | L7: 43178 | M7: 57654.88 | N7: Damage caused by accident with S32432 | Q7: Closed | R7: Paid Out | S7: 50654.88 | T7: 43205

Sheet LPS
E2: MPV-23-HEA-P0002132 - Schedules
E4: Records Found - 4
F6: Action | G6: Year | H6: Year | I6: Status | J6: Policy Plan | L6: Sum Insured | M6: Inclusions | N6: Start Date | O6: End Date | P6: Base Premium | Q6: Full Premium | R6: FOP | S6: NOP | T6: Pay Plan | U6: Regn No | X6: Term | Y6: Insured Item | Z6: Excess | AA6: Note | AB6: Schedule ID
H7: 2024 | I7: In Force | J7: Comprehensive | L7: 380000 | M7: WSC 10k, LOU 7k, PA250k | N7: =O7-364 -> 45588 | O7: =TODAY() -> 45952 | P7: 9875.77 | Q7: 11455.893 | R7: A | S7: 2 | T7: Instalments | U7: S4444 | X7: 1 | Y7: S4444 Suzuki Fronx | Z7: 5000 or 10% | AB7: SH23087
H8: 2023 | I8: Expired | J8: Comprehensive | L8: 390000 | M8: WSC 10k, LOU 7k, PA250k | N8: =O8-365 -> 45222 | O8: =N7-1 -> 45587 | P8: 9875.77 | Q8: 11455.893 | R8: A | S8: 2 | T8: Instalments | U8: S4444 | X8: 1 | Y8: S4444 Suzuki Fronx | Z8: 5000 or 10% | AB8: SH22067
H9: 2022 | I9: Expired | J9: Comprehensive | L9: 400000 | M9: WSC 10k, LOU 7k, PA250k | N9: =O9-364 -> 44857 | O9: =N8-1 -> 45221 | P9: 9875.77 | Q9: 11455.893 | R9: A | S9: 1 | T9: Full payment | U9: S4444 | X9: 1 | Y9: S17876 Toyota Corolla | Z9: 5000 or 10% | AA9: Car Sold | AB9: SH21053
H10: 2021 | I10: Expired | J10: Comprehensive | L10: 410000 | M10: WSC 10k, LOU 7k, PA250k | N10: =O10-364 -> 44492 | O10: =N9-1 -> 44856 | P10: 10576.5 | Q10: 12268.74 | R10: A | S10: 1 | T10: Full payment | U10: S17896 | X10: 1 | Y10: S17876 Toyota Corolla | Z10: 5000 or 10% | AB10: SH20030
H11: 2020 | I11: Expired | J11: Comprehensive | L11: 420000 | M11: WSC 10k, LOU 7k, PA250k | N11: =O11-364 -> 44127 | O11: =N10-1 -> 44491 | P11: 11277.23 | Q11: 13081.587 | R11: A | S11: 1 | T11: Full payment | U11: S17896

Sheet VPP
E2: MPV-23-HEA-P0002132 - Payments
E4: Records Found - 5
G6: Line | H6: Action | I6: Debit Note | J6: Payment Type | K6: Date Due | L6: Amount Due | M6: Status | N6: Amount Paid | O6: Date Paid | P6: Payment Mode | Q6: Cheque No | R6: Policy Number | S6: Comments
G7: 1 | I7: DN24100 | J7: Instalment | K7: 45640 | L7: 5727.9466 | M7: Unpaid | R7: MPV-23-HEA-P0002132
G8: 2 | I8: DN24099 | J8: Instalment | K8: 45610 | L8: 5727.9466 | M8: Paid | N8: 5727.9466 | O8: 45610 | P8: Cheque | Q8: NB0002413 | R8: MPV-23-HEA-P0002132
G9: 3 | I9: DN23078 | J9: Full payment | K9: 45219 | L9: 11455.893 | M9: Paid | N9: 11455.893 | O9: 45219 | P9: Transfer | R9: MPV-23-HEA-P0002132
G10: 4 | I10: DN22066 | J10: Full payment | K10: 44854 | L10: 12268.74 | M10: Paid | N10: 12268.74 | O10: 44854 | P10: Cheque | R10: MPV-23-HEA-P0002132
G11: 5 | I11: DN21061 | J11: Full payment | K11: 44488 | L11: 14383.095 | M11: Paid | N11: 14383.095 | O11: 44488 | P11: Cheque | R11: MPV-23-HEA-P0002132

Sheet VPCo
E2: MPV-23-HEA-P0002132 - Commission
E4: Records Found - 5
F6: Action | G6: Invoice | H6: Invoice | I6: Invoice | J6: Policy Number | K6: Insurer | L6: Grouping | M6: Date Due | N6: Basic Premium | O6: Rate | P6: Amount Due | Q6: Status | R6: Amount Paid | S6: Date Paid | T6: Mode | U6: State No | Y6: Note | Z6: Select
G7: 1 | I7: CN23090 | J7: MPV-23-HEA-P0002132 | K7: SACOS | L7: Motor | M7: 45316 | N7: 4937.89 | O7: 0.1 | P7: 740.68 | Q7: Unpaid
G8: 2 | I8: CN22070 | J8: MPV-23-HEA-P0002132 | K8: SACOS | L8: Motor | M8: 44920 | N8: 9875.77 | O8: 0.1 | P8: 1481.3655 | Q8: Paid | R8: 1481.36 | S8: 44931 | T8: Bank Transfer | U8: SG-2212 | Y8: Part Commission
G9: 3 | I9: CN21052 | J9: MPV-23-HEA-P0002132 | K9: SACOS | L9: Motor | M9: 44555 | N9: 10576.5 | O9: 0.1 | P9: 1586.475 | Q9: Paid | R9: 1481.36 | S9: 44578 | T9: Bank Transfer | U9: SG-2112
G10: 4 | I10: CN20045 | J10: MPV-23-HEA-P0002132 | K10: SACOS | L10: Motor | M10: 44190 | N10: 12399.22 | O10: 0.1 | P10: 1859.883 | Q10: Paid | R10: 1481.36 | S10: 44208 | T10: Bank Transfer | U10: SG-2012
G11: 5

Sheet VPC
E2: MPV-23-HEA-P0002132 - Claims
E4: Records Found - 1
F6: Action | G6: Claim No | H6: Claim No | I6: Claim No | J6: Loss Date | K6: Claim Date | L6: Claim Amount | M6: Claim Summary | P6: Stage | Q6: Status | R6: Amount Paid | S6: Date Paid | T6: Claim Description
G7: 1 | I7: CM18011 | J7: 43177 | K7: 43178 | L7: 57654.88 | M7: Damage caused by accident with S32432 | P7: Closed | Q7: Paid Out | R7: 50654.88 | S7: 43205

Sheet VPV
E2: MPV-23-HEA-P0002132 - Vehicles
E4: Records Found - f 2
F6: Action | G6: Regn No | H6: Regn No | I6: Regn No | J6: Make | K6: Model | L6: Type | M6: Useage | N6: Year | O6: Value | P6: Engine Type | Q6: CC | R6: Engine No | S6: Chassis No | U6: From | V6: To | Y6: Notes | AB6: VehicleID
G7: 1 | I7: S4444 | J7: Suzuki | K7: Fronx | L7: SUV | M7: Private | N7: 2024 | O7: 360000 | P7: Hybrid | Q7: 1462 | R7: KB15HJG645 | S7: VBVG8675G666FF | AB7: V24021
G8: 2 | I8: S32454 | J8: Suzuki | K8: Grand Vitara | L8: Sedan | M8: For Hire | N8: 2023 | O8: 1200000 | P8: Petrol | Q8: 3120 | R8: KB67HG7282 | U8: 44388 | AB8: V23008

Sheet EPV
E2: Policy - MPV-23-HEA-P0002132 - Vehicles
E4: Records 1 to 2 of 2
H6: Line | I6: Action | J6: Regn No | K6: Make | L6: Model | M6: Type | N6: Useage | O6: Year | P6: Value | Q6: Engine Type
H7: 1 | J7: S4444 | K7: Suzuki | L7: Fronx | M7: SUV | N7: Private | O7: 2024 | P7: 360000 | Q7: Hybrid
H8: 2 | J8: S32454 | K8: Suzuki | L8: Grand Vitara | M8: Sedan | N8: For Hire | O8: 2023 | P8: 1200000 | Q8: Petrol

Sheet PRN
E2: Policy - MPV-23-HEA-P0002132
E6: PARTIES AND CLASS | L6: POLICY NOTE | R6: BUSINESS DETAILS | X6: RENEWAL NOTICES
E8: Policyholder | H8: Jean Grey | J8: ▼ | L8: Insured Item | N8: S4444 Suzuki Fronx | R8: Agency | S8: Keystone | X8: Renewal Notices | Z8: Annually
E10: Insurer | H10: SACOS | J10: ▼ | L10: Application Date | N10: =TODAY()-2 -> 45950 | R10: Agent | S10: Simon | X10: Days Notice | Y10: 21 | Z10: 45664
E12: Policy Class | H12: Motor | J12: ▼ | L12: Policy Status | N12: In Force | P12: DFR | R12: Business Type | S12: Transfer | X12: Channel | Y12: SMS
E15: Policy Schedule
E16: COVER DETAILS | L16: PERIOD OF COVER | R16: ADD ONS & EXCESS | X16: PREMIUM & PAYMENT PLAN
E18: Year | H18: 2023 | L18: Term | N18: 1 | O18: Year ▼ | R18: Add Ons | S18: WSC 10K, PA 100K, LOU 8K | X18: Base Premium | Y18: 9875.77
E20: Policy Plan | H20: Comprehensive | J20: ▼ | L20: Start Date | N20: =TODAY() -> 45952 | X20: Full Premium | Y20: =1.16*Y18 -> 11455.893
E22: Sum Insured | H22: 475000 | L22: End Date | N22: =N20+364 -> 46316 | R22: Excess | S22: 5000 or 10% | X22: Plan Type | Y22: Single
E24: Note | H24: Sum Insured reduced | L24: Cancelled Date | X24: Frequency | Y24: 2 | Z24: Monthly
E27: Debit Notes | L27: Premium Payments
E28: Debit Note | G28: Amount Due | I28: Date Due | J28: Status | L28: Amount Paid | M28: Date Paid | O28: Payment Type | R28: Payment Mode | T28: Cheque No | V28: Payment Notes
E29: DN-23099 | G29: =Y20/Y24 -> 5727.9466 | I29: =N20 -> 45952 | J29: Paid | L29: =G29 -> 5727.9466 | M29: =I29 -> 45952 | O29: Instalment | Q29: ▼ | R29: Cheque | S29: ▼ | T29: BOB-000234 | V29: 1st instalment
E30: DN-230100 | G30: =Y20/Y24 -> 5727.9466 | I30: =N20+30 -> 45982 | J30: Unpaid
E33: Documents
F36: Proposal | H36: Debit Note | J36: Receipt | K36: Schedule

Sheet LPF
E2: Policies
E4: Records 1 to 15 of 199 | R4: ` | Y4: FILTER
H6: Line | I6: Action | J6: Policy No | K6: Client Name | L6: Policy Class | M6: Policy Plan | N6: Insurer | O6: Sum Insured | P6: Premium | Q6: Start Date | R6: End Date | S6: Regn No | T6: Status | X6: Submission Date | Y6: Base Premium | AA6: Insured Item | AB6: Inclusions | AC6: Excess | AD6: Renewable | AE6: Biz Type | AF6: Term | AG6: Freq | AH6: Pay Plan | AI6: NOI | AJ6: Source | AK6: Source Name | AL6: Notes
H7: 1 | J7: MPV-23-HEA-P0002132 | K7: Jean Grey | L7: Motor | M7: Comprehensive | N7: SACOS | O7: 390000 | P7: =Y7*1.16 -> 11455.893 | Q7: =R7-364 -> 45593 | R7: =TODAY()+5 -> 45957 | S7: S44444 | T7: In Force | X7: =Q7 -> 45593 | Y7: 9875.77 | AA7: Suzuki Fronx | AB7: WSC 10k, LOU 8k, PA 250k | AC7: 5000 or 10% | AD7: Yes | AE7: Renewal | AF7: 1 year | AG7: Annually | AH7: Full | AJ7: Referal
H8: 2 | J8: HS1-22-HIN-000321 | K8: Tom Thumb | L8: General | M8: House Insurance | N8: Hsavy | O8: 2500000 | P8: =Y8*1.16 -> 8874 | Q8: 45250 | R8: 45615 | T8: In Force | X8: =Q8-368 -> 44882 | Y8: 7650 | AA8: Residence at Anse Royal | AD8: Yes | AE8: Renewal | AF8: 1 year | AG8: Annually | AH8: Full
H9: 3 | J9: PL-22-ALP-000033 | K9: Cornerstone (Pty) Ltd | L9: General | M9: Public Liability | N9: Alliance | O9: 2000000 | P9: =Y9*1.16 -> 5800 | Q9: 45584 | R9: 45949 | T9: DFR | X9: =Q9-350 -> 45234 | Y9: 5000 | AD9: Yes | AE9: Renewal | AF9: 1 year | AG9: Annually | AH9: Full
H10: 4 | J10: HS1-23-P00023132 | K10: Cornerstone (Pty) Ltd | L10: General | M10: Employer's Liabilithy | N10: Alliance | O10: 1000000 | P10: 2900 | Q10: 45589 | R10: 45954 | T10: DFR | X10: =Q10-370 -> 45219 | Y10: 2500 | AD10: Yes | AE10: New | AF10: 1 year | AG10: Annually | AH10: Instalments | AI10: 4
H11: 5 | J11: FSP-19-P00024 | K11: Anna's Spa | L11: General | M11: Fire & Special Perils | N11: SACOS | O11: 1500000 | P11: =Y11*1.16 -> 4350 | Q11: 45205 | R11: 45570 | T11: Expired | X11: =Q11-366 -> 44839 | Y11: 3750 | AA11: SPA at English River | AD11: Yes | AE11: New | AF11: 1 year | AG11: Annually | AH11: Full
H12: 6 | J12: MVC-18-000331 | K12: Brian Trapper | L12: Motor | M12: Comprehensive | N12: Hsavy | O12: 285000 | P12: =Y12*1.16 -> 7716.32 | Q12: 45245 | R12: 45610 | S12: S260 | T12: In Force | X12: =Q12-365 -> 44880 | Y12: 6652 | AA12: Toyota Hyrider | AD12: Yes | AE12: New | AF12: 1 year | AG12: Annually | AH12: Full
H13: 7 | J13: MTC-22-000012 | K13: Adbul Juma | L13: Motor | M13: Third Party | N13: Alliance | O13: 0 | P13: 1827 | Q13: 45180 | R13: 45545 | S13: S32453 | T13: Cancelled | X13: =Q13-365 -> 44815 | Y13: 1500 | AA13: Hyundai Creta | AD13: Yes | AE13: Transfer | AF13: 1 year | AG13: Annually | AH13: Full
H14: 8 | J14: MVT-21-000324 | K14: Beta Center | L14: General | M14: Fire & Special Perils | N14: Hsavy | O14: 7000000 | P14: =Y14*1.16 -> 16677.32 | Q14: 45265 | R14: 45630 | T14: In Force | X14: =Q14-367 -> 44898 | Y14: 14377 | AA14: Shop Office Complex Prividence | AD14: Yes | AE14: Transfer | AF14: 1 year | AG14: Annually | AH14: Full
H15: 9 | J15: MVT-21-000324 | K15: Steven Drax | L15: General | M15: House Insurance | N15: Hsavy | O15: 2978000 | P15: =Y15*1.16 -> 10168.096 | Q15: 45295 | R15: 45660 | T15: In Force | X15: =Q15-365 -> 44930 | Y15: 8765.6 | AA15: Residence at Belombre | AD15: Yes | AE15: New | AF15: 1 year | AG15: Annually | AH15: Full
H16: 10 | J16: HS1-070-1-P0000435 | K16: Cold Cuts | L16: General | M16: Fire Industrial | N16: Alliance | O16: 2000000 | P16: =Y16*1.16 -> 5510 | Q16: 45156 | R16: 45521 | T16: Expired | X16: =Q16-371 -> 44785 | Y16: 4750 | AD16: Yes | AE16: Transfer | AF16: 1 year | AG16: Annually | AH16: Full
H17: 11 | J17: MVC-22-000023 | K17: Atlas Cars | L17: Motor | M17: Comprehensive | N17: Alliance | O17: 386000 | P17: =1.16*Y17 -> 16617.638 | Q17: 45154 | R17: 45519 | T17: In Force | X17: =Q17-365 -> 44789 | Y17: 14325.55 | AD17: Yes | AE17: Renewal | AF17: 1 year | AG17: Annually | AH17: Full
H18: 12 | J18: TIP-23-P67367283 | K18: Trevor Thomas | L18: Travel | M18: World Wide Basic | N18: SACOS | P18: 1657.44 | Q18: 45151 | R18: 45516 | T18: In Force | X18: =Q18-372 -> 44779 | Y18: 1657.44 | AD18: No | AE18: New | AF18: 14 days | AG18: One Off | AH18: Full
H19: 13 | J19: S002223 | K19: Walter Cox | L19: Life | M19: Endowment | N19: SACOS | O19: 400000 | P19: 13436 | Q19: 44715 | R19: 45080 | T19: In Force | X19: =Q19-365 -> 44350 | Y19: 13456 | AD19: No | AE19: New | AF19: 20 years | AG19: Monthly | AH19: Regular
H20: 14 | J20: S796722 | K20: Barbara Walton | L20: Life | M20: Mortgage | N20: SACOS | O20: 2500000 | P20: 35467 | Q20: 44307 | R20: 44672 | T20: In Force | X20: =Q20-366 -> 43941 | Y20: 35467 | AD20: No | AE20: New | AF20: 12 years | AG20: Single | AH20: Full
H21: 15 | J21: PI-23-P00432 | K21: Track Adventures | L21: General | M21: Proffessional Indemnity | N21: Hsavy | O21: 1500000 | P21: =1.16*Y21 -> 14573.08 | Q21: 44633 | R21: 44998 | T21: In Force | X21: =Q21-369 -> 44264 | Y21: 12563 | AD21: Yes | AE21: New | AF21: 1 year | AG21: Annually | AH21: Full

Sheet LCom
E2: Commissions
E4: Records Found - 192
F6: Action | G6: CNID | H6: Policy Number | I6: Client's Name | J6: Insurer | K6: Grouping | L6: Basic Premium | M6: Rate | N6: Amount Due | O6: Com Status | P6: Amount Rcvd | Q6: Date Rcvd | R6: State No | S6: Select | V6: Mode | W6: Variance | X6: Reason | Y6: Date Due | Z6: CNID
G7: 1 | H7: MPV-23-HEA-P0002132 | I7: Jean Grey | J7: SACOS | K7: Motor | L7: 9875.76 | M7: 0.1 | N7: =L7*M7 -> 987.576 | O7: Unpaid | Y7: 45316 | Z7: CN23090
G8: 2 | H8: FSP-17-HEA-P0002311 | I8: Samantha Fox | J8: SACOS | K8: General | L8: 6823 | M8: 0.15 | N8: =L8*M8 -> 1023.45 | O8: Paid | P8: =N8 -> 1023.45 | Q8: 44931 | R8: SG-2312 | Y8: 45651 | Z8: CN23089
G9: 3 | H9: HS1-22-HIN-000321 | I9: Greenways | J9: SACOS | K9: General | L9: 4350 | M9: 0.15 | N9: =L9*M9 -> 652.5 | O9: Paid | P9: 1481.36 | Q9: 44931 | R9: SG-2312 | V9: Bank Transfer | Y9: 45279 | Z9: CN23088
G10: 4 | H10: HS1-23-P00023132 | I10: Hot Bits | J10: SACOS | K10: General | L10: 5510 | M10: 0.15 | N10: =L10*M10 -> 826.5 | O10: Paid | P10: 1481.36 | Q10: 44578 | R10: SG-2311 | V10: Bank Transfer | Y10: 45271 | Z10: CN23087
G11: 5 | H11: HI-17-000043 | I11: Woodworks Ltd | J11: SACOS | K11: General | L11: 12399.22 | M11: 0.1 | N11: =L11*M11 -> 1239.922 | O11: Balance Due | V11: Bank Transfer | Y11: 44190 | Z11: CN23086
H12: HS1-22-HIN-000321 | I12: Motor Parts (Pty) Ltd | J12: SACOS | K12: General | L12: 4350 | M12: 0.15 | N12: =L12*M12 -> 652.5 | O12: Unpaid | Y12: 45279 | Z12: CN23085
H13: HS1-23-P00023132 | I13: Hot Bits | J13: SACOS | K13: General | L13: 5510 | M13: 0.15 | N13: =L13*M13 -> 826.5 | O13: Unpaid | Y13: 45271 | Z13: CN23084
H14: PL-21-CSG-62371899 | I14: George Baker | J14: Alliance | K14: General | L14: 2564 | M14: 0.15 | N14: =L14*M14 -> 384.6 | O14: Paid | P14: =L14 -> 2564 | Q14: 45304 | R14: AG-2311 | Y14: 45269 | Z14: CN23083
H15: HI-17-002903993 | I15: John Ball | J15: Alliance | K15: General | L15: 7648 | M15: 0.15 | N15: =L15*M15 -> 1147.2 | O15: Paid | P15: =L15 -> 7648 | Q15: 45304 | R15: AG-2311 | Y15: 45259 | Z15: CN23082
H16: MCT-20-83831111 | I16: Wallace James | J16: Alliance | K16: Motor | L16: 21455 | M16: 0.1 | N16: =L16*M16 -> 2145.5 | O16: Paid | P16: =L16 -> 21455 | Q16: 45304 | R16: AG-2311 | Y16: 45255 | Z16: CN23081
H17: PL-22-ALP-000033 | I17: Adbul Juma | J17: Hsavy | K17: General | L17: 1827 | M17: 0.15 | N17: 274.05 | O17: Outstanding | Y17: 45240 | Z17: CN23080
H18: MCV-18-821884299 | I18: Virginie Bold | J18: Alliance | K18: Motor | L18: 17022 | M18: 0.1 | N18: =L18*M18 -> 1702.2 | O18: Paid | P18: =L18 -> 17022 | Q18: 45304 | R18: AG-2311 | Y18: 45233 | Z18: CN23079
H19: HI-19-98392922 | I19: Mc Lure | J19: Hsavy | K19: General | L19: 9811 | M19: 0.15 | N19: 275.05 | O19: Paid | P19: =L19 -> 9811 | R19: HG-2311 | Y19: 45228 | Z19: CN23078
H20: HI-18-P000321 | I20: Relais Des Iles | J20: SACOS | K20: General | L20: 5800 | M20: 0.15 | N20: =L20*M20 -> 870 | O20: Outstanding | Y20: 45216 | Z20: CN23077

Sheet ECom
E2: Commissions
E4: Records 1 to 15 of 192
H6: Line | I6: CNID | J6: Policy Number | K6: Client's Name | L6: Insurer | M6: Grouping | N6: Basic Premium | O6: Rate | P6: Amount Due | Q6: Status | R6: Amount Rcvd | S6: Date Rcvd | T6: State No | U6: Select | X6: Mode | Z6: Variance | AA6: Reason | AB6: Date Due
H7: 1 | I7: CN23090 | J7: MPV-23-HEA-P0002132 | K7: Jean Grey | L7: SACOS | M7: Motor | N7: 9875.76 | O7: 0.1 | P7: =N7*O7 -> 987.576 | Q7: Outstanding | AB7: 45316
H8: 2 | I8: CN23089 | J8: FSP-17-HEA-P0002311 | K8: Samantha Fox | L8: Hsavy | M8: General | N8: 6823 | O8: 0.15 | P8: =N8*O8 -> 1023.45 | Q8: Paid | R8: =P8 -> 1023.45 | S8: 44931 | T8: SG-2312 | AB8: 45651
H9: 3 | I9: CN23088 | J9: HS1-22-HIN-000321 | K9: Greenways | L9: SACOS | M9: General | N9: 4350 | O9: 0.15 | P9: =N9*O9 -> 652.5 | Q9: Paid | R9: 1481.36 | S9: 44931 | T9: SG-2312 | X9: Bank Transfer | AB9: 45279
H10: 4 | I10: CN23087 | J10: HS1-23-P00023132 | K10: Hot Bits | L10: SACOS | M10: General | N10: 5510 | O10: 0.15 | P10: =N10*O10 -> 826.5 | Q10: Paid | R10: 1481.36 | S10: 44578 | T10: SG-2311 | X10: Bank Transfer | AB10: 45271
H11: 5 | I11: CN23086 | J11: HI-17-000043 | K11: Woodworks Ltd | L11: SACOS | M11: General | N11: 12399.22 | O11: 0.1 | P11: =N11*O11 -> 1239.922 | Q11: Outstanding | X11: Bank Transfer | AB11: 44190
I12: CN23085 | J12: HS1-22-HIN-000321 | K12: Motor Parts (Pty) Ltd | L12: SACOS | M12: General | N12: 4350 | O12: 0.15 | P12: =N12*O12 -> 652.5 | Q12: Outstanding | AB12: 45279
I13: CN23084 | J13: HS1-23-P00023132 | K13: Hot Bits | L13: SACOS | M13: General | N13: 5510 | O13: 0.15 | P13: =N13*O13 -> 826.5 | Q13: Outstanding | AB13: 45271
I14: CN23083 | J14: PL-21-CSG-62371899 | K14: George Baker | L14: Alliance | M14: General | N14: 2564 | O14: 0.15 | P14: =N14*O14 -> 384.6 | Q14: Paid | R14: =N14 -> 2564 | S14: 45304 | T14: AG-2311 | AB14: 45269
I15: CN23082 | J15: HI-17-002903993 | K15: John Ball | L15: Alliance | M15: General | N15: 7648 | O15: 0.15 | P15: =N15*O15 -> 1147.2 | Q15: Paid | R15: =N15 -> 7648 | S15: 45304 | T15: AG-2311 | AB15: 45259
I16: CN23081 | J16: MCT-20-83831111 | K16: Wallace James | L16: Alliance | M16: Motor | N16: 21455 | O16: 0.1 | P16: =N16*O16 -> 2145.5 | Q16: Paid | R16: =N16 -> 21455 | S16: 45304 | T16: AG-2311 | AB16: 45255
I17: CN23080 | J17: PL-22-ALP-000033 | K17: Adbul Juma | L17: Hsavy | M17: General | N17: 1827 | O17: 0.15 | P17: 274.05 | Q17: Outstanding | AB17: 45240
I18: CN23079 | J18: MCV-18-821884299 | K18: Virginie Bold | L18: Alliance | M18: Motor | N18: 17022 | O18: 0.1 | P18: =N18*O18 -> 1702.2 | Q18: Paid | R18: =N18 -> 17022 | S18: 45304 | T18: AG-2311 | AB18: 45233
I19: CN23078 | J19: HI-19-98392922 | K19: Mc Lure | L19: Hsavy | M19: General | N19: 9811 | O19: 0.15 | P19: 275.05 | Q19: Paid | R19: =N19 -> 9811 | T19: HG-2311 | AB19: 45228
I20: CN23077 | J20: HI-18-P000321 | K20: Relais Des Iles | L20: SACOS | M20: General | N20: 5800 | O20: 0.15 | P20: =N20*O20 -> 870 | Q20: Outstanding | AB20: 45216
I21: CN23076 | J21: MCT-19-823812981 | K21: Daisy Flatre | L21: HSavy | M21: Motor | N21: 4567 | O21: 0.1 | P21: 276.05 | Q21: Paid | R21: =N21 -> 4567 | AB21: 45215

Sheet ComE
E2: Commissions
E4: Records 1 to 8 of 8
H6: Line | I6: CNID | J6: Policy Number | K6: Client's Name | L6: Insurer | M6: Grouping | N6: Basic Premium | O6: Rate | P6: Amount Due | Q6: Status | R6: Amount Rcvd | S6: Date Rcvd | T6: State No | U6: Select | X6: Date Due | Y6: Mode | AA6: Variance | AB6: Reason
H7: 1 | I7: CN23090 | J7: MPV-23-HEA-P0002132 | K7: Jean Grey | L7: SACOS | M7: Motor | N7: 9875.76 | O7: 0.1 | P7: 740.68 | Q7: Outstanding | X7: 45316
H8: 2 | I8: CN23089 | J8: FSP-19-HEA-P0000321 | K8: Jules Baker | L8: Alliance | M8: General | N8: 7355 | O8: 0.15 | P8: 1103.25 | Q8: Outstanding | X8: 45285
I9: CN23085 | J9: HS1-22-HIN-000321 | K9: Motor Parts (Pty) Ltd | L9: SACOS | M9: General | N9: 4350 | O9: 0.15 | P9: =N9*O9 -> 652.5 | Q9: Outstanding | X9: 45279
I10: CN23084 | J10: HS1-23-P00023132 | K10: Hot Bits | L10: SACOS | M10: General | N10: 5510 | O10: 0.15 | P10: =N10*O10 -> 826.5 | Q10: Outstanding | X10: 45271
I11: CN23080 | J11: PL-22-ALP-000033 | K11: Adbul Juma | L11: Hsavy | M11: General | N11: 1827 | O11: 0.15 | P11: =N11*O11 -> 274.05 | Q11: Outstanding | X11: 45240
I12: CN23077 | J12: HI-18-P000321 | K12: Relais Des Iles | L12: SACOS | M12: General | N12: 5800 | O12: 0.15 | P12: =N12*O12 -> 870 | Q12: Outstanding | X12: 45216
I13: CN23071 | J13: MCV-22-00000231 | K13: Luke Cage | L13: Alliance | M13: General | N13: 8043 | O13: 0.1 | P13: =N13*O13 -> 804.3 | Q13: Outstanding | X13: 45214
I14: CN23067 | J14: MCV-19-00000044 | K14: Trevor Stevens | L14: Alliance | M14: Motor | N14: 11500 | O14: 0.1 | P14: =N14*O14 -> 1150 | Q14: Outstanding | X14: 45211
O15: TOTAL Outstanding | P15: =SUM(P7:P14) -> 6421.28

Sheet LComU
E2: Commissions - Outstanding
A3: 15
E4: Records Found - 8
F6: Action | G6: Policy Number | H6: Client's Name | I6: Insurer | J6: Grouping | K6: Basic Premium | L6: Rate | M6: Amount Due | N6: Com Status | O6: Amount Rcvd | P6: Date Rcvd | Q6: State No | R6: Select | U6: Date Due | W6: Mode | X6: Variance | Y6: Reason | Z6: CNID
G7: MPV-23-HEA-P0002132 | H7: Jean Grey | I7: SACOS | J7: Motor | K7: 9875.76 | L7: 0.1 | M7: 987.58 | N7: Unpaid | U7: 45316 | Z7: CN23090
G8: HI-17-000043 | H8: Woodworks Ltd | I8: SACOS | J8: General | K8: 12399.22 | L8: 0.1 | M8: 1239.922 | N8: Balance Due | U8: 45285 | Z8: CN23086
G9: HS1-22-HIN-000321 | H9: Motor Parts (Pty) Ltd | I9: SACOS | J9: General | K9: 4350 | L9: 0.15 | M9: 652.5 | N9: Unpaid | U9: 45279 | Z9: CN23085
G10: HS1-23-P00023132 | H10: Hot Bits | I10: SACOS | J10: General | K10: 5510 | L10: 0.15 | M10: 826.5 | N10: Unpaid | U10: 45271 | Z10: CN23084
G11: PL-22-ALP-000033 | H11: Adbul Juma | I11: Hsavy | J11: General | K11: 1827 | L11: 0.15 | M11: =K11*L11 -> 274.05 | N11: Unpaid | U11: 45240 | Z11: CN23080
G12: HI-18-P000321 | H12: Relais Des Iles | I12: SACOS | J12: General | K12: 5800 | L12: 0.15 | M12: =K12*L12 -> 870 | N12: Unpaid | U12: 45216 | Z12: CN23077
G13: MCV-22-00000231 | H13: Luke Cage | I13: Alliance | J13: General | K13: 8043 | L13: 0.1 | M13: =K13*L13 -> 804.3 | N13: Unpaid | U13: 45214 | Z13: CN23071
G14: MCV-19-00000044 | H14: Trevor Stevens | I14: Alliance | J14: Motor | K14: 11500 | L14: 0.1 | M14: =K14*L14 -> 1150 | N14: Unpaid | U14: 45211 | Z14: CN23067
L15: TOTAL Outstanding | M15: =SUM(M7:M14) -> 6804.852

Sheet LComS
E2: Commissions - SACOS
E4: Records Found - 192
F6: Action | G6: CNID | H6: CNID | I6: Policy Number | J6: Client's Name | K6: Insurer | L6: Grouping | M6: Basic Premium | N6: Rate | O6: Amount Due | P6: Com Status | Q6: Amount Rcvd | R6: Date Rcvd | S6: State No | T6: Select | W6: Mode | Y6: Variance | Z6: Reason | AA6: Date Due
G7: 1 | H7: CN23090 | I7: MPV-23-HEA-P0002132 | J7: Jean Grey | K7: SACOS | L7: Motor | M7: 9875.76 | N7: 0.1 | O7: =M7*N7 -> 987.576 | P7: Unpaid | AA7: 45316
G8: 3 | H8: CN23088 | I8: HS1-22-HIN-000321 | J8: Greenways | K8: SACOS | L8: General | M8: 4350 | N8: 0.15 | O8: =M8*N8 -> 652.5 | P8: Paid | Q8: 1481.36 | R8: 44931 | S8: SG-2312 | W8: Bank Transfer | AA8: 45279
G9: 4 | H9: CN23087 | I9: HS1-23-P00023132 | J9: Hot Bits | K9: SACOS | L9: General | M9: 5510 | N9: 0.15 | O9: =M9*N9 -> 826.5 | P9: Paid | Q9: 1481.36 | R9: 44578 | S9: SG-2311 | W9: Bank Transfer | AA9: 45271
G10: 5 | H10: CN23086 | I10: HI-17-000043 | J10: Woodworks Ltd | K10: SACOS | L10: General | M10: 12399.22 | N10: 0.1 | O10: =M10*N10 -> 1239.922 | P10: Balance Due | W10: Bank Transfer | AA10: 44190
H11: CN23085 | I11: HS1-22-HIN-000321 | J11: Motor Parts (Pty) Ltd | K11: SACOS | L11: General | M11: 4350 | N11: 0.15 | O11: =M11*N11 -> 652.5 | P11: Unpaid | AA11: 45279
H12: CN23084 | I12: HS1-23-P00023132 | J12: Hot Bits | K12: SACOS | L12: General | M12: 5510 | N12: 0.15 | O12: =M12*N12 -> 826.5 | P12: Unpaid | AA12: 45271
H13: CN23077 | I13: HI-18-P000321 | J13: Relais Des Iles | K13: SACOS | L13: General | M13: 5800 | N13: 0.15 | O13: =M13*N13 -> 870 | P13: Outstanding | AA13: 45216
H14: CN23083 | I14: PL-21-CSG-62371899 | J14: George Baker | K14: SACOS | L14: General | M14: 2564 | N14: 0.15 | O14: =M14*N14 -> 384.6 | P14: Paid | Q14: =M14 -> 2564 | R14: 45304 | S14: AG-2311 | AA14: 45269
H15: CN23082 | I15: HI-17-002903993 | J15: John Ball | K15: SACOS | L15: General | M15: 7648 | N15: 0.15 | O15: =M15*N15 -> 1147.2 | P15: Paid | Q15: =M15 -> 7648 | R15: 45304 | S15: AG-2311 | AA15: 45259
H16: CN23081 | I16: MCT-20-83831111 | J16: Wallace James | K16: SACOS | L16: Motor | M16: 21455 | N16: 0.1 | O16: =M16*N16 -> 2145.5 | P16: Paid | Q16: =M16 -> 21455 | R16: 45304 | S16: AG-2311 | AA16: 45255
H17: CN23080 | I17: PL-22-ALP-000033 | J17: Adbul Juma | K17: SACOS | L17: General | M17: 1827 | N17: 0.15 | O17: 274.05 | P17: Outstanding | AA17: 45240
H18: CN23079 | I18: MCV-18-821884299 | J18: Virginie Bold | K18: SACOS | L18: Motor | M18: 17022 | N18: 0.1 | O18: =M18*N18 -> 1702.2 | P18: Paid | Q18: =M18 -> 17022 | R18: 45304 | S18: AG-2311 | AA18: 45233
H19: CN23078 | I19: HI-19-98392922 | J19: Mc Lure | K19: SACOS | L19: General | M19: 9811 | N19: 0.15 | O19: 275.05 | P19: Paid | Q19: =M19 -> 9811 | S19: HG-2311 | AA19: 45228
H20: CN23077 | I20: HI-18-P000321 | J20: Relais Des Iles | K20: SACOS | L20: General | M20: 5800 | N20: 0.15 | O20: =M20*N20 -> 870 | P20: Outstanding | AA20: 45216

Sheet LComOS
E2: Commissions - Outstanding - SACOS
E4: Records Found - 4
F6: CNID | G6: Policy Number | H6: Client's Name | I6: Insurer | J6: Grouping | K6: Basic Premium | L6: Rate | M6: Amount Due | N6: Com Status | O6: Amount Rcvd | P6: Variance | Q6: Date Rcvd | R6: Select | U6: Date Due | V6: State No | W6: Mode | Y6: Reason
F7: CN23090 | G7: MPV-23-HEA-P0002132 | H7: Jean Grey | I7: SACOS | J7: Motor | K7: 9875.76 | L7: 0.1 | M7: 740.68 | N7: Unpaid | U7: 45316
F8: CN23086 | G8: HI-17-000043 | H8: Woodworks Ltd | I8: SACOS | J8: General | K8: 12399.22 | L8: 0.1 | M8: 1239.922 | N8: Balance Due | U8: 45279
F9: CN23085 | G9: HS1-22-HIN-000321 | H9: Motor Parts (Pty) Ltd | I9: SACOS | J9: General | K9: 4350 | L9: 0.15 | M9: 652.5 | N9: Unpaid | U9: 45271
F10: CN23084 | G10: HS1-23-P00023132 | H10: Hot Bits | I10: SACOS | J10: General | K10: 5510 | L10: 0.15 | M10: 826.5 | N10: Unpaid | U10: 45216
L11: TOTAL Outstanding | M11: =SUM(M7:M10) -> 3459.602

Sheet PreS
E2: Preview Statement - SACOS
E4: Records Selected - 3
F6: CNID | G6: CNID | H6: CNID | I6: Policy Number | J6: Client's Name | K6: Insurer | L6: Grouping | M6: Basic Premium | N6: Rate | O6: Amount Due | P6: Status | Q6: Amount Rcvd | R6: Variance | S6: Reason | T6: Select | W6: Mode | X6: Date Due | Y6: Date Rcvd | Z6: Stat No
F7: 1 | H7: CN23090 | I7: MPV-23-HEA-P0002132 | J7: Jean Grey | K7: SACOS | L7: Motor | M7: 9875.76 | N7: 0.1 | O7: 740.68 | P7: Unpaid | Q7: =O7 -> 740.68 | R7: =Q7-O7 -> 0 | X7: 45316
F8: 2 | H8: CN23085 | I8: HS1-23-P00023132 | J8: Hot Bits | K8: SACOS | L8: General | M8: 5510 | N8: 0.15 | O8: 826.5 | P8: Unpaid | Q8: =O8 -> 826.5 | R8: =Q8-O8 -> 0 | X8: 45271
H9: CN23084 | I9: HI-18-P000321 | J9: Relais Des Iles | K9: SACOS | L9: General | M9: 5800 | N9: 0.15 | O9: 870 | P9: Unpaid | Q9: =O9 -> 870 | R9: =Q9-O9 -> 0 | X9: 45216
N10: TOTALS | O10: =SUM(O7:O9) -> 2437.18 | Q10: =Q7+Q8+Q9 -> 2437.18

Sheet CCom
E2: =PreS!E2 -> Preview Statement - SACOS
E4: Records Found - 3
H6: Line | I6: CNID | J6: Policy Number | K6: Client's Name | L6: Insurer | M6: Grouping | N6: Basic Premium | O6: Rate | P6: Amount Due | Q6: Status | R6: Received | S6: Variance | T6: Reason | U6: Select | X6: Date Due | Y6: Mode | AA6: Date Rcvd | AB6: Stat No
H7: 1 | I7: CN23090 | J7: MPV-23-HEA-P0002132 | K7: Jean Grey | L7: SACOS | M7: Motor | N7: 9875.76 | O7: 0.1 | P7: 740.68 | Q7: Outstanding | R7: =P7/2 -> 370.34 | S7: =P7-R7 -> 370.34 | T7: Instalment | X7: 45316
H8: 2 | I8: CN23085 | J8: HS1-23-P00023132 | K8: Hot Bits | L8: SACOS | M8: General | N8: 5510 | O8: 0.15 | P8: 826.5 | Q8: Outstanding | R8: =P8 -> 826.5 | S8: 0 | X8: 45271
I9: CN23084 | J9: HI-18-P000321 | K9: Relais Des Iles | L9: SACOS | M9: General | N9: 5800 | O9: 0.15 | P9: 870 | Q9: Outstanding | R9: =P9 -> 870 | S9: 0 | X9: 45216
R10: =SUM(R7:R9) -> 2066.84

Sheet LS
E2: Statements
E4: Records Found - 80
F6: Action | G6: Statement No | H6: Statement No | I6: Statement No | J6: Year | K6: Insurer | L6: Business Category | M6: Date Received | N6: Amount Received | O6: Mode Of Payment | P6: Remarks
I7: AG-2403 | J7: 2024 | K7: Alliance | L7: General | M7: 45553 | N7: 2087.74 | O7: Cheque | P7: SEP General Commission
I8: SL-2408 | J8: 2024 | K8: SACOS | L8: Life | M8: 45550 | N8: 5467.6 | O8: Bank Transfer | P8: AUG Life Commission
I9: HL-2408 | J9: 2024 | K9: Hsavy | L9: Life | M9: 45549 | N9: 3457 | O9: Bank Transfer | P9: AUG Life Commission
I10: HG-2403 | J10: 2024 | K10: Alliance | L10: General | M10: 45525 | N10: 10634 | O10: Cheque | P10: AUG General Commission
I11: SG-2404 | J11: 2024 | K11: SACOS | L11: General | M11: 45523 | N11: 6470.4 | O11: Bank Transfer | P11: AUG General Commission
I12: SL-2407 | J12: 2024 | K12: SACOS | L12: Life | M12: 45519 | N12: 17543 | O12: Bank Transfer | P12: JUL Life Commission
I13: HL-2407 | J13: 2024 | K13: Hsavy | L13: Life | M13: 45517 | N13: 2134 | O13: Bank Transfer | P13: JUL Life Commission
I14: SL-2406 | J14: 2024 | K14: SACOS | L14: Life | M14: 45490 | N14: 7411.66 | O14: Bank Transfer | P14: JUN Life Commission
I15: HL-2406 | J15: 2024 | K15: Hsavy | L15: Life | M15: 45487 | N15: 2567.83 | O15: Bank Transfer | P15: JUN Life Commission
I16: SL-2405 | J16: 2024 | K16: SACOS | L16: Life | M16: 45458 | N16: 5003 | O16: Bank Transfer | P16: MAY Life Commission
I17: HL-2405 | J17: 2024 | K17: Hsavy | L17: Life | M17: 45460 | N17: 12671.4 | O17: Bank Transfer | P17: MAY Life Commission
I18: SG-2403 | J18: 2024 | K18: SACOS | L18: General | M18: 45460 | N18: 12671.4 | O18: Bank Transfer | P18: JUN General Commission
... I20: AG-2401 | J20: 2024 | K20: Alliance | L20: General | M20: 45427 | N20: 17899 | O20: Cheque | P20: MAY General Commission

Sheet LSF
E2: Statements - SACOS
E4: Records Found - 60
F6: Action | G6: Statement No | H6: Statement No | I6: Statement No | J6: Year | K6: Insurer | L6: Business Category | M6: Date Received | N6: Amount Received | O6: Mode Of Payment | P6: Remarks
I7: SL-2408 | J7: 2024 | K7: SACOS | L7: Life | M7: 45550 | N7: 5467.6 | O7: Bank Transfer | P7: AUG Life Commission
I8: SG-2404 | J8: 2024 | K8: SACOS | L8: General | M8: 45523 | N8: 6470.4 | O8: Bank Transfer
I9: SL-2407 | J9: 2024 | K9: SACOS | L9: Life | M9: 45519 | N9: 17543 | O9: Bank Transfer | P9: JUL Life Commission
I10: SL-2406 | J10: 2024 | K10: SACOS | L10: Life | M10: 45490 | N10: 7411.66 | O10: Bank Transfer | P10: JUN Life Commission
I11: SL-2405 | J11: 2024 | K11: SACOS | L11: Life | M11: 45458 | N11: 5003 | O11: Bank Transfer | P11: MAY Life Commission
I12: SG-2403 | J12: 2024 | K12: SACOS | L12: General | M12: 45460 | N12: 12671.4 | O12: Bank Transfer
I13: SL-2404 | J13: 2024 | K13: SACOS | L13: Life | M13: 45427 | N13: 9342.65 | O13: Bank Transfer | P13: APR Life Commission
I14: SL-2403 | J14: 2024 | K14: SACOS | L14: Life | M14: 45397 | N14: 10486.77 | O14: Bank Transfer | P14: MAR Life Commission
I15: SG-2402 | J15: 2024 | K15: SACOS | L15: General | M15: 45396 | N15: 4673 | O15: Bank Transfer
I16: SL-2402 | J16: 2024 | K16: SACOS | L16: Life | M16: 45366 | N16: 8654 | O16: Bank Transfer | P16: FEB Life Commission
I17: SL-2401 | J17: 2024 | K17: SACOS | L17: Life | M17: 45337 | N17: 8023.6 | O17: Bank Transfer | P17: JAN Life Commission
I18: SG-2401 | J18: 2024 | K18: SACOS | L18: General | M18: 45334 | N18: 3477 | O18: Bank Transfer
I19: SL-2312 | J19: 2023 | K19: SACOS | L19: Life | M19: 45306 | N19: 8465 | O19: Bank Transfer | P19: DEC Life Commission
I20: SG-2307 | J20: 2023 | K20: SACOS | L20: General | M20: 45277 | N20: 3675.4 | O20: Bank Transfer

Sheet VS
E2: View Statement
E4: Statement No - AG-2403
E5: Commission Statement Summary
E7: Insurer | F7: Alliance | K7: Class | L7: General | P7: Total | Q7: 2074.89 | U7: Date Received | V7: 45563 | X7: Mode | Y7: Bank Transfer | AB7: Chq No | AC7: NOU | AD7: 00000000
E9: Commission Details
E10: CNID | F10: Policy Number | L10: Client Name | Q10: Basic Premium | S10: Rate | T10: Amount Due | V10: Amount Received | X10: Variance | Z10: Variance Reason
E11: CN23061 | F11: MPV-23-HEA-P0002110 | L11: Kendra Moller | Q11: 7356.4 | S11: 0.1 | T11: =Q11*S11 -> 735.64 | V11: =T11 -> 735.64 | X11: =T11-V11 -> 0
E12: CN23059 | F12: FSP-23-HEA-P0002309 | L12: Pierro Leclerk | Q12: 8441 | S12: 0.15 | T12: =Q12*S12 -> 1266.15 | V12: =T12/2 -> 633.075 | X12: =T12-V12 -> 633.075 | Z12: Part commission on instalment
E13: CN23055 | F13: HS1-23-HIN-0000088 | L13: Margo Slater | Q13: 4793.5 | S13: 0.15 | T13: =Q13*S13 -> 719.025 | V13: =T13 -> 719.025 | X13: =T13-V13 -> 0
E20: Documents

Sheet LI
M1: 4
E2: Income
E4: Records Found - 188
F6: Action | G6: IncomeID | H6: Income Source | I6: Date Rcvd | J6: Amount Received | K6: Description | L6: Category | M6: Mode Of Payment | N6: Statement No | O6: Income Notes
G7: IN-24014 | H7: Alliance | I7: 45448 | J7: 3546.77 | K7: Commission | L7: General | M7: Cheque | N7: AG-2405
G8: IN-24013 | H8: Hsavy Life | I8: 45444 | J8: 763.2 | K8: May Commission | L8: Life | M8: Bank Transfer | N8: HL-2406
G9: IN-24012 | H9: SACOS Life | I9: 45414 | J9: 376.22 | K9: Commission | L9: General | M9: Bank Transfer | N9: SL-2405
G10: IN-24011 | H10: SACOS Life | I10: 45416 | J10: 1572.33 | K10: Bonus | L10: Life | M10: Bank Transfer
G11: IN-24010 | H11: SACOS Life | I11: 45410 | J11: 2350 | K11: Life Contest Prize | L11: Life | M11: Bank Transfer
G12: IN-24009 | H12: HSavy General | I12: 45405 | J12: 1652 | K12: Commission | L12: General | M12: Bank Transfer | N12: HG-2404
G13: IN-24008 | H13: SACOS General | I13: 45337 | J13: 13987.4 | K13: Commission | L13: General | M13: Bank Transfer | N13: SG-2402
G14: IN-24007 | H14: Alliance | I14: 45362 | J14: 1976 | K14: Commission | L14: General | M14: Cheque | N14: AG-2403
G15: IN-24006 | H15: SACOS General | I15: 45331 | J15: 2355 | K15: Commission | L15: General | M15: Bank Transfer | N15: SG-2401
G16: IN-24005 | H16: Hsavy Life | I16: 45330 | J16: 12500 | K16: Mar Commission | L16: Life | M16: Bank Transfer | N16: HL-2403
G17: IN-24004 | H17: Alliance | I17: 45327 | J17: 5362 | K17: Commission | L17: General | M17: Cheque | N17: AG-2402
G18: IN-24003 | H18: Hsavy Life | I18: 45354 | J18: 32790 | K18: Feb Commission | L18: Life | M18: Bank Transfer | N18: HL-2402
G19: IN-24002 | H19: SACOS General | I19: 45298 | J19: 42935 | K19: Commission | L19: General | M19: Bank Transfer | N19: SG-2312
G20: IN-24001 | H20: Hsavy Life | I20: 45347 | J20: 53080 | K20: Jan Commission | L20: Life | M20: Bank Transfer | N20: HL-2401

Sheet AI
N1: 4
E2: Income
E4: Records Found - 198
H6: IncomeID | I6: Income Source | J6: Date Rcvd | K6: Amount Received | L6: Description | M6: Category | N6: Mode | O6: Bank | P6: Cheque No | Q6: Statement No
H7: IN24-014 | I7: Alliance | J7: 45448 | K7: 3546.77 | L7: Commission | M7: General | N7: Cheque | O7: BOB | P7: 0065674 | Q7: AG24-05
H8: IN24-013 | I8: Hsavy Life | J8: 45444 | K8: 763.2 | L8: May Commission | M8: Life | N8: Bank Transfer | Q8: HL24-06
H9: IN24-012 | I9: SACOS Life | J9: 45414 | K9: 376.22 | L9: Commission | M9: General | N9: Bank Transfer | Q9: SL24-05
H10: IN24-011 | I10: SACOS Life | J10: 45416 | K10: 1572.33 | L10: Bonus | M10: Life | N10: Bank Transfer
H11: IN24-010 | I11: SACOS Life | J11: 45410 | K11: 2350 | L11: Life Contest Prize | M11: Life | N11: Bank Transfer
H12: IN24-009 | I12: HSavy General | J12: 45405 | K12: 1652 | L12: Commission | M12: General | N12: Bank Transfer | Q12: HG24-04
H13: IN24-008 | I13: SACOS General | J13: 45337 | K13: 13987.4 | L13: Commission | M13: General | N13: Bank Transfer | Q13: SG24-02
H14: IN24-007 | I14: Alliance | J14: 45362 | K14: 1976 | L14: Commission | M14: General | N14: Cheque | O14: BOB | P14: 006543 | Q14: AG24-03
H15: IN24-006 | I15: SACOS General | J15: 45331 | K15: 2355 | L15: Commission | M15: General | N15: Bank Transfer | Q15: SG24-01
H16: IN24-005 | I16: Hsavy Life | J16: 45330 | K16: 12500 | L16: Mar Commission | M16: Life | N16: Bank Transfer | Q16: HL24-03
H17: IN24-004 | I17: Alliance | J17: 45327 | K17: 5362 | L17: Commission | M17: General | N17: Cheque | O17: BOB | P17: 006501 | Q17: AG24-02
H18: IN24-003 | I18: Hsavy Life | J18: 45354 | K18: 32790 | L18: Feb Commission | M18: Life | N18: Bank Transfer | Q18: HL24-02
H19: IN24-002 | I19: SACOS General | J19: 45298 | K19: 42935 | L19: Commission | M19: General | N19: Bank Transfer | Q19: SG23-12
H20: IN24-001 | I20: Hsavy Life | J20: 45347 | K20: 53080 | L20: Jan Commission | M20: Life | N20: Bank Transfer | Q20: HL24-01
H21: IN23-023 | I21: SACOS General | J21: 45280 | K21: 63225 | L21: Commission | M21: General | N21: Bank Transfer | Q21: SG23-11

Sheet LE
E2: Expenses
E4: Records Found - 218
F6: Action | G6: Expense ID | H6: Payee | I6: Date Paid | J6: Amount Paid | K6: Description | L6: Category | M6: Mode Of Payment | N6: Expense Notes
G7: EX-24035 | H7: Alliance | I7: 45463 | J7: 6943.77 | K7: PI Insurance | L7: Insurance | M7: Cheque
G8: EX-24034 | H8: Seychelles Revenue Commission | I8: 45461 | J8: 3425.5 | K8: 2023 Tax Return | L8: Tax | M8: Cheque
G9: EX-24033 | H9: Cable & Wireless | I9: 45458 | J9: 1987.33 | K9: May 2024 Bill | L9: Telecoms | M9: Card
G10: EX-24032 | H10: Registrar | I10: 45458 | J10: 500 | K10: Annual Company Fee | L10: Legal | M10: Cash
G11: EX-24031 | H11: Seychelles Postal Services | I11: 45455 | J11: 1500 | K11: P.O Box rental | L11: Fees | M11: Cheque
G12: EX-24030 | H12: Nouvobanq | I12: 45444 | J12: 20 | K12: Service Fee | L12: Bank charges | M12: Bank Debit
G13: EX-24029 | H13: Alpha Energy | I13: 45437 | J13: 500 | K13: Fuel | L13: Transport | M13: Cash
G14: EX-24028 | H14: Paradise Computers | I14: 45423 | J14: 1976 | K14: Toner | L14: Office Supplies | M14: Card
G15: EX-24027 | H15: Excell Printing | I15: 45421 | J15: 2355 | K15: 400 Flyers | L15: Marketing | M15: Cheque
G16: EX-24026 | H16: FSA | I16: 45420 | J16: 12500 | K16: Broker License Fee 2024 | L16: License Fee | M16: Bank Transfer
G17: EX-24025 | H17: Excell Printing | I17: 45419 | J17: 22645 | K17: 401 Flyers | L17: Marketing | M17: Cheque
G18: EX-24024 | H18: FSA | I18: 45418 | J18: 32790 | K18: Broker License Fee 2025 | L18: License Fee | M18: Bank Transfer
... G20: EX-24022 | H20: FSA | I20: 45416 | J20: 53080 | K20: Broker License Fee 2026 | L20: License Fee | M20: Bank Transfer

Sheet AE
E2: Expenses
E4: Records 1 to 15 of 216
H6: Expense ID | I6: Payee | J6: Date Paid | K6: Amount Paid | L6: Description | M6: Category | N6: Mode | O6: Bank | P6: Cheq No | Q6: Expense Notes | T6: Receipt No
H7: EX24-0057 | I7: Alliance | J7: 45463 | K7: 6943.77 | L7: PI Insurance | M7: Insurance | N7: Cheque | O7: NOU | P7: 00034
H8: EX24-0056 | I8: Seychelles Revenue Commission | J8: 45461 | K8: 3425.5 | L8: 2023 Tax Return | M8: Tax | N8: Cheque | O8: NOU | P8: 00033
H9: EX24-0055 | I9: Cable & Wireless | J9: 45458 | K9: 1987.33 | L9: May 2024 Bill | M9: Telecoms | N9: Card
H10: EX24-0054 | I10: Registrar | J10: 45458 | K10: 500 | L10: Annual Company Fee | M10: Legal | N10: Cash
H11: EX24-0053 | I11: Seychelles Postal Services | J11: 45455 | K11: 1500 | L11: P.O Box rental | M11: Fees | N11: Cheque | O11: NOU | P11: 00032
H12: EX24-0052 | I12: Nouvobanq | J12: 45444 | K12: 20 | L12: Service Fee | M12: Bank charges | N12: Bank Debit
